Workbook

Sheet Screener
A1: Screener: one row per stock per trading day (join key ISIN + Date)
A2: Real data. Trading date: 01-Oct-2026. Generated 06-Oct-2026.
A4: Identity | G4: Red flags | J4: Weakness | L4: Price | Q4: Volume | Z4: Delivery | AG4: Activity | AH4: Deals | AJ4: F&O | AN4: Factors | AT4: Scans | AY4: Output | BB4: Price band | BC4: Surveillance watch | BE4: Corporate action | BF4: Buy checks | BH4: Returns | BN4: Trend | BV4: Selection
A5: Date | B5: Symbol | C5: ISIN | D5: Industry | E5: NSE Index | F5: Market cap (cr) | G5: Red flag | H5: Red flag reason | I5: No intraday | J5: Weakness list | K5: Weakness reason | L5: Close | M5: Chg % (vs previous close) | N5: Rank Gainer/Loser (of universe) | O5: NSE Top 20 Gainers/Losers | P5: 52-wk status | Q5: Volume (lakh) | R5: Avg volume, 20-day (lakh) | S5: Volume vs 20-day avg (x) | T5: Volume vs 50-day avg (x) | U5: Volume vs 100-day avg (x) | V5: Volume build-up (x) | W5: Volume active days (of 20) | X5: Rank volume spike | Y5: NSE Most Active (Top 20) | Z5: Delivery % | AA5: Delivery % vs 20-day avg (x) | AB5: Delivery % vs 50-day avg (x) | AC5: Delivered qty vs 20-day avg (x) | AD5: Delivered qty vs 50-day avg (x) | AE5: Delivered qty vs 100-day avg (x) | AF5: Delivery share trend (x) | AG5: Activity stage | AH5: Bulk deal net qty | AI5: Block deal buy qty | AJ5: Traded in F&O | AK5: % chg in open interest | AL5: OI signal | AM5: Rank F&O activity | AN5: Momentum indices | AO5: Momentum index count (of 7) | AP5: Own momentum score | AQ5: Own momentum percentile (of universe) | AR5: FPI 150 member | AS5: Industry strength vs Nifty, 20-day (%) | AT5: Breakout | AU5: Accumulation | AV5: Institutional buying | AW5: Long buildup | AX5: Momentum leader | AY5: Buy scans passed (count) | AZ5: Scans passed (buy-side) | BA5: Why ranked here | BB5: Price band hit today | BC5: Surveillance watch | BD5: Surveillance watch reason | BE5: Split/bonus (recent) | BF5: Liquidity (>= 1 lakh) | BG5: Market cap (> 500 cr) | BH5: % change from 52-week high/low | BI5: Return 1 week (%) | BJ5: Return 1 month (%) | BK5: Return 3 months (%) | BL5: Return 6 months (%) | BM5: Return 12 months (%) | BN5: Close vs EMA 20 (%) | BO5: Close vs EMA 50 (%) | BP5: Close vs EMA 100 (%) | BQ5: Close vs EMA 200 (%) | BR5: EMA trend | BS5: EMA 20/50 cross | BT5: RSI (9) | BU5: EMA pullback bounce | BV5: Selection score (of 10) | BW5: Rank buy scans
A6: 46296 | B6: RELIANCE | C6: INE002A01018 | D6: Oil Gas & Consumable Fuels | E6: Nifty 50 | F6: 1580195 | G6: N | I6: N | J6: =IF(K6="","N","Y") | K6: =_xlfn.TEXTJOIN("; ",TRUE,IF(P6="52-wk low","52-wk low",""),IF(AND(AD6>=Settings!$B$12,M6<0),"Distribution",""),IF(AND(AJ6="Y",M6<0,AK6<-Settings!$B$13),"Long unwinding",""),IF(AND(AJ6="Y",M6<0,AK6>Settings!$B$13),"Short buildup","")) | L6: 1167.7 | M6: -1.63 | N6: 1420 | O6: None | P6: 52-wk low | Q6: 167.71 | R6: 123.35 | S6: 1.38 | T6: 1.47 | U6: 1.24 | V6: 0.91 | W6: 6 | X6: 220 | Y6: By value | Z6: 61.24 | AA6: 0.97 | AB6: 1 | AC6: 1.32 | AD6: 1.44 | AE6: 1.34 | AF6: 1.12 | AG6: Normal | AH6: 0 | AI6: 0 | AJ6: Y | AK6: 1.6 | AL6: Short buildup | AM6: 5 | AN6: None | AO6: 0 | AP6: 0.52 | AQ6: 8 | AR6: Y | AS6: 2.69 | AT6: =IF(AND(P6="52-wk high",T6>=Settings!$B$7),"Y","N") | AU6: =IF(AND(AD6>=Settings!$B$8,M6>0),"Y","N") | AV6: =IF(OR(AH6>Settings!$B$9,AI6>Settings!$B$9),"Y","N") | AW6: =IF(AJ6<>"Y","n/a",IF(AND(M6>0,AK6>Settings!$B$10),"Y","N")) | AX6: =IF(AO6>=Settings!$B$11,"Y","N") | AY6: =(AT6="Y")+(AU6="Y")+(AV6="Y")+(AW6="Y")+(AX6="Y") | AZ6: =IF(AY6=0,"None",_xlfn.TEXTJOIN(", ",TRUE(),IF(AT6="Y","Breakout",""),IF(AU6="Y","Accumulation",""),IF(AV6="Y","Institutional buying",""),IF(AW6="Y","Long buildup",""),IF(AX6="Y","Momentum leader",""))) | BA6: =IF(BW6="","","Passes "&AY6&" of 5 buy-side scans"&IF(G6="Y","; RED FLAG: filter out using Red flag column","")) | BB6: None | BC6: N | BF6: =IF(R6*100000>=Settings!$B$5,"Y","N") | BG6: =IF(F6>Settings!$B$6,"Y","N") | BH6: -27.55 | BI6: -4.22 | BJ6: -10.79 | BK6: -10.73 | BL6: -14.72 | BM6: -14.69 | BN6: -5.4 | BO6: -7.98 | BP6: -10.13 | BQ6: -12.67 | BR6: Stacked down | BS6: None | BT6: 23.8 | BU6: N | BV6: =IF(OR(BF6<>"Y",BG6<>"Y"),"",(AND(ISNUMBER(BQ6),BQ6>0))+(BR6="Stacked up")+(AND(ISNUMBER(BH6),BH6>=-Settings!$B$17))+(AND(ISNUMBER(BK6),ISNUMBER(BM6),BK6>0,BM6>0))+(AND(ISNUMBER(AQ6),AQ6>=Settings!$B$18))+(AND(ISNUMBER(BT6),BT6>=Settings!$B$19,BT6<=Settings!$B$20))+(AND(ISNUMBER(AS6),AS6>0))+(AND(ISNUMBER(T6),ISNUMBER(M6),T6>=Settings!$B$21,M6>0))+(AND(ISNUMBER(AD6),ISNUMBER(M6),AD6>=Settings!$B$22,M6>0))+(AY6>=1)) | BW6: =IF(OR(AY6=0,BF6<>"Y",BG6<>"Y"),"",1+SUMPRODUCT(($A$6:$A$2604=A6)*($AY$6:$AY$2604>0)*($BF$6:$BF$2604="Y")*($BG$6:$BG$2604="Y")*(($AY$6:$AY$2604>AY6)+($AY$6:$AY$2604=AY6)*($AD$6:$AD$2604>AD6))))
A7: 46296 | B7: HDFCBANK | C7: INE040A01034 | D7: Financial Services | E7: Nifty 50 | F7: 1111852 | G7: N | I7: N | J7: =IF(K7="","N","Y") | K7: =_xlfn.TEXTJOIN("; ",TRUE,IF(P7="52-wk low","52-wk low",""),IF(AND(AD7>=Settings!$B$12,M7<0),"Distribution",""),IF(AND(AJ7="Y",M7<0,AK7<-Settings!$B$13),"Long unwinding",""),IF(AND(AJ7="Y",M7<0,AK7>Settings!$B$13),"Short buildup","")) | L7: 721.2 | M7: 1.76 | N7: 216 | O7: None | P7: None | Q7: 373.9 | R7: 297.8 | S7: 1.26 | T7: 1.29 | U7: 1.13 | V7: 0.9 | W7: 8 | X7: 258 | Y7: Both | Z7: 63.31 | AA7: 1.02 | AB7: 1.01 | AC7: 1.28 | AD7: 1.32 | AE7: 1.2 | AF7: 1.04 | AG7: Normal | AH7: 0 | AI7: 0 | AJ7: Y | AK7: -1.28 | AL7: Short covering | AM7: 3 | AN7: None | AO7: 0 | AP7: 0.55 | AQ7: 11 | AR7: Y | AS7: 0.6 | AT7: =IF(AND(P7="52-wk high",T7>=Settings!$B$7),"Y","N") | AU7: =IF(AND(AD7>=Settings!$B$8,M7>0),"Y","N") | AV7: =IF(OR(AH7>Settings!$B$9,AI7>Settings!$B$9),"Y","N") | AW7: =IF(AJ7<>"Y","n/a",IF(AND(M7>0,AK7>Settings!$B$10),"Y","N")) | AX7: =IF(AO7>=Settings!$B$11,"Y","N") | AY7: =(AT7="Y")+(AU7="Y")+(AV7="Y")+(AW7="Y")+(AX7="Y") | AZ7: =IF(AY7=0,"None",_xlfn.TEXTJOIN(", ",TRUE(),IF(AT7="Y","Breakout",""),IF(AU7="Y","Accumulation",""),IF(AV7="Y","Institutional buying",""),IF(AW7="Y","Long buildup",""),IF(AX7="Y","Momentum leader",""))) | BA7: =IF(BW7="","","Passes "&AY7&" of 5 buy-side scans"&IF(G7="Y","; RED FLAG: filter out using Red flag column","")) | BB7: None | BC7: N | BF7: =IF(R7*100000>=Settings!$B$5,"Y","N") | BG7: =IF(F7>Settings!$B$6,"Y","N") | BH7: -29.33 | BI7: -1.06 | BJ7: 1.31 | BK7: -9.41 | BL7: -2.84 | BM7: -25.28 | BN7: -0.08 | BO7: -1.41 | BP7: -4.58 | BQ7: -10.11 | BR7: Stacked down | BS7: None | BT7: 49.6 | BU7: N | BV7: =IF(OR(BF7<>"Y",BG7<>"Y"),"",(AND(ISNUMBER(BQ7),BQ7>0))+(BR7="Stacked up")+(AND(ISNUMBER(BH7),BH7>=-Settings!$B$17))+(AND(ISNUMBER(BK7),ISNUMBER(BM7),BK7>0,BM7>0))+(AND(ISNUMBER(AQ7),AQ7>=Settings!$B$18))+(AND(ISNUMBER(BT7),BT7>=Settings!$B$19,BT7<=Settings!$B$20))+(AND(ISNUMBER(AS7),AS7>0))+(AND(ISNUMBER(T7),ISNUMBER(M7),T7>=Settings!$B$21,M7>0))+(AND(ISNUMBER(AD7),ISNUMBER(M7),AD7>=Settings!$B$22,M7>0))+(AY7>=1)) | BW7: =IF(OR(AY7=0,BF7<>"Y",BG7<>"Y"),"",1+SUMPRODUCT(($A$6:$A$2604=A7)*($AY$6:$AY$2604>0)*($BF$6:$BF$2604="Y")*($BG$6:$BG$2604="Y")*(($AY$6:$AY$2604>AY7)+($AY$6:$AY$2604=AY7)*($AD$6:$AD$2604>AD7))))
A8: 46296 | B8: BHARTIARTL | C8: INE397D01024 | D8: Telecommunication | E8: Nifty 50 | F8: 1086534 | G8: N | I8: N | J8: =IF(K8="","N","Y") | K8: =_xlfn.TEXTJOIN("; ",TRUE,IF(P8="52-wk low","52-wk low",""),IF(AND(AD8>=Settings!$B$12,M8<0),"Distribution",""),IF(AND(AJ8="Y",M8<0,AK8<-Settings!$B$13),"Long unwinding",""),IF(AND(AJ8="Y",M8<0,AK8>Settings!$B$13),"Short buildup","")) | L8: 1741.1 | M8: -0.9 | N8: 987 | O8: None | P8: 52-wk low | Q8: 56.1 | R8: 56.21 | S8: 1.01 | T8: 0.89 | U8: 0.75 | V8: 0.77 | W8: 4 | Y8: By value | Z8: 63.89 | AA8: 0.91 | AB8: 0.93 | AC8: 0.9 | AD8: 0.83 | AE8: 0.73 | AF8: 1.08 | AG8: Normal | AH8: 0 | AI8: 0 | AJ8: Y | AK8: -0.69 | AL8: Long unwinding | AM8: 20 | AN8: None | AO8: 0 | AP8: 0.7 | AQ8: 38 | AR8: Y | AS8: 2.57 | AT8: =IF(AND(P8="52-wk high",T8>=Settings!$B$7),"Y","N") | AU8: =IF(AND(AD8>=Settings!$B$8,M8>0),"Y","N") | AV8: =IF(OR(AH8>Settings!$B$9,AI8>Settings!$B$9),"Y","N") | AW8: =IF(AJ8<>"Y","n/a",IF(AND(M8>0,AK8>Settings!$B$10),"Y","N")) | AX8: =IF(AO8>=Settings!$B$11,"Y","N") | AY8: =(AT8="Y")+(AU8="Y")+(AV8="Y")+(AW8="Y")+(AX8="Y") | AZ8: =IF(AY8=0,"None",_xlfn.TEXTJOIN(", ",TRUE(),IF(AT8="Y","Breakout",""),IF(AU8="Y","Accumulation",""),IF(AV8="Y","Institutional buying",""),IF(AW8="Y","Long buildup",""),IF(AX8="Y","Momentum leader",""))) | BA8: =IF(BW8="","","Passes "&AY8&" of 5 buy-side scans"&IF(G8="Y","; RED FLAG: filter out using Red flag column","")) | BB8: None | BC8: N | BF8: =IF(R8*100000>=Settings!$B$5,"Y","N") | BG8: =IF(F8>Settings!$B$6,"Y","N") | BH8: -19.93 | BI8: -3.05 | BJ8: -7.25 | BK8: -6.94 | BL8: -2.29 | BM8: -6.77 | BN8: -4.13 | BO8: -6.23 | BP8: -7.22 | BQ8: -8.34 | BR8: Stacked down | BS8: None | BT8: 27.4 | BU8: N | BV8: =IF(OR(BF8<>"Y",BG8<>"Y"),"",(AND(ISNUMBER(BQ8),BQ8>0))+(BR8="Stacked up")+(AND(ISNUMBER(BH8),BH8>=-Settings!$B$17))+(AND(ISNUMBER(BK8),ISNUMBER(BM8),BK8>0,BM8>0))+(AND(ISNUMBER(AQ8),AQ8>=Settings!$B$18))+(AND(ISNUMBER(BT8),BT8>=Settings!$B$19,BT8<=Settings!$B$20))+(AND(ISNUMBER(AS8),AS8>0))+(AND(ISNUMBER(T8),ISNUMBER(M8),T8>=Settings!$B$21,M8>0))+(AND(ISNUMBER(AD8),ISNUMBER(M8),AD8>=Settings!$B$22,M8>0))+(AY8>=1)) | BW8: =IF(OR(AY8=0,BF8<>"Y",BG8<>"Y"),"",1+SUMPRODUCT(($A$6:$A$2604=A8)*($AY$6:$AY$2604>0)*($BF$6:$BF$2604="Y")*($BG$6:$BG$2604="Y")*(($AY$6:$AY$2604>AY8)+($AY$6:$AY$2604=AY8)*($AD$6:$AD$2604>AD8))))
A9: 46296 | B9: ICICIBANK | C9: INE090A01021 | D9: Financial Services | E9: Nifty 50 | F9: 940809 | G9: N | I9: N | J9: =IF(K9="","N","Y") | K9: =_xlfn.TEXTJOIN("; ",TRUE,IF(P9="52-wk low","52-wk low",""),IF(AND(AD9>=Settings!$B$12,M9<0),"Distribution",""),IF(AND(AJ9="Y",M9<0,AK9<-Settings!$B$13),"Long unwinding",""),IF(AND(AJ9="Y",M9<0,AK9>Settings!$B$13),"Short buildup","")) | L9: 1310.6 | M9: -0.84 | N9: 951 | O9: None | P9: None | Q9: 131.63 | R9: 94.58 | S9: 1.43 | T9: 1.34 | U9: 1.03 | V9: 0.74 | W9: 4 | X9: 238 | Y9: By value | Z9: 57.07 | AA9: 0.88 | AB9: 0.92 | AC9: 1.25 | AD9: 1.23 | AE9: 0.97 | AF9: 1.07 | AG9: Normal | AH9: 0 | AI9: 0 | AJ9: Y | AK9: 0.06 | AL9: Short buildup | AM9: 6 | AN9: None | AO9: 0 | AP9: 0.91 | AQ9: 57 | AR9: Y | AS9: 0.6 | AT9: =IF(AND(P9="52-wk high",T9>=Settings!$B$7),"Y","N") | AU9: =IF(AND(AD9>=Settings!$B$8,M9>0),"Y","N") | AV9: =IF(OR(AH9>Settings!$B$9,AI9>Settings!$B$9),"Y","N") | AW9: =IF(AJ9<>"Y","n/a",IF(AND(M9>0,AK9>Settings!$B$10),"Y","N")) | AX9: =IF(AO9>=Settings!$B$11,"Y","N") | AY9: =(AT9="Y")+(AU9="Y")+(AV9="Y")+(AW9="Y")+(AX9="Y") | AZ9: =IF(AY9=0,"None",_xlfn.TEXTJOIN(", ",TRUE(),IF(AT9="Y","Breakout",""),IF(AU9="Y","Accumulation",""),IF(AV9="Y","Institutional buying",""),IF(AW9="Y","Long buildup",""),IF(AX9="Y","Momentum leader",""))) | BA9: =IF(BW9="","","Passes "&AY9&" of 5 buy-side scans"&IF(G9="Y","; RED FLAG: filter out using Red flag column","")) | BB9: None | BC9: N | BF9: =IF(R9*100000>=Settings!$B$5,"Y","N") | BG9: =IF(F9>Settings!$B$6,"Y","N") | BH9: -11.45 | BI9: -1.79 | BJ9: -8.86 | BK9: -5.02 | BL9: 8.07 | BM9: -4.48 | BN9: -2.89 | BO9: -4.73 | BP9: -4.51 | BQ9: -4.01 | BR9: Mixed | BS9: None | BT9: 33.5 | BU9: N | BV9: =IF(OR(BF9<>"Y",BG9<>"Y"),"",(AND(ISNUMBER(BQ9),BQ9>0))+(BR9="Stacked up")+(AND(ISNUMBER(BH9),BH9>=-Settings!$B$17))+(AND(ISNUMBER(BK9),ISNUMBER(BM9),BK9>0,BM9>0))+(AND(ISNUMBER(AQ9),AQ9>=Settings!$B$18))+(AND(ISNUMBER(BT9),BT9>=Settings!$B$19,BT9<=Settings!$B$20))+(AND(ISNUMBER(AS9),AS9>0))+(AND(ISNUMBER(T9),ISNUMBER(M9),T9>=Settings!$B$21,M9>0))+(AND(ISNUMBER(AD9),ISNUMBER(M9),AD9>=Settings!$B$22,M9>0))+(AY9>=1)) | BW9: =IF(OR(AY9=0,BF9<>"Y",BG9<>"Y"),"",1+SUMPRODUCT(($A$6:$A$2604=A9)*($AY$6:$AY$2604>0)*($BF$6:$BF$2604="Y")*($BG$6:$BG$2604="Y")*(($AY$6:$AY$2604>AY9)+($AY$6:$AY$2604=AY9)*($AD$6:$AD$2604>AD9))))
A10: 46296 | B10: SBIN | C10: INE062A01020 | D10: Financial Services | E10: Nifty 50 | F10: 880707 | G10: N | I10: N | J10: =IF(K10="","N","Y") | K10: =_xlfn.TEXTJOIN("; ",TRUE,IF(P10="52-wk low","52-wk low",""),IF(AND(AD10>=Settings!$B$12,M10<0),"Distribution",""),IF(AND(AJ10="Y",M10<0,AK10<-Settings!$B$13),"Long unwinding",""),IF(AND(AJ10="Y",M10<0,AK10>Settings!$B$13),"Short buildup","")) | L10: 954.1 | M10: -0.56 | N10: 816 | O10: None | P10: None | Q10: 73.9 | R10: 84.23 | S10: 0.85 | T10: 0.81 | U10: 0.63 | V10: 0.75 | W10: 2 | Y10: None | Z10: 50.73 | AA10: 0.88 | AB10: 0.93 | AC10: 0.7 | AD10: 0.75 | AE10: 0.6 | AF10: 1.12 | AG10: Normal | AH10: 0 | AI10: 0 | AJ10: Y | AK10: -0.09 | AL10: Long unwinding | AM10: 19 | AN10: None | AO10: 0 | AP10: 0.86 | AQ10: 54 | AR10: Y | AS10: 0.6 | AT10: =IF(AND(P10="52-wk high",T10>=Settings!$B$7),"Y","N") | AU10: =IF(AND(AD10>=Settings!$B$8,M10>0),"Y","N") | AV10: =IF(OR(AH10>Settings!$B$9,AI10>Settings!$B$9),"Y","N") | AW10: =IF(AJ10<>"Y","n/a",IF(AND(M10>0,AK10>Settings!$B$10),"Y","N")) | AX10: =IF(AO10>=Settings!$B$11,"Y","N") | AY10: =(AT10="Y")+(AU10="Y")+(AV10="Y")+(AW10="Y")+(AX10="Y") | AZ10: =IF(AY10=0,"None",_xlfn.TEXTJOIN(", ",TRUE(),IF(AT10="Y","Breakout",""),IF(AU10="Y","Accumulation",""),IF(AV10="Y","Institutional buying",""),IF(AW10="Y","Long buildup",""),IF(AX10="Y","Momentum leader",""))) | BA10: =IF(BW10="","","Passes "&AY10&" of 5 buy-side scans"&IF(G10="Y","; RED FLAG: filter out using Red flag column","")) | BB10: None | BC10: N | BF10: =IF(R10*100000>=Settings!$B$5,"Y","N") | BG10: =IF(F10>Settings!$B$6,"Y","N") | BH10: -22.73 | BI10: -2.49 | BJ10: -7.77 | BK10: -8.91 | BL10: -6.26 | BM10: 10.42 | BN10: -3.52 | BO10: -5.63 | BP10: -6.55 | BQ10: -5.81 | BR10: Mixed | BS10: None | BT10: 28.5 | BU10: N | BV10: =IF(OR(BF10<>"Y",BG10<>"Y"),"",(AND(ISNUMBER(BQ10),BQ10>0))+(BR10="Stacked up")+(AND(ISNUMBER(BH10),BH10>=-Settings!$B$17))+(AND(ISNUMBER(BK10),ISNUMBER(BM10),BK10>0,BM10>0))+(AND(ISNUMBER(AQ10),AQ10>=Settings!$B$18))+(AND(ISNUMBER(BT10),BT10>=Settings!$B$19,BT10<=Settings!$B$20))+(AND(ISNUMBER(AS10),AS10>0))+(AND(ISNUMBER(T10),ISNUMBER(M10),T10>=Settings!$B$21,M10>0))+(AND(ISNUMBER(AD10),ISNUMBER(M10),AD10>=Settings!$B$22,M10>0))+(AY10>=1)) | BW10: =IF(OR(AY10=0,BF10<>"Y",BG10<>"Y"),"",1+SUMPRODUCT(($A$6:$A$2604=A10)*($AY$6:$AY$2604>0)*($BF$6:$BF$2604="Y")*($BG$6:$BG$2604="Y")*(($AY$6:$AY$2604>AY10)+($AY$6:$AY$2604=AY10)*($AD$6:$AD$2604>AD10))))
A11: 46296 | B11: TCS | C11: INE467B01029 | D11: Information Technology | E11: Nifty 50 | F11: 750753 | G11: N | I11: N | J11: =IF(K11="","N","Y") | K11: =_xlfn.TEXTJOIN("; ",TRUE,IF(P11="52-wk low","52-wk low",""),IF(AND(AD11>=Settings!$B$12,M11<0),"Distribution",""),IF(AND(AJ11="Y",M11<0,AK11<-Settings!$B$13),"Long unwinding",""),IF(AND(AJ11="Y",M11<0,AK11>Settings!$B$13),"Short buildup","")) | L11: 2075 | M11: 1.19 | N11: 300 | O11: None | P11: None | Q11: 34.29 | R11: 31.51 | S11: 1.1 | T11: 1.08 | U11: 0.8 | V11: 0.74 | W11: 3 | Y11: None | Z11: 54.9 | AA11: 1.1 | AB11: 1.12 | AC11: 1.2 | AD11: 1.2 | AE11: 0.9 | AF11: 1.04 | AG11: Normal | AH11: 0 | AI11: 0 | AJ11: Y | AK11: 1.83 | AL11: Long buildup | AM11: 14 | AN11: None | AO11: 0 | AP11: 0.52 | AQ11: 7 | AR11: Y | AS11: -0.75 | AT11: =IF(AND(P11="52-wk high",T11>=Settings!$B$7),"Y","N") | AU11: =IF(AND(AD11>=Settings!$B$8,M11>0),"Y","N") | AV11: =IF(OR(AH11>Settings!$B$9,AI11>Settings!$B$9),"Y","N") | AW11: =IF(AJ11<>"Y","n/a",IF(AND(M11>0,AK11>Settings!$B$10),"Y","N")) | AX11: =IF(AO11>=Settings!$B$11,"Y","N") | AY11: =(AT11="Y")+(AU11="Y")+(AV11="Y")+(AW11="Y")+(AX11="Y") | AZ11: =IF(AY11=0,"None",_xlfn.TEXTJOIN(", ",TRUE(),IF(AT11="Y","Breakout",""),IF(AU11="Y","Accumulation",""),IF(AV11="Y","Institutional buying",""),IF(AW11="Y","Long buildup",""),IF(AX11="Y","Momentum leader",""))) | BA11: =IF(BW11="","","Passes "&AY11&" of 5 buy-side scans"&IF(G11="Y","; RED FLAG: filter out using Red flag column","")) | BB11: None | BC11: N | BF11: =IF(R11*100000>=Settings!$B$5,"Y","N") | BG11: =IF(F11>Settings!$B$6,"Y","N") | BH11: -38.06 | BI11: -0.57 | BJ11: -12.41 | BK11: 4.66 | BL11: -13.84 | BM11: -28.8 | BN11: -3.31 | BO11: -6.39 | BP11: -9.44 | BQ11: -15.48 | BR11: Stacked down | BS11: None | BT11: 35.4 | BU11: N | BV11: =IF(OR(BF11<>"Y",BG11<>"Y"),"",(AND(ISNUMBER(BQ11),BQ11>0))+(BR11="Stacked up")+(AND(ISNUMBER(BH11),BH11>=-Settings!$B$17))+(AND(ISNUMBER(BK11),ISNUMBER(BM11),BK11>0,BM11>0))+(AND(ISNUMBER(AQ11),AQ11>=Settings!$B$18))+(AND(ISNUMBER(BT11),BT11>=Settings!$B$19,BT11<=Settings!$B$20))+(AND(ISNUMBER(AS11),AS11>0))+(AND(ISNUMBER(T11),ISNUMBER(M11),T11>=Settings!$B$21,M11>0))+(AND(ISNUMBER(AD11),ISNUMBER(M11),AD11>=Settings!$B$22,M11>0))+(AY11>=1)) | BW11: =IF(OR(AY11=0,BF11<>"Y",BG11<>"Y"),"",1+SUMPRODUCT(($A$6:$A$2604=A11)*($AY$6:$AY$2604>0)*($BF$6:$BF$2604="Y")*($BG$6:$BG$2604="Y")*(($AY$6:$AY$2604>AY11)+($AY$6:$AY$2604=AY11)*($AD$6:$AD$2604>AD11))))
A12: 46296 | B12: BAJFINANCE | C12: INE296A01032 | D12: Financial Services | E12: Nifty 50 | F12: 590407 | G12: N | I12: N | J12: =IF(K12="","N","Y") | K12: =_xlfn.TEXTJOIN("; ",TRUE,IF(P12="52-wk low","52-wk low",""),IF(AND(AD12>=Settings!$B$12,M12<0),"Distribution",""),IF(AND(AJ12="Y",M12<0,AK12<-Settings!$B$13),"Long unwinding",""),IF(AND(AJ12="Y",M12<0,AK12>Settings!$B$13),"Short buildup","")) | L12: 948.3 | M12: -1.16 | N12: 1124 | O12: None | P12: None | Q12: 56.99 | R12: 63.1 | S12: 0.9 | T12: 0.8 | U12: 0.69 | V12: 0.76 | W12: 4 | Y12: None | Z12: 59.38 | AA12: 0.9 | AB12: 0.93 | AC12: 0.83 | AD12: 0.75 | AE12: 0.67 | AF12: 1.05 | AG12: Normal | AH12: 0 | AI12: 0 | AJ12: Y | AK12: 1.56 | AL12: Short buildup | AM12: 21 | AN12: None | AO12: 0 | AP12: 1 | AQ12: 62 | AR12: Y | AS12: 0.6 | AT12: =IF(AND(P12="52-wk high",T12>=Settings!$B$7),"Y","N") | AU12: =IF(AND(AD12>=Settings!$B$8,M12>0),"Y","N") | AV12: =IF(OR(AH12>Settings!$B$9,AI12>Settings!$B$9),"Y","N") | AW12: =IF(AJ12<>"Y","n/a",IF(AND(M12>0,AK12>Settings!$B$10),"Y","N")) | AX12: =IF(AO12>=Settings!$B$11,"Y","N") | AY12: =(AT12="Y")+(AU12="Y")+(AV12="Y")+(AW12="Y")+(AX12="Y") | AZ12: =IF(AY12=0,"None",_xlfn.TEXTJOIN(", ",TRUE(),IF(AT12="Y","Breakout",""),IF(AU12="Y","Accumulation",""),IF(AV12="Y","Institutional buying",""),IF(AW12="Y","Long buildup",""),IF(AX12="Y","Momentum leader",""))) | BA12: =IF(BW12="","","Passes "&AY12&" of 5 buy-side scans"&IF(G12="Y","; RED FLAG: filter out using Red flag column","")) | BB12: None | BC12: N | BF12: =IF(R12*100000>=Settings!$B$5,"Y","N") | BG12: =IF(F12>Settings!$B$6,"Y","N") | BH12: -19.39 | BI12: -3.43 | BJ12: -10.02 | BK12: -6.56 | BL12: 16.03 | BM12: -3.99 | BN12: -6.14 | BO12: -7.88 | BP12: -6.74 | BQ12: -5.42 | BR12: Mixed | BS12: None | BT12: 28.7 | BU12: N | BV12: =IF(OR(BF12<>"Y",BG12<>"Y"),"",(AND(ISNUMBER(BQ12),BQ12>0))+(BR12="Stacked up")+(AND(ISNUMBER(BH12),BH12>=-Settings!$B$17))+(AND(ISNUMBER(BK12),ISNUMBER(BM12),BK12>0,BM12>0))+(AND(ISNUMBER(AQ12),AQ12>=Settings!$B$18))+(AND(ISNUMBER(BT12),BT12>=Settings!$B$19,BT12<=Settings!$B$20))+(AND(ISNUMBER(AS12),AS12>0))+(AND(ISNUMBER(T12),ISNUMBER(M12),T12>=Settings!$B$21,M12>0))+(AND(ISNUMBER(AD12),ISNUMBER(M12),AD12>=Settings!$B$22,M12>0))+(AY12>=1)) | BW12: =IF(OR(AY12=0,BF12<>"Y",BG12<>"Y"),"",1+SUMPRODUCT(($A$6:$A$2604=A12)*($AY$6:$AY$2604>0)*($BF$6:$BF$2604="Y")*($BG$6:$BG$2604="Y")*(($AY$6:$AY$2604>AY12)+($AY$6:$AY$2604=AY12)*($AD$6:$AD$2604>AD12))))
A13: 46296 | B13: LT | C13: INE018A01030 | D13: Construction | E13: Nifty 50 | F13: 508173 | G13: N | I13: N | J13: =IF(K13="","N","Y") | K13: =_xlfn.TEXTJOIN("; ",TRUE,IF(P13="52-wk low","52-wk low",""),IF(AND(AD13>=Settings!$B$12,M13<0),"Distribution",""),IF(AND(AJ13="Y",M13<0,AK13<-Settings!$B$13),"Long unwinding",""),IF(AND(AJ13="Y",M13<0,AK13>Settings!$B$13),"Short buildup","")) | L13: 3693.4 | M13: -1.77 | N13: 1511 | O13: None | P13: None | Q13: 22.21 | R13: 15.83 | S13: 1.45 | T13: 1.47 | U13: 1.23 | V13: 0.87 | W13: 5 | X13: 215 | Y13: By value | Z13: 59.8 | AA13: 0.99 | AB13: 1.04 | AC13: 1.4 | AD13: 1.52 | AE13: 1.31 | AF13: 1.09 | AG13: Normal | AH13: 0 | AI13: 0 | AJ13: Y | AK13: 2.29 | AL13: Short buildup | AM13: 42 | AN13: None | AO13: 0 | AP13: 0.86 | AQ13: 54 | AR13: Y | AS13: 0.78 | AT13: =IF(AND(P13="52-wk high",T13>=Settings!$B$7),"Y","N") | AU13: =IF(AND(AD13>=Settings!$B$8,M13>0),"Y","N") | AV13: =IF(OR(AH13>Settings!$B$9,AI13>Settings!$B$9),"Y","N") | AW13: =IF(AJ13<>"Y","n/a",IF(AND(M13>0,AK13>Settings!$B$10),"Y","N")) | AX13: =IF(AO13>=Settings!$B$11,"Y","N") | AY13: =(AT13="Y")+(AU13="Y")+(AV13="Y")+(AW13="Y")+(AX13="Y") | AZ13: =IF(AY13=0,"None",_xlfn.TEXTJOIN(", ",TRUE(),IF(AT13="Y","Breakout",""),IF(AU13="Y","Accumulation",""),IF(AV13="Y","Institutional buying",""),IF(AW13="Y","Long buildup",""),IF(AX13="Y","Momentum leader",""))) | BA13: =IF(BW13="","","Passes "&AY13&" of 5 buy-side scans"&IF(G13="Y","; RED FLAG: filter out using Red flag column","")) | BB13: None | BC13: N | BF13: =IF(R13*100000>=Settings!$B$5,"Y","N") | BG13: =IF(F13>Settings!$B$6,"Y","N") | BH13: -16.82 | BI13: -4.28 | BJ13: -7.2 | BK13: -9.75 | BL13: 2.38 | BM13: 0.63 | BN13: -4.34 | BO13: -5.89 | BP13: -6.44 | BQ13: -6.12 | BR13: Mixed | BS13: None | BT13: 27.4 | BU13: N | BV13: =IF(OR(BF13<>"Y",BG13<>"Y"),"",(AND(ISNUMBER(BQ13),BQ13>0))+(BR13="Stacked up")+(AND(ISNUMBER(BH13),BH13>=-Settings!$B$17))+(AND(ISNUMBER(BK13),ISNUMBER(BM13),BK13>0,BM13>0))+(AND(ISNUMBER(AQ13),AQ13>=Settings!$B$18))+(AND(ISNUMBER(BT13),BT13>=Settings!$B$19,BT13<=Settings!$B$20))+(AND(ISNUMBER(AS13),AS13>0))+(AND(ISNUMBER(T13),ISNUMBER(M13),T13>=Settings!$B$21,M13>0))+(AND(ISNUMBER(AD13),ISNUMBER(M13),AD13>=Settings!$B$22,M13>0))+(AY13>=1)) | BW13: =IF(OR(AY13=0,BF13<>"Y",BG13<>"Y"),"",1+SUMPRODUCT(($A$6:$A$2604=A13)*($AY$6:$AY$2604>0)*($BF$6:$BF$2604="Y")*($BG$6:$BG$2604="Y")*(($AY$6:$AY$2604>AY13)+($AY$6:$AY$2604=AY13)*($AD$6:$AD$2604>AD13))))
A14: 46296 | B14: SUNPHARMA | C14: INE044A01036 | D14: Healthcare | E14: Nifty 50 | F14: 432120 | G14: N | I14: N | J14: =IF(K14="","N","Y") | K14: =_xlfn.TEXTJOIN("; ",TRUE,IF(P14="52-wk low","52-wk low",""),IF(AND(AD14>=Settings!$B$12,M14<0),"Distribution",""),IF(AND(AJ14="Y",M14<0,AK14<-Settings!$B$13),"Long unwinding",""),IF(AND(AJ14="Y",M14<0,AK14>Settings!$B$13),"Short buildup","")) | L14: 1801 | M14: -0.86 | N14: 966 | O14: None | P14: None | Q14: 23.15 | R14: 15.87 | S14: 1.51 | T14: 1.21 | U14: 1.08 | V14: 0.74 | W14: 5 | X14: 238 | Y14: None | Z14: 63.96 | AA14: 0.98 | AB14: 0.98 | AC14: 1.5 | AD14: 1.19 | AE14: 1.09 | AF14: 1.02 | AG14: Normal | AH14: 0 | AI14: 0 | AJ14: Y | AK14: 2.46 | AL14: Short buildup | AM14: 93 | AN14: None | AO14: 0 | AP14: 1.13 | AQ14: 67 | AR14: Y | AS14: 3.79 | AT14: =IF(AND(P14="52-wk high",T14>=Settings!$B$7),"Y","N") | AU14: =IF(AND(AD14>=Settings!$B$8,M14>0),"Y","N") | AV14: =IF(OR(AH14>Settings!$B$9,AI14>Settings!$B$9),"Y","N") | AW14: =IF(AJ14<>"Y","n/a",IF(AND(M14>0,AK14>Settings!$B$10),"Y","N")) | AX14: =IF(AO14>=Settings!$B$11,"Y","N") | AY14: =(AT14="Y")+(AU14="Y")+(AV14="Y")+(AW14="Y")+(AX14="Y") | AZ14: =IF(AY14=0,"None",_xlfn.TEXTJOIN(", ",TRUE(),IF(AT14="Y","Breakout",""),IF(AU14="Y","Accumulation",""),IF(AV14="Y","Institutional buying",""),IF(AW14="Y","Long buildup",""),IF(AX14="Y","Momentum leader",""))) | BA14: =IF(BW14="","","Passes "&AY14&" of 5 buy-side scans"&IF(G14="Y","; RED FLAG: filter out using Red flag column","")) | BB14: None | BC14: N | BF14: =IF(R14*100000>=Settings!$B$5,"Y","N") | BG14: =IF(F14>Settings!$B$6,"Y","N") | BH14: -12.01 | BI14: -2.64 | BJ14: -6.64 | BK14: -3.49 | BL14: 4.19 | BM14: 10.07 | BN14: -3.07 | BO14: -4.21 | BP14: -3.56 | BQ14: -1.17 | BR14: Mixed | BS14: None | BT14: 34 | BU14: N | BV14: =IF(OR(BF14<>"Y",BG14<>"Y"),"",(AND(ISNUMBER(BQ14),BQ14>0))+(BR14="Stacked up")+(AND(ISNUMBER(BH14),BH14>=-Settings!$B$17))+(AND(ISNUMBER(BK14),ISNUMBER(BM14),BK14>0,BM14>0))+(AND(ISNUMBER(AQ14),AQ14>=Settings!$B$18))+(AND(ISNUMBER(BT14),BT14>=Settings!$B$19,BT14<=Settings!$B$20))+(AND(ISNUMBER(AS14),AS14>0))+(AND(ISNUMBER(T14),ISNUMBER(M14),T14>=Settings!$B$21,M14>0))+(AND(ISNUMBER(AD14),ISNUMBER(M14),AD14>=Settings!$B$22,M14>0))+(AY14>=1)) | BW14: =IF(OR(AY14=0,BF14<>"Y",BG14<>"Y"),"",1+SUMPRODUCT(($A$6:$A$2604=A14)*($AY$6:$AY$2604>0)*($BF$6:$BF$2604="Y")*($BG$6:$BG$2604="Y")*(($AY$6:$AY$2604>AY14)+($AY$6:$AY$2604=AY14)*($AD$6:$AD$2604>AD14))))
A15: 46296 | B15: HINDUNILVR | C15: INE030A01027 | D15: Fast Moving Consumer Goods | E15: Nifty 50 | F15: 431385 | G15: N | I15: N | J15: =IF(K15="","N","Y") | K15: =_xlfn.TEXTJOIN("; ",TRUE,IF(P15="52-wk low","52-wk low",""),IF(AND(AD15>=Settings!$B$12,M15<0),"Distribution",""),IF(AND(AJ15="Y",M15<0,AK15<-Settings!$B$13),"Long unwinding",""),IF(AND(AJ15="Y",M15<0,AK15>Settings!$B$13),"Short buildup","")) | L15: 1836 | M15: -2.29 | N15: 1783 | O15: None | P15: 52-wk low | Q15: 13.32 | R15: 13.48 | S15: 0.98 | T15: 0.89 | U15: 0.79 | V15: 0.8 | W15: 4 | Y15: None | Z15: 52.1 | AA15: 0.86 | AB15: 0.87 | AC15: 0.83 | AD15: 0.78 | AE15: 0.68 | AF15: 1.01 | AG15: Normal | AH15: 0 | AI15: 0 | AJ15: Y | AK15: -0.36 | AL15: Long unwinding | AM15: 99 | AN15: None | AO15: 0 | AP15: 0.49 | AQ15: 4 | AR15: Y | AS15: 2.11 | AT15: =IF(AND(P15="52-wk high",T15>=Settings!$B$7),"Y","N") | AU15: =IF(AND(AD15>=Settings!$B$8,M15>0),"Y","N") | AV15: =IF(OR(AH15>Settings!$B$9,AI15>Settings!$B$9),"Y","N") | AW15: =IF(AJ15<>"Y","n/a",IF(AND(M15>0,AK15>Settings!$B$10),"Y","N")) | AX15: =IF(AO15>=Settings!$B$11,"Y","N") | AY15: =(AT15="Y")+(AU15="Y")+(AV15="Y")+(AW15="Y")+(AX15="Y") | AZ15: =IF(AY15=0,"None",_xlfn.TEXTJOIN(", ",TRUE(),IF(AT15="Y","Breakout",""),IF(AU15="Y","Accumulation",""),IF(AV15="Y","Institutional buying",""),IF(AW15="Y","Long buildup",""),IF(AX15="Y","Momentum leader",""))) | BA15: =IF(BW15="","","Passes "&AY15&" of 5 buy-side scans"&IF(G15="Y","; RED FLAG: filter out using Red flag column","")) | BB15: None | BC15: N | BF15: =IF(R15*100000>=Settings!$B$5,"Y","N") | BG15: =IF(F15>Settings!$B$6,"Y","N") | BH15: -31.16 | BI15: -5.04 | BJ15: -7.96 | BK15: -15.86 | BL15: -11.08 | BM15: -27.61 | BN15: -4.91 | BO15: -8.06 | BP15: -11.32 | BQ15: -15.47 | BR15: Stacked down | BS15: None | BT15: 25.8 | BU15: N | BV15: =IF(OR(BF15<>"Y",BG15<>"Y"),"",(AND(ISNUMBER(BQ15),BQ15>0))+(BR15="Stacked up")+(AND(ISNUMBER(BH15),BH15>=-Settings!$B$17))+(AND(ISNUMBER(BK15),ISNUMBER(BM15),BK15>0,BM15>0))+(AND(ISNUMBER(AQ15),AQ15>=Settings!$B$18))+(AND(ISNUMBER(BT15),BT15>=Settings!$B$19,BT15<=Settings!$B$20))+(AND(ISNUMBER(AS15),AS15>0))+(AND(ISNUMBER(T15),ISNUMBER(M15),T15>=Settings!$B$21,M15>0))+(AND(ISNUMBER(AD15),ISNUMBER(M15),AD15>=Settings!$B$22,M15>0))+(AY15>=1)) | BW15: =IF(OR(AY15=0,BF15<>"Y",BG15<>"Y"),"",1+SUMPRODUCT(($A$6:$A$2604=A15)*($AY$6:$AY$2604>0)*($BF$6:$BF$2604="Y")*($BG$6:$BG$2604="Y")*(($AY$6:$AY$2604>AY15)+($AY$6:$AY$2604=AY15)*($AD$6:$AD$2604>AD15))))
A16: 46296 | B16: INFY | C16: INE009A01021 | D16: Information Technology | E16: Nifty 50 | F16: 420027 | G16: N | I16: N | J16: =IF(K16="","N","Y") | K16: =_xlfn.TEXTJOIN("; ",TRUE,IF(P16="52-wk low","52-wk low",""),IF(AND(AD16>=Settings!$B$12,M16<0),"Distribution",""),IF(AND(AJ16="Y",M16<0,AK16<-Settings!$B$13),"Long unwinding",""),IF(AND(AJ16="Y",M16<0,AK16>Settings!$B$13),"Short buildup","")) | L16: 1035 | M16: 4.11 | N16: 86 | O16: None | P16: None | Q16: 151.66 | R16: 95.42 | S16: 1.65 | T16: 1.42 | U16: 1.19 | V16: 0.75 | W16: 6 | X16: 210 | Y16: By value | Z16: 51.96 | AA16: 0.93 | AB16: 0.93 | AC16: 1.49 | AD16: 1.32 | AE16: 1.12 | AF16: 1.03 | AG16: Normal | AH16: 0 | AI16: 0 | AJ16: Y | AK16: 3.81 | AL16: Long buildup | AM16: 2 | AN16: None | AO16: 0 | AP16: 0.51 | AQ16: 6 | AR16: Y | AS16: -0.75 | AT16: =IF(AND(P16="52-wk high",T16>=Settings!$B$7),"Y","N") | AU16: =IF(AND(AD16>=Settings!$B$8,M16>0),"Y","N") | AV16: =IF(OR(AH16>Settings!$B$9,AI16>Settings!$B$9),"Y","N") | AW16: =IF(AJ16<>"Y","n/a",IF(AND(M16>0,AK16>Settings!$B$10),"Y","N")) | AX16: =IF(AO16>=Settings!$B$11,"Y","N") | AY16: =(AT16="Y")+(AU16="Y")+(AV16="Y")+(AW16="Y")+(AX16="Y") | AZ16: =IF(AY16=0,"None",_xlfn.TEXTJOIN(", ",TRUE(),IF(AT16="Y","Breakout",""),IF(AU16="Y","Accumulation",""),IF(AV16="Y","Institutional buying",""),IF(AW16="Y","Long buildup",""),IF(AX16="Y","Momentum leader",""))) | BA16: =IF(BW16="","","Passes "&AY16&" of 5 buy-side scans"&IF(G16="Y","; RED FLAG: filter out using Red flag column","")) | BB16: None | BC16: N | BF16: =IF(R16*100000>=Settings!$B$5,"Y","N") | BG16: =IF(F16>Settings!$B$6,"Y","N") | BH16: -40.1 | BI16: 2.02 | BJ16: -10.47 | BK16: 5.04 | BL16: -18.87 | BM16: -28.41 | BN16: -0.99 | BO16: -4.35 | BP16: -8.34 | BQ16: -15.12 | BR16: Stacked down | BS16: None | BT16: 48.3 | BU16: N | BV16: =IF(OR(BF16<>"Y",BG16<>"Y"),"",(AND(ISNUMBER(BQ16),BQ16>0))+(BR16="Stacked up")+(AND(ISNUMBER(BH16),BH16>=-Settings!$B$17))+(AND(ISNUMBER(BK16),ISNUMBER(BM16),BK16>0,BM16>0))+(AND(ISNUMBER(AQ16),AQ16>=Settings!$B$18))+(AND(ISNUMBER(BT16),BT16>=Settings!$B$19,BT16<=Settings!$B$20))+(AND(ISNUMBER(AS16),AS16>0))+(AND(ISNUMBER(T16),ISNUMBER(M16),T16>=Settings!$B$21,M16>0))+(AND(ISNUMBER(AD16),ISNUMBER(M16),AD16>=Settings!$B$22,M16>0))+(AY16>=1)) | BW16: =IF(OR(AY16=0,BF16<>"Y",BG16<>"Y"),"",1+SUMPRODUCT(($A$6:$A$2604=A16)*($AY$6:$AY$2604>0)*($BF$6:$BF$2604="Y")*($BG$6:$BG$2604="Y")*(($AY$6:$AY$2604>AY16)+($AY$6:$AY$2604=AY16)*($AD$6:$AD$2604>AD16))))
A17: 46296 | B17: KOTAKBANK | C17: INE237A01036 | D17: Financial Services | E17: Nifty 50 | F17: 416160 | G17: N | I17: N | J17: =IF(K17="","N","Y") | K17: =_xlfn.TEXTJOIN("; ",TRUE,IF(P17="52-wk low","52-wk low",""),IF(AND(AD17>=Settings!$B$12,M17<0),"Distribution",""),IF(AND(AJ17="Y",M17<0,AK17<-Settings!$B$13),"Long unwinding",""),IF(AND(AJ17="Y",M17<0,AK17>Settings!$B$13),"Short buildup","")) | L17: 418.35 | M17: 0.32 | N17: 491 | O17: None | P17: None | Q17: 766.37 | R17: 164.86 | S17: 5.83 | T17: 6.16 | U17: 5.24 | V17: 1.09 | W17: 5 | X17: 18 | Y17: Both | Z17: 58.17 | AA17: 0.85 | AB17: 0.86 | AC17: 4.82 | AD17: 5.21 | AE17: 4.62 | AF17: 1.03 | AG17: Normal | AH17: 0 | AI17: 0 | AJ17: Y | AK17: -1.97 | AL17: Short covering | AM17: 1 | AN17: None | AO17: 0 | AR17: Y | AS17: 0.6 | AT17: =IF(AND(P17="52-wk high",T17>=Settings!$B$7),"Y","N") | AU17: =IF(AND(AD17>=Settings!$B$8,M17>0),"Y","N") | AV17: =IF(OR(AH17>Settings!$B$9,AI17>Settings!$B$9),"Y","N") | AW17: =IF(AJ17<>"Y","n/a",IF(AND(M17>0,AK17>Settings!$B$10),"Y","N")) | AX17: =IF(AO17>=Settings!$B$11,"Y","N") | AY17: =(AT17="Y")+(AU17="Y")+(AV17="Y")+(AW17="Y")+(AX17="Y") | AZ17: =IF(AY17=0,"None",_xlfn.TEXTJOIN(", ",TRUE(),IF(AT17="Y","Breakout",""),IF(AU17="Y","Accumulation",""),IF(AV17="Y","Institutional buying",""),IF(AW17="Y","Long buildup",""),IF(AX17="Y","Momentum leader",""))) | BA17: =IF(BW17="","","Passes "&AY17&" of 5 buy-side scans"&IF(G17="Y","; RED FLAG: filter out using Red flag column","")) | BB17: Upper | BC17: N | BF17: =IF(R17*100000>=Settings!$B$5,"Y","N") | BG17: =IF(F17>Settings!$B$6,"Y","N") | BH17: -7.69 | BI17: 3.3 | BJ17: -1.56 | BK17: 4.47 | BL17: 17.5 | BN17: 1.64 | BO17: 2.96 | BP17: 4.3 | BS17: None | BT17: 60.2 | BV17: =IF(OR(BF17<>"Y",BG17<>"Y"),"",(AND(ISNUMBER(BQ17),BQ17>0))+(BR17="Stacked up")+(AND(ISNUMBER(BH17),BH17>=-Settings!$B$17))+(AND(ISNUMBER(BK17),ISNUMBER(BM17),BK17>0,BM17>0))+(AND(ISNUMBER(AQ17),AQ17>=Settings!$B$18))+(AND(ISNUMBER(BT17),BT17>=Settings!$B$19,BT17<=Settings!$B$20))+(AND(ISNUMBER(AS17),AS17>0))+(AND(ISNUMBER(T17),ISNUMBER(M17),T17>=Settings!$B$21,M17>0))+(AND(ISNUMBER(AD17),ISNUMBER(M17),AD17>=Settings!$B$22,M17>0))+(AY17>=1)) | BW17: =IF(OR(AY17=0,BF17<>"Y",BG17<>"Y"),"",1+SUMPRODUCT(($A$6:$A$2604=A17)*($AY$6:$AY$2604>0)*($BF$6:$BF$2604="Y")*($BG$6:$BG$2604="Y")*(($AY$6:$AY$2604>AY17)+($AY$6:$AY$2604=AY17)*($AD$6:$AD$2604>AD17))))
A18: 46296 | B18: TITAN | C18: INE280A01028 | D18: Consumer Durables | E18: Nifty 50 | F18: 400898 | G18: N | I18: N | J18: =IF(K18="","N","Y") | K18: =_xlfn.TEXTJOIN("; ",TRUE,IF(P18="52-wk low","52-wk low",""),IF(AND(AD18>=Settings!$B$12,M18<0),"Distribution",""),IF(AND(AJ18="Y",M18<0,AK18<-Settings!$B$13),"Long unwinding",""),IF(AND(AJ18="Y",M18<0,AK18>Settings!$B$13),"Short buildup","")) | L18: 4515.7 | M18: -1.55 | N18: 1366 | O18: None | P18: None | Q18: 6.94 | R18: 6.23 | S18: 1.1 | T18: 0.93 | U18: 0.77 | V18: 0.73 | W18: 3 | Y18: None | Z18: 57.67 | AA18: 0.99 | AB18: 1 | AC18: 1.08 | AD18: 0.96 | AE18: 0.83 | AF18: 1.09 | AG18: Normal | AH18: 0 | AI18: 0 | AJ18: Y | AK18: 2.29 | AL18: Short buildup | AM18: 48 | AN18: None | AO18: 0 | AP18: 1.65 | AQ18: 83 | AR18: Y | AS18: 0.75 | AT18: =IF(AND(P18="52-wk high",T18>=Settings!$B$7),"Y","N") | AU18: =IF(AND(AD18>=Settings!$B$8,M18>0),"Y","N") | AV18: =IF(OR(AH18>Settings!$B$9,AI18>Settings!$B$9),"Y","N") | AW18: =IF(AJ18<>"Y","n/a",IF(AND(M18>0,AK18>Settings!$B$10),"Y","N")) | AX18: =IF(AO18>=Settings!$B$11,"Y","N") | AY18: =(AT18="Y")+(AU18="Y")+(AV18="Y")+(AW18="Y")+(AX18="Y") | AZ18: =IF(AY18=0,"None",_xlfn.TEXTJOIN(", ",TRUE(),IF(AT18="Y","Breakout",""),IF(AU18="Y","Accumulation",""),IF(AV18="Y","Institutional buying",""),IF(AW18="Y","Long buildup",""),IF(AX18="Y","Momentum leader",""))) | BA18: =IF(BW18="","","Passes "&AY18&" of 5 buy-side scans"&IF(G18="Y","; RED FLAG: filter out using Red flag column","")) | BB18: None | BC18: Y | BD18: PE > 50 | BF18: =IF(R18*100000>=Settings!$B$5,"Y","N") | BG18: =IF(F18>Settings!$B$6,"Y","N") | BH18: -12.94 | BI18: -6.56 | BJ18: -10.58 | BK18: 2.66 | BL18: 11.07 | BM18: 32.49 | BN18: -6.6 | BO18: -6.79 | BP18: -3.9 | BQ18: 1.71 | BR18: Mixed | BS18: Bearish cross | BT18: 21 | BU18: N | BV18: =IF(OR(BF18<>"Y",BG18<>"Y"),"",(AND(ISNUMBER(BQ18),BQ18>0))+(BR18="Stacked up")+(AND(ISNUMBER(BH18),BH18>=-Settings!$B$17))+(AND(ISNUMBER(BK18),ISNUMBER(BM18),BK18>0,BM18>0))+(AND(ISNUMBER(AQ18),AQ18>=Settings!$B$18))+(AND(ISNUMBER(BT18),BT18>=Settings!$B$19,BT18<=Settings!$B$20))+(AND(ISNUMBER(AS18),AS18>0))+(AND(ISNUMBER(T18),ISNUMBER(M18),T18>=Settings!$B$21,M18>0))+(AND(ISNUMBER(AD18),ISNUMBER(M18),AD18>=Settings!$B$22,M18>0))+(AY18>=1)) | BW18: =IF(OR(AY18=0,BF18<>"Y",BG18<>"Y"),"",1+SUMPRODUCT(($A$6:$A$2604=A18)*($AY$6:$AY$2604>0)*($BF$6:$BF$2604="Y")*($BG$6:$BG$2604="Y")*(($AY$6:$AY$2604>AY18)+($AY$6:$AY$2604=AY18)*($AD$6:$AD$2604>AD18))))
A19: 46296 | B19: ADANIPORTS | C19: INE742F01042 | D19: Services | E19: Nifty 50 | F19: 400382 | G19: N | I19: N | J19: =IF(K19="","N","Y") | K19: =_xlfn.TEXTJOIN("; ",TRUE,IF(P19="52-wk low","52-wk low",""),IF(AND(AD19>=Settings!$B$12,M19<0),"Distribution",""),IF(AND(AJ19="Y",M19<0,AK19<-Settings!$B$13),"Long unwinding",""),IF(AND(AJ19="Y",M19<0,AK19>Settings!$B$13),"Short buildup","")) | L19: 1737.8 | M19: -3.36 | N19: 2185 | O19: None | P19: None | Q19: 21.58 | R19: 21.17 | S19: 1.02 | T19: 0.93 | U19: 0.96 | V19: 0.95 | W19: 6 | Y19: None | Z19: 52.62 | AA19: 0.9 | AB19: 0.92 | AC19: 0.89 | AD19: 0.83 | AE19: 0.95 | AF19: 1.13 | AG19: Normal | AH19: 0 | AI19: 0 | AJ19: Y | AK19: -2.41 | AL19: Long unwinding | AM19: 51 | AN19: None | AO19: 0 | AP19: 1.58 | AQ19: 81 | AR19: Y | AS19: 5.23 | AT19: =IF(AND(P19="52-wk high",T19>=Settings!$B$7),"Y","N") | AU19: =IF(AND(AD19>=Settings!$B$8,M19>0),"Y","N") | AV19: =IF(OR(AH19>Settings!$B$9,AI19>Settings!$B$9),"Y","N") | AW19: =IF(AJ19<>"Y","n/a",IF(AND(M19>0,AK19>Settings!$B$10),"Y","N")) | AX19: =IF(AO19>=Settings!$B$11,"Y","N") | AY19: =(AT19="Y")+(AU19="Y")+(AV19="Y")+(AW19="Y")+(AX19="Y") | AZ19: =IF(AY19=0,"None",_xlfn.TEXTJOIN(", ",TRUE(),IF(AT19="Y","Breakout",""),IF(AU19="Y","Accumulation",""),IF(AV19="Y","Institutional buying",""),IF(AW19="Y","Long buildup",""),IF(AX19="Y","Momentum leader",""))) | BA19: =IF(BW19="","","Passes "&AY19&" of 5 buy-side scans"&IF(G19="Y","; RED FLAG: filter out using Red flag column","")) | BB19: None | BC19: N | BF19: =IF(R19*100000>=Settings!$B$5,"Y","N") | BG19: =IF(F19>Settings!$B$6,"Y","N") | BH19: -8.11 | BI19: -2.66 | BJ19: 5.48 | BK19: -5.97 | BL19: 25.44 | BM19: 22.15 | BN19: -1.25 | BO19: -0.33 | BP19: 1.08 | BQ19: 4.92 | BR19: Mixed | BS19: None | BT19: 45.2 | BU19: N | BV19: =IF(OR(BF19<>"Y",BG19<>"Y"),"",(AND(ISNUMBER(BQ19),BQ19>0))+(BR19="Stacked up")+(AND(ISNUMBER(BH19),BH19>=-Settings!$B$17))+(AND(ISNUMBER(BK19),ISNUMBER(BM19),BK19>0,BM19>0))+(AND(ISNUMBER(AQ19),AQ19>=Settings!$B$18))+(AND(ISNUMBER(BT19),BT19>=Settings!$B$19,BT19<=Settings!$B$20))+(AND(ISNUMBER(AS19),AS19>0))+(AND(ISNUMBER(T19),ISNUMBER(M19),T19>=Settings!$B$21,M19>0))+(AND(ISNUMBER(AD19),ISNUMBER(M19),AD19>=Settings!$B$22,M19>0))+(AY19>=1)) | BW19: =IF(OR(AY19=0,BF19<>"Y",BG19<>"Y"),"",1+SUMPRODUCT(($A$6:$A$2604=A19)*($AY$6:$AY$2604>0)*($BF$6:$BF$2604="Y")*($BG$6:$BG$2604="Y")*(($AY$6:$AY$2604>AY19)+($AY$6:$AY$2604=AY19)*($AD$6:$AD$2604>AD19))))
A20: 46296 | B20: ADANIENT | C20: INE423A01024 | D20: Metals & Mining | E20: Nifty 50 | F20: 381234 | G20: N | I20: N | J20: =IF(K20="","N","Y") | K20: =_xlfn.TEXTJOIN("; ",TRUE,IF(P20="52-wk low","52-wk low",""),IF(AND(AD20>=Settings!$B$12,M20<0),"Distribution",""),IF(AND(AJ20="Y",M20<0,AK20<-Settings!$B$13),"Long unwinding",""),IF(AND(AJ20="Y",M20<0,AK20>Settings!$B$13),"Short buildup","")) | L20: 2816.8 | M20: -2.98 | N20: 2082 | O20: None | P20: None | Q20: 21 | R20: 15.31 | S20: 1.39 | T20: 1.34 | U20: 1.07 | V20: 0.77 | W20: 3 | X20: 238 | Y20: None | Z20: 42.05 | AA20: 1.03 | AB20: 1.03 | AC20: 1.33 | AD20: 1.19 | AE20: 1.18 | AF20: 1.16 | AG20: Normal | AH20: 0 | AI20: 0 | AJ20: Y | AK20: 0.71 | AL20: Short buildup | AM20: 33 | AN20: None | AO20: 0 | AP20: 1.66 | AQ20: 83 | AR20: Y | AS20: -1.09 | AT20: =IF(AND(P20="52-wk high",T20>=Settings!$B$7),"Y","N") | AU20: =IF(AND(AD20>=Settings!$B$8,M20>0),"Y","N") | AV20: =IF(OR(AH20>Settings!$B$9,AI20>Settings!$B$9),"Y","N") | AW20: =IF(AJ20<>"Y","n/a",IF(AND(M20>0,AK20>Settings!$B$10),"Y","N")) | AX20: =IF(AO20>=Settings!$B$11,"Y","N") | AY20: =(AT20="Y")+(AU20="Y")+(AV20="Y")+(AW20="Y")+(AX20="Y") | AZ20: =IF(AY20=0,"None",_xlfn.TEXTJOIN(", ",TRUE(),IF(AT20="Y","Breakout",""),IF(AU20="Y","Accumulation",""),IF(AV20="Y","Institutional buying",""),IF(AW20="Y","Long buildup",""),IF(AX20="Y","Momentum leader",""))) | BA20: =IF(BW20="","","Passes "&AY20&" of 5 buy-side scans"&IF(G20="Y","; RED FLAG: filter out using Red flag column","")) | BB20: None | BC20: Y | BD20: PE > 50 | BF20: =IF(R20*100000>=Settings!$B$5,"Y","N") | BG20: =IF(F20>Settings!$B$6,"Y","N") | BH20: -13.2 | BI20: -2.87 | BJ20: -1.64 | BK20: -10.4 | BL20: 52.88 | BM20: 8.64 | BN20: -4.32 | BO20: -5.05 | BP20: -2.39 | BQ20: 2.94 | BR20: Mixed | BS20: None | BT20: 38 | BU20: N | BV20: =IF(OR(BF20<>"Y",BG20<>"Y"),"",(AND(ISNUMBER(BQ20),BQ20>0))+(BR20="Stacked up")+(AND(ISNUMBER(BH20),BH20>=-Settings!$B$17))+(AND(ISNUMBER(BK20),ISNUMBER(BM20),BK20>0,BM20>0))+(AND(ISNUMBER(AQ20),AQ20>=Settings!$B$18))+(AND(ISNUMBER(BT20),BT20>=Settings!$B$19,BT20<=Settings!$B$20))+(AND(ISNUMBER(AS20),AS20>0))+(AND(ISNUMBER(T20),ISNUMBER(M20),T20>=Settings!$B$21,M20>0))+(AND(ISNUMBER(AD20),ISNUMBER(M20),AD20>=Settings!$B$22,M20>0))+(AY20>=1)) | BW20: =IF(OR(AY20=0,BF20<>"Y",BG20<>"Y"),"",1+SUMPRODUCT(($A$6:$A$2604=A20)*($AY$6:$AY$2604>0)*($BF$6:$BF$2604="Y")*($BG$6:$BG$2604="Y")*(($AY$6:$AY$2604>AY20)+($AY$6:$AY$2604=AY20)*($AD$6:$AD$2604>AD20))))
A21: 46296 | B21: AXISBANK | C21: INE238A01034 | D21: Financial Services | E21: Nifty 50 | F21: 378953 | G21: N | I21: N | J21: =IF(K21="","N","Y") | K21: =_xlfn.TEXTJOIN("; ",TRUE,IF(P21="52-wk low","52-wk low",""),IF(AND(AD21>=Settings!$B$12,M21<0),"Distribution",""),IF(AND(AJ21="Y",M21<0,AK21<-Settings!$B$13),"Long unwinding",""),IF(AND(AJ21="Y",M21<0,AK21>Settings!$B$13),"Short buildup","")) | L21: 1217.1 | M21: -0.73 | N21: 897 | O21: None | P21: None | Q21: 70.05 | R21: 50.51 | S21: 1.39 | T21: 1.3 | U21: 1.11 | V21: 0.8 | W21: 5 | X21: 238 | Y21: By value | Z21: 60.93 | AA21: 0.99 | AB21: 0.96 | AC21: 1.38 | AD21: 1.23 | AE21: 1.07 | AF21: 0.98 | AG21: Normal | AH21: 0 | AI21: 0 | AJ21: Y | AK21: -0.27 | AL21: Long unwinding | AM21: 9 | AN21: None | AO21: 0 | AP21: 0.92 | AQ21: 58 | AR21: Y | AS21: 0.6 | AT21: =IF(AND(P21="52-wk high",T21>=Settings!$B$7),"Y","N") | AU21: =IF(AND(AD21>=Settings!$B$8,M21>0),"Y","N") | AV21: =IF(OR(AH21>Settings!$B$9,AI21>Settings!$B$9),"Y","N") | AW21: =IF(AJ21<>"Y","n/a",IF(AND(M21>0,AK21>Settings!$B$10),"Y","N")) | AX21: =IF(AO21>=Settings!$B$11,"Y","N") | AY21: =(AT21="Y")+(AU21="Y")+(AV21="Y")+(AW21="Y")+(AX21="Y") | AZ21: =IF(AY21=0,"None",_xlfn.TEXTJOIN(", ",TRUE(),IF(AT21="Y","Breakout",""),IF(AU21="Y","Accumulation",""),IF(AV21="Y","Institutional buying",""),IF(AW21="Y","Long buildup",""),IF(AX21="Y","Momentum leader",""))) | BA21: =IF(BW21="","","Passes "&AY21&" of 5 buy-side scans"&IF(G21="Y","; RED FLAG: filter out using Red flag column","")) | BB21: None | BC21: N | BF21: =IF(R21*100000>=Settings!$B$5,"Y","N") | BG21: =IF(F21>Settings!$B$6,"Y","N") | BH21: -14.19 | BI21: 2.58 | BJ21: -3.25 | BK21: -11.08 | BL21: 2.01 | BM21: 4.97 | BN21: -1.25 | BO21: -2.49 | BP21: -3.61 | BQ21: -3.63 | BR21: Stacked down | BS21: None | BT21: 44.2 | BU21: N | BV21: =IF(OR(BF21<>"Y",BG21<>"Y"),"",(AND(ISNUMBER(BQ21),BQ21>0))+(BR21="Stacked up")+(AND(ISNUMBER(BH21),BH21>=-Settings!$B$17))+(AND(ISNUMBER(BK21),ISNUMBER(BM21),BK21>0,BM21>0))+(AND(ISNUMBER(AQ21),AQ21>=Settings!$B$18))+(AND(ISNUMBER(BT21),BT21>=Settings!$B$19,BT21<=Settings!$B$20))+(AND(ISNUMBER(AS21),AS21>0))+(AND(ISNUMBER(T21),ISNUMBER(M21),T21>=Settings!$B$21,M21>0))+(AND(ISNUMBER(AD21),ISNUMBER(M21),AD21>=Settings!$B$22,M21>0))+(AY21>=1)) | BW21: =IF(OR(AY21=0,BF21<>"Y",BG21<>"Y"),"",1+SUMPRODUCT(($A$6:$A$2604=A21)*($AY$6:$AY$2604>0)*($BF$6:$BF$2604="Y")*($BG$6:$BG$2604="Y")*(($AY$6:$AY$2604>AY21)+($AY$6:$AY$2604=AY21)*($AD$6:$AD$2604>AD21))))
A22: 46296 | B22: MARUTI | C22: INE585B01010 | D22: Automobile and Auto Components | E22: Nifty 50 | F22: 357979 | G22: N | I22: N | J22: =IF(K22="","N","Y") | K22: =_xlfn.TEXTJOIN("; ",TRUE,IF(P22="52-wk low","52-wk low",""),IF(AND(AD22>=Settings!$B$12,M22<0),"Distribution",""),IF(AND(AJ22="Y",M22<0,AK22<-Settings!$B$13),"Long unwinding",""),IF(AND(AJ22="Y",M22<0,AK22>Settings!$B$13),"Short buildup","")) | L22: 11386 | M22: -4.86 | N22: 2458 | O22: None | P22: 52-wk low | Q22: 8.86 | R22: 3.99 | S22: 2.3 | T22: 2.36 | U22: 2.1 | V22: 0.94 | W22: 6 | X22: 86 | Y22: By value | Z22: 45.98 | AA22: 0.84 | AB22: 0.85 | AC22: 1.91 | AD22: 1.99 | AE22: 1.8 | AF22: 1.01 | AG22: Normal | AH22: 0 | AI22: 0 | AJ22: Y | AK22: 2 | AL22: Short buildup | AM22: 17 | AN22: None | AO22: 0 | AP22: 0.51 | AQ22: 6 | AR22: Y | AS22: 0.56 | AT22: =IF(AND(P22="52-wk high",T22>=Settings!$B$7),"Y","N") | AU22: =IF(AND(AD22>=Settings!$B$8,M22>0),"Y","N") | AV22: =IF(OR(AH22>Settings!$B$9,AI22>Settings!$B$9),"Y","N") | AW22: =IF(AJ22<>"Y","n/a",IF(AND(M22>0,AK22>Settings!$B$10),"Y","N")) | AX22: =IF(AO22>=Settings!$B$11,"Y","N") | AY22: =(AT22="Y")+(AU22="Y")+(AV22="Y")+(AW22="Y")+(AX22="Y") | AZ22: =IF(AY22=0,"None",_xlfn.TEXTJOIN(", ",TRUE(),IF(AT22="Y","Breakout",""),IF(AU22="Y","Accumulation",""),IF(AV22="Y","Institutional buying",""),IF(AW22="Y","Long buildup",""),IF(AX22="Y","Momentum leader",""))) | BA22: =IF(BW22="","","Passes "&AY22&" of 5 buy-side scans"&IF(G22="Y","; RED FLAG: filter out using Red flag column","")) | BB22: Upper | BC22: N | BF22: =IF(R22*100000>=Settings!$B$5,"Y","N") | BG22: =IF(F22>Settings!$B$6,"Y","N") | BH22: -34.45 | BI22: -5.04 | BJ22: -12.08 | BK22: -20.9 | BL22: -8.98 | BM22: -28.68 | BN22: -7.31 | BO22: -11.38 | BP22: -14.13 | BQ22: -17.89 | BR22: Stacked down | BS22: None | BT22: 18.8 | BU22: N | BV22: =IF(OR(BF22<>"Y",BG22<>"Y"),"",(AND(ISNUMBER(BQ22),BQ22>0))+(BR22="Stacked up")+(AND(ISNUMBER(BH22),BH22>=-Settings!$B$17))+(AND(ISNUMBER(BK22),ISNUMBER(BM22),BK22>0,BM22>0))+(AND(ISNUMBER(AQ22),AQ22>=Settings!$B$18))+(AND(ISNUMBER(BT22),BT22>=Settings!$B$19,BT22<=Settings!$B$20))+(AND(ISNUMBER(AS22),AS22>0))+(AND(ISNUMBER(T22),ISNUMBER(M22),T22>=Settings!$B$21,M22>0))+(AND(ISNUMBER(AD22),ISNUMBER(M22),AD22>=Settings!$B$22,M22>0))+(AY22>=1)) | BW22: =IF(OR(AY22=0,BF22<>"Y",BG22<>"Y"),"",1+SUMPRODUCT(($A$6:$A$2604=A22)*($AY$6:$AY$2604>0)*($BF$6:$BF$2604="Y")*($BG$6:$BG$2604="Y")*(($AY$6:$AY$2604>AY22)+($AY$6:$AY$2604=AY22)*($AD$6:$AD$2604>AD22))))
A23: 46296 | B23: M&M | C23: INE101A01026 | D23: Automobile and Auto Components | E23: Nifty 50 | F23: 355649 | G23: N | I23: N | J23: =IF(K23="","N","Y") | K23: =_xlfn.TEXTJOIN("; ",TRUE,IF(P23="52-wk low","52-wk low",""),IF(AND(AD23>=Settings!$B$12,M23<0),"Distribution",""),IF(AND(AJ23="Y",M23<0,AK23<-Settings!$B$13),"Long unwinding",""),IF(AND(AJ23="Y",M23<0,AK23>Settings!$B$13),"Short buildup","")) | L23: 2860 | M23: -3.05 | N23: 2107 | O23: None | P23: 52-wk low | Q23: 54.53 | R23: 21.61 | S23: 2.68 | T23: 2.53 | U23: 2.16 | V23: 0.85 | W23: 3 | X23: 62 | Y23: By value | Z23: 58.85 | AA23: 0.94 | AB23: 0.97 | AC23: 2.52 | AD23: 2.46 | AE23: 2.17 | AF23: 1.06 | AG23: Normal | AH23: 0 | AI23: 0 | AJ23: Y | AK23: -4.8 | AL23: Long unwinding | AM23: 8 | AN23: None | AO23: 0 | AP23: 0.62 | AQ23: 23 | AR23: Y | AS23: 0.56 | AT23: =IF(AND(P23="52-wk high",T23>=Settings!$B$7),"Y","N") | AU23: =IF(AND(AD23>=Settings!$B$8,M23>0),"Y","N") | AV23: =IF(OR(AH23>Settings!$B$9,AI23>Settings!$B$9),"Y","N") | AW23: =IF(AJ23<>"Y","n/a",IF(AND(M23>0,AK23>Settings!$B$10),"Y","N")) | AX23: =IF(AO23>=Settings!$B$11,"Y","N") | AY23: =(AT23="Y")+(AU23="Y")+(AV23="Y")+(AW23="Y")+(AX23="Y") | AZ23: =IF(AY23=0,"None",_xlfn.TEXTJOIN(", ",TRUE(),IF(AT23="Y","Breakout",""),IF(AU23="Y","Accumulation",""),IF(AV23="Y","Institutional buying",""),IF(AW23="Y","Long buildup",""),IF(AX23="Y","Momentum leader",""))) | BA23: =IF(BW23="","","Passes "&AY23&" of 5 buy-side scans"&IF(G23="Y","; RED FLAG: filter out using Red flag column","")) | BB23: None | BC23: N | BF23: =IF(R23*100000>=Settings!$B$5,"Y","N") | BG23: =IF(F23>Settings!$B$6,"Y","N") | BH23: -25.52 | BI23: -4.11 | BJ23: -12.24 | BK23: -8.63 | BL23: -5.66 | BM23: -17.42 | BN23: -6.51 | BO23: -9.34 | BP23: -10.52 | BQ23: -12.53 | BR23: Stacked down | BS23: None | BT23: 18.4 | BU23: N | BV23: =IF(OR(BF23<>"Y",BG23<>"Y"),"",(AND(ISNUMBER(BQ23),BQ23>0))+(BR23="Stacked up")+(AND(ISNUMBER(BH23),BH23>=-Settings!$B$17))+(AND(ISNUMBER(BK23),ISNUMBER(BM23),BK23>0,BM23>0))+(AND(ISNUMBER(AQ23),AQ23>=Settings!$B$18))+(AND(ISNUMBER(BT23),BT23>=Settings!$B$19,BT23<=Settings!$B$20))+(AND(ISNUMBER(AS23),AS23>0))+(AND(ISNUMBER(T23),ISNUMBER(M23),T23>=Settings!$B$21,M23>0))+(AND(ISNUMBER(AD23),ISNUMBER(M23),AD23>=Settings!$B$22,M23>0))+(AY23>=1)) | BW23: =IF(OR(AY23=0,BF23<>"Y",BG23<>"Y"),"",1+SUMPRODUCT(($A$6:$A$2604=A23)*($AY$6:$AY$2604>0)*($BF$6:$BF$2604="Y")*($BG$6:$BG$2604="Y")*(($AY$6:$AY$2604>AY23)+($AY$6:$AY$2604=AY23)*($AD$6:$AD$2604>AD23))))
A24: 46296 | B24: HCLTECH | C24: INE860A01027 | D24: Information Technology | E24: Nifty 50 | F24: 337336 | G24: N | I24: N | J24: =IF(K24="","N","Y") | K24: =_xlfn.TEXTJOIN("; ",TRUE,IF(P24="52-wk low","52-wk low",""),IF(AND(AD24>=Settings!$B$12,M24<0),"Distribution",""),IF(AND(AJ24="Y",M24<0,AK24<-Settings!$B$13),"Long unwinding",""),IF(AND(AJ24="Y",M24<0,AK24>Settings!$B$13),"Short buildup","")) | L24: 1243.1 | M24: 1.07 | N24: 319 | O24: None | P24: None | Q24: 34.3 | R24: 26.2 | S24: 1.33 | T24: 1.38 | U24: 1.03 | V24: 0.78 | W24: 4 | X24: 248 | Y24: None | Z24: 52.43 | AA24: 1.05 | AB24: 1.02 | AC24: 1.36 | AD24: 1.4 | AE24: 1.12 | AF24: 1.06 | AG24: Normal | AH24: 0 | AI24: 0 | AJ24: Y | AK24: 0.89 | AL24: Long buildup | AM24: 43 | AN24: None | AO24: 0 | AP24: 0.65 | AQ24: 29 | AR24: Y | AS24: -0.75 | AT24: =IF(AND(P24="52-wk high",T24>=Settings!$B$7),"Y","N") | AU24: =IF(AND(AD24>=Settings!$B$8,M24>0),"Y","N") | AV24: =IF(OR(AH24>Settings!$B$9,AI24>Settings!$B$9),"Y","N") | AW24: =IF(AJ24<>"Y","n/a",IF(AND(M24>0,AK24>Settings!$B$10),"Y","N")) | AX24: =IF(AO24>=Settings!$B$11,"Y","N") | AY24: =(AT24="Y")+(AU24="Y")+(AV24="Y")+(AW24="Y")+(AX24="Y") | AZ24: =IF(AY24=0,"None",_xlfn.TEXTJOIN(", ",TRUE(),IF(AT24="Y","Breakout",""),IF(AU24="Y","Accumulation",""),IF(AV24="Y","Institutional buying",""),IF(AW24="Y","Long buildup",""),IF(AX24="Y","Momentum leader",""))) | BA24: =IF(BW24="","","Passes "&AY24&" of 5 buy-side scans"&IF(G24="Y","; RED FLAG: filter out using Red flag column","")) | BB24: None | BC24: N | BF24: =IF(R24*100000>=Settings!$B$5,"Y","N") | BG24: =IF(F24>Settings!$B$6,"Y","N") | BH24: -30.17 | BI24: -0.04 | BJ24: -8.01 | BK24: 20.2 | BL24: -8.22 | BM24: -10.54 | BN24: -1.2 | BO24: -1.87 | BP24: -2.56 | BQ24: -5.93 | BR24: Stacked down | BS24: None | BT24: 45.2 | BU24: N | BV24: =IF(OR(BF24<>"Y",BG24<>"Y"),"",(AND(ISNUMBER(BQ24),BQ24>0))+(BR24="Stacked up")+(AND(ISNUMBER(BH24),BH24>=-Settings!$B$17))+(AND(ISNUMBER(BK24),ISNUMBER(BM24),BK24>0,BM24>0))+(AND(ISNUMBER(AQ24),AQ24>=Settings!$B$18))+(AND(ISNUMBER(BT24),BT24>=Settings!$B$19,BT24<=Settings!$B$20))+(AND(ISNUMBER(AS24),AS24>0))+(AND(ISNUMBER(T24),ISNUMBER(M24),T24>=Settings!$B$21,M24>0))+(AND(ISNUMBER(AD24),ISNUMBER(M24),AD24>=Settings!$B$22,M24>0))+(AY24>=1)) | BW24: =IF(OR(AY24=0,BF24<>"Y",BG24<>"Y"),"",1+SUMPRODUCT(($A$6:$A$2604=A24)*($AY$6:$AY$2604>0)*($BF$6:$BF$2604="Y")*($BG$6:$BG$2604="Y")*(($AY$6:$AY$2604>AY24)+($AY$6:$AY$2604=AY24)*($AD$6:$AD$2604>AD24))))
A25: 46296 | B25: ITC | C25: INE154A01025 | D25: Fast Moving Consumer Goods | E25: Nifty 50 | F25: 320656 | G25: N | I25: N | J25: =IF(K25="","N","Y") | K25: =_xlfn.TEXTJOIN("; ",TRUE,IF(P25="52-wk low","52-wk low",""),IF(AND(AD25>=Settings!$B$12,M25<0),"Distribution",""),IF(AND(AJ25="Y",M25<0,AK25<-Settings!$B$13),"Long unwinding",""),IF(AND(AJ25="Y",M25<0,AK25>Settings!$B$13),"Short buildup","")) | L25: 255.9 | M25: -2.61 | N25: 1945 | O25: None | P25: 52-wk low | Q25: 164.47 | R25: 115.34 | S25: 1.44 | T25: 1.17 | U25: 1.11 | V25: 0.78 | W25: 3 | X25: 251 | Y25: None | Z25: 60.19 | AA25: 1.04 | AB25: 1.04 | AC25: 1.49 | AD25: 1.24 | AE25: 1.14 | AF25: 1 | AG25: Normal | AH25: 0 | AI25: 0 | AJ25: Y | AK25: 0.82 | AL25: Short buildup | AM25: 55 | AN25: None | AO25: 0 | AP25: 0.43 | AQ25: 1 | AR25: Y | AS25: 2.11 | AT25: =IF(AND(P25="52-wk high",T25>=Settings!$B$7),"Y","N") | AU25: =IF(AND(AD25>=Settings!$B$8,M25>0),"Y","N") | AV25: =IF(OR(AH25>Settings!$B$9,AI25>Settings!$B$9),"Y","N") | AW25: =IF(AJ25<>"Y","n/a",IF(AND(M25>0,AK25>Settings!$B$10),"Y","N")) | AX25: =IF(AO25>=Settings!$B$11,"Y","N") | AY25: =(AT25="Y")+(AU25="Y")+(AV25="Y")+(AW25="Y")+(AX25="Y") | AZ25: =IF(AY25=0,"None",_xlfn.TEXTJOIN(", ",TRUE(),IF(AT25="Y","Breakout",""),IF(AU25="Y","Accumulation",""),IF(AV25="Y","Institutional buying",""),IF(AW25="Y","Long buildup",""),IF(AX25="Y","Momentum leader",""))) | BA25: =IF(BW25="","","Passes "&AY25&" of 5 buy-side scans"&IF(G25="Y","; RED FLAG: filter out using Red flag column","")) | BB25: None | BC25: N | BF25: =IF(R25*100000>=Settings!$B$5,"Y","N") | BG25: =IF(F25>Settings!$B$6,"Y","N") | BH25: -39.99 | BI25: -4.51 | BJ25: -4.01 | BK25: -11.85 | BL25: -12.27 | BM25: -36.91 | BN25: -3.4 | BO25: -5.41 | BP25: -9.07 | BQ25: -15.92 | BR25: Stacked down | BS25: None | BT25: 31.9 | BU25: N | BV25: =IF(OR(BF25<>"Y",BG25<>"Y"),"",(AND(ISNUMBER(BQ25),BQ25>0))+(BR25="Stacked up")+(AND(ISNUMBER(BH25),BH25>=-Settings!$B$17))+(AND(ISNUMBER(BK25),ISNUMBER(BM25),BK25>0,BM25>0))+(AND(ISNUMBER(AQ25),AQ25>=Settings!$B$18))+(AND(ISNUMBER(BT25),BT25>=Settings!$B$19,BT25<=Settings!$B$20))+(AND(ISNUMBER(AS25),AS25>0))+(AND(ISNUMBER(T25),ISNUMBER(M25),T25>=Settings!$B$21,M25>0))+(AND(ISNUMBER(AD25),ISNUMBER(M25),AD25>=Settings!$B$22,M25>0))+(AY25>=1)) | BW25: =IF(OR(AY25=0,BF25<>"Y",BG25<>"Y"),"",1+SUMPRODUCT(($A$6:$A$2604=A25)*($AY$6:$AY$2604>0)*($BF$6:$BF$2604="Y")*($BG$6:$BG$2604="Y")*(($AY$6:$AY$2604>AY25)+($AY$6:$AY$2604=AY25)*($AD$6:$AD$2604>AD25))))
A26: 46296 | B26: ULTRACEMCO | C26: INE481G01011 | D26: Construction Materials | E26: Nifty 50 | F26: 315601 | G26: N | I26: N | J26: =IF(K26="","N","Y") | K26: =_xlfn.TEXTJOIN("; ",TRUE,IF(P26="52-wk low","52-wk low",""),IF(AND(AD26>=Settings!$B$12,M26<0),"Distribution",""),IF(AND(AJ26="Y",M26<0,AK26<-Settings!$B$13),"Long unwinding",""),IF(AND(AJ26="Y",M26<0,AK26>Settings!$B$13),"Short buildup","")) | L26: 10710 | M26: -2.25 | N26: 1767 | O26: None | P26: None | Q26: 5.71 | R26: 2.99 | S26: 2.03 | T26: 2.18 | U26: 1.95 | V26: 1.01 | W26: 9 | X26: 104 | Y26: None | Z26: 57.14 | AA26: 0.94 | AB26: 0.97 | AC26: 1.92 | AD26: 2.1 | AE26: 1.83 | AF26: 0.99 | AG26: Normal | AH26: 0 | AI26: 0 | AJ26: Y | AK26: 3.56 | AL26: Short buildup | AM26: 68 | AN26: None | AO26: 0 | AP26: 0.69 | AQ26: 36 | AR26: Y | AS26: -0.71 | AT26: =IF(AND(P26="52-wk high",T26>=Settings!$B$7),"Y","N") | AU26: =IF(AND(AD26>=Settings!$B$8,M26>0),"Y","N") | AV26: =IF(OR(AH26>Settings!$B$9,AI26>Settings!$B$9),"Y","N") | AW26: =IF(AJ26<>"Y","n/a",IF(AND(M26>0,AK26>Settings!$B$10),"Y","N")) | AX26: =IF(AO26>=Settings!$B$11,"Y","N") | AY26: =(AT26="Y")+(AU26="Y")+(AV26="Y")+(AW26="Y")+(AX26="Y") | AZ26: =IF(AY26=0,"None",_xlfn.TEXTJOIN(", ",TRUE(),IF(AT26="Y","Breakout",""),IF(AU26="Y","Accumulation",""),IF(AV26="Y","Institutional buying",""),IF(AW26="Y","Long buildup",""),IF(AX26="Y","Momentum leader",""))) | BA26: =IF(BW26="","","Passes "&AY26&" of 5 buy-side scans"&IF(G26="Y","; RED FLAG: filter out using Red flag column","")) | BB26: None | BC26: N | BF26: =IF(R26*100000>=Settings!$B$5,"Y","N") | BG26: =IF(F26>Settings!$B$6,"Y","N") | BH26: -18.31 | BI26: -3.13 | BJ26: -6.05 | BK26: -6.51 | BL26: -0.04 | BM26: -11.45 | BN26: -3.09 | BO26: -5.1 | BP26: -6.45 | BQ26: -7.87 | BR26: Stacked down | BS26: None | BT26: 36.1 | BU26: N | BV26: =IF(OR(BF26<>"Y",BG26<>"Y"),"",(AND(ISNUMBER(BQ26),BQ26>0))+(BR26="Stacked up")+(AND(ISNUMBER(BH26),BH26>=-Settings!$B$17))+(AND(ISNUMBER(BK26),ISNUMBER(BM26),BK26>0,BM26>0))+(AND(ISNUMBER(AQ26),AQ26>=Settings!$B$18))+(AND(ISNUMBER(BT26),BT26>=Settings!$B$19,BT26<=Settings!$B$20))+(AND(ISNUMBER(AS26),AS26>0))+(AND(ISNUMBER(T26),ISNUMBER(M26),T26>=Settings!$B$21,M26>0))+(AND(ISNUMBER(AD26),ISNUMBER(M26),AD26>=Settings!$B$22,M26>0))+(AY26>=1)) | BW26: =IF(OR(AY26=0,BF26<>"Y",BG26<>"Y"),"",1+SUMPRODUCT(($A$6:$A$2604=A26)*($AY$6:$AY$2604>0)*($BF$6:$BF$2604="Y")*($BG$6:$BG$2604="Y")*(($AY$6:$AY$2604>AY26)+($AY$6:$AY$2604=AY26)*($AD$6:$AD$2604>AD26))))
A27: 46296 | B27: NTPC | C27: INE733E01010 | D27: Power | E27: Nifty 50 | F27: 305542 | G27: N | I27: N | J27: =IF(K27="","N","Y") | K27: =_xlfn.TEXTJOIN("; ",TRUE,IF(P27="52-wk low","52-wk low",""),IF(AND(AD27>=Settings!$B$12,M27<0),"Distribution",""),IF(AND(AJ27="Y",M27<0,AK27<-Settings!$B$13),"Long unwinding",""),IF(AND(AJ27="Y",M27<0,AK27>Settings!$B$13),"Short buildup","")) | L27: 315.1 | M27: -2.37 | N27: 1827 | O27: None | P27: 52-wk low | Q27: 100.94 | R27: 75.98 | S27: 1.31 | T27: 1.21 | U27: 0.98 | V27: 0.74 | W27: 3 | Y27: None | Z27: 61.51 | AA27: 0.97 | AB27: 1.01 | AC27: 1.28 | AD27: 1.22 | AE27: 0.97 | AF27: 1.02 | AG27: Normal | AH27: 0 | AI27: 0 | AJ27: Y | AK27: -2.32 | AL27: Long unwinding | AM27: 104 | AN27: 200 Mom 30 | AO27: 1 | AP27: 0.56 | AQ27: 13 | AR27: Y | AS27: 3.38 | AT27: =IF(AND(P27="52-wk high",T27>=Settings!$B$7),"Y","N") | AU27: =IF(AND(AD27>=Settings!$B$8,M27>0),"Y","N") | AV27: =IF(OR(AH27>Settings!$B$9,AI27>Settings!$B$9),"Y","N") | AW27: =IF(AJ27<>"Y","n/a",IF(AND(M27>0,AK27>Settings!$B$10),"Y","N")) | AX27: =IF(AO27>=Settings!$B$11,"Y","N") | AY27: =(AT27="Y")+(AU27="Y")+(AV27="Y")+(AW27="Y")+(AX27="Y") | AZ27: =IF(AY27=0,"None",_xlfn.TEXTJOIN(", ",TRUE(),IF(AT27="Y","Breakout",""),IF(AU27="Y","Accumulation",""),IF(AV27="Y","Institutional buying",""),IF(AW27="Y","Long buildup",""),IF(AX27="Y","Momentum leader",""))) | BA27: =IF(BW27="","","Passes "&AY27&" of 5 buy-side scans"&IF(G27="Y","; RED FLAG: filter out using Red flag column","")) | BB27: None | BC27: N | BF27: =IF(R27*100000>=Settings!$B$5,"Y","N") | BG27: =IF(F27>Settings!$B$6,"Y","N") | BH27: -23.96 | BI27: -3.52 | BJ27: -3.79 | BK27: -11.96 | BL27: -13.59 | BM27: -7.39 | BN27: -3.59 | BO27: -5.93 | BP27: -8.58 | BQ27: -10.12 | BR27: Stacked down | BS27: None | BT27: 25.6 | BU27: N | BV27: =IF(OR(BF27<>"Y",BG27<>"Y"),"",(AND(ISNUMBER(BQ27),BQ27>0))+(BR27="Stacked up")+(AND(ISNUMBER(BH27),BH27>=-Settings!$B$17))+(AND(ISNUMBER(BK27),ISNUMBER(BM27),BK27>0,BM27>0))+(AND(ISNUMBER(AQ27),AQ27>=Settings!$B$18))+(AND(ISNUMBER(BT27),BT27>=Settings!$B$19,BT27<=Settings!$B$20))+(AND(ISNUMBER(AS27),AS27>0))+(AND(ISNUMBER(T27),ISNUMBER(M27),T27>=Settings!$B$21,M27>0))+(AND(ISNUMBER(AD27),ISNUMBER(M27),AD27>=Settings!$B$22,M27>0))+(AY27>=1)) | BW27: =IF(OR(AY27=0,BF27<>"Y",BG27<>"Y"),"",1+SUMPRODUCT(($A$6:$A$2604=A27)*($AY$6:$AY$2604>0)*($BF$6:$BF$2604="Y")*($BG$6:$BG$2604="Y")*(($AY$6:$AY$2604>AY27)+($AY$6:$AY$2604=AY27)*($AD$6:$AD$2604>AD27))))
A28: 46296 | B28: ETERNAL | C28: INE758T01015 | D28: Consumer Services | E28: Nifty 50 | F28: 302925 | G28: N | I28: N | J28: =IF(K28="","N","Y") | K28: =_xlfn.TEXTJOIN("; ",TRUE,IF(P28="52-wk low","52-wk low",""),IF(AND(AD28>=Settings!$B$12,M28<0),"Distribution",""),IF(AND(AJ28="Y",M28<0,AK28<-Settings!$B$13),"Long unwinding",""),IF(AND(AJ28="Y",M28<0,AK28>Settings!$B$13),"Short buildup","")) | L28: 313.9 | M28: -1.91 | N28: 1583 | O28: None | P28: None | Q28: 297.17 | R28: 198.11 | S28: 1.54 | T28: 0.94 | U28: 0.96 | V28: 0.64 | W28: 0 | Y28: By value | Z28: 51.58 | AA28: 0.89 | AB28: 0.93 | AC28: 1.35 | AD28: 0.82 | AE28: 0.88 | AF28: 1.04 | AG28: Normal | AH28: 0 | AI28: 0 | AJ28: Y | AK28: -1.52 | AL28: Long unwinding | AM28: 18 | AN28: None | AO28: 0 | AP28: 1.24 | AQ28: 71 | AR28: Y | AS28: 2.34 | AT28: =IF(AND(P28="52-wk high",T28>=Settings!$B$7),"Y","N") | AU28: =IF(AND(AD28>=Settings!$B$8,M28>0),"Y","N") | AV28: =IF(OR(AH28>Settings!$B$9,AI28>Settings!$B$9),"Y","N") | AW28: =IF(AJ28<>"Y","n/a",IF(AND(M28>0,AK28>Settings!$B$10),"Y","N")) | AX28: =IF(AO28>=Settings!$B$11,"Y","N") | AY28: =(AT28="Y")+(AU28="Y")+(AV28="Y")+(AW28="Y")+(AX28="Y") | AZ28: =IF(AY28=0,"None",_xlfn.TEXTJOIN(", ",TRUE(),IF(AT28="Y","Breakout",""),IF(AU28="Y","Accumulation",""),IF(AV28="Y","Institutional buying",""),IF(AW28="Y","Long buildup",""),IF(AX28="Y","Momentum leader",""))) | BA28: =IF(BW28="","","Passes "&AY28&" of 5 buy-side scans"&IF(G28="Y","; RED FLAG: filter out using Red flag column","")) | BB28: None | BC28: Y | BD28: PE > 50 | BF28: =IF(R28*100000>=Settings!$B$5,"Y","N") | BG28: =IF(F28>Settings!$B$6,"Y","N") | BH28: -14.81 | BI28: -6.44 | BJ28: -4.23 | BK28: 12.23 | BL28: 32.72 | BM28: -4.59 | BN28: -3.75 | BO28: -0.79 | BP28: 4.18 | BQ28: 6.84 | BR28: Mixed | BS28: None | BT28: 31.5 | BU28: N | BV28: =IF(OR(BF28<>"Y",BG28<>"Y"),"",(AND(ISNUMBER(BQ28),BQ28>0))+(BR28="Stacked up")+(AND(ISNUMBER(BH28),BH28>=-Settings!$B$17))+(AND(ISNUMBER(BK28),ISNUMBER(BM28),BK28>0,BM28>0))+(AND(ISNUMBER(AQ28),AQ28>=Settings!$B$18))+(AND(ISNUMBER(BT28),BT28>=Settings!$B$19,BT28<=Settings!$B$20))+(AND(ISNUMBER(AS28),AS28>0))+(AND(ISNUMBER(T28),ISNUMBER(M28),T28>=Settings!$B$21,M28>0))+(AND(ISNUMBER(AD28),ISNUMBER(M28),AD28>=Settings!$B$22,M28>0))+(AY28>=1)) | BW28: =IF(OR(AY28=0,BF28<>"Y",BG28<>"Y"),"",1+SUMPRODUCT(($A$6:$A$2604=A28)*($AY$6:$AY$2604>0)*($BF$6:$BF$2604="Y")*($BG$6:$BG$2604="Y")*(($AY$6:$AY$2604>AY28)+($AY$6:$AY$2604=AY28)*($AD$6:$AD$2604>AD28))))
A29: 46296 | B29: JSWSTEEL | C29: INE019A01038 | D29: Metals & Mining | E29: Nifty 50 | F29: 301524 | G29: N | I29: N | J29: =IF(K29="","N","Y") | K29: =_xlfn.TEXTJOIN("; ",TRUE,IF(P29="52-wk low","52-wk low",""),IF(AND(AD29>=Settings!$B$12,M29<0),"Distribution",""),IF(AND(AJ29="Y",M29<0,AK29<-Settings!$B$13),"Long unwinding",""),IF(AND(AJ29="Y",M29<0,AK29>Settings!$B$13),"Short buildup","")) | L29: 1233 | M29: -1.63 | N29: 1420 | O29: None | P29: None | Q29: 31.58 | R29: 14.49 | S29: 2.31 | T29: 1.97 | U29: 1.92 | V29: 0.87 | W29: 4 | X29: 102 | Y29: None | Z29: 58.44 | AA29: 1.04 | AB29: 1.04 | AC29: 2.36 | AD29: 2 | AE29: 2.04 | AF29: 1.03 | AG29: Normal | AH29: 0 | AI29: 0 | AJ29: Y | AK29: -1.07 | AL29: Long unwinding | AM29: 70 | AN29: None | AO29: 0 | AP29: 1.1 | AQ29: 66 | AR29: Y | AS29: -1.09 | AT29: =IF(AND(P29="52-wk high",T29>=Settings!$B$7),"Y","N") | AU29: =IF(AND(AD29>=Settings!$B$8,M29>0),"Y","N") | AV29: =IF(OR(AH29>Settings!$B$9,AI29>Settings!$B$9),"Y","N") | AW29: =IF(AJ29<>"Y","n/a",IF(AND(M29>0,AK29>Settings!$B$10),"Y","N")) | AX29: =IF(AO29>=Settings!$B$11,"Y","N") | AY29: =(AT29="Y")+(AU29="Y")+(AV29="Y")+(AW29="Y")+(AX29="Y") | AZ29: =IF(AY29=0,"None",_xlfn.TEXTJOIN(", ",TRUE(),IF(AT29="Y","Breakout",""),IF(AU29="Y","Accumulation",""),IF(AV29="Y","Institutional buying",""),IF(AW29="Y","Long buildup",""),IF(AX29="Y","Momentum leader",""))) | BA29: =IF(BW29="","","Passes "&AY29&" of 5 buy-side scans"&IF(G29="Y","; RED FLAG: filter out using Red flag column","")) | BB29: None | BC29: N | BF29: =IF(R29*100000>=Settings!$B$5,"Y","N") | BG29: =IF(F29>Settings!$B$6,"Y","N") | BH29: -8.73 | BI29: -3.16 | BJ29: -6.13 | BK29: 1.38 | BL29: 8.12 | BM29: 7.58 | BN29: -3.14 | BO29: -3.5 | BP29: -2.75 | BQ29: -0.81 | BR29: Mixed | BS29: None | BT29: 34.7 | BU29: N | BV29: =IF(OR(BF29<>"Y",BG29<>"Y"),"",(AND(ISNUMBER(BQ29),BQ29>0))+(BR29="Stacked up")+(AND(ISNUMBER(BH29),BH29>=-Settings!$B$17))+(AND(ISNUMBER(BK29),ISNUMBER(BM29),BK29>0,BM29>0))+(AND(ISNUMBER(AQ29),AQ29>=Settings!$B$18))+(AND(ISNUMBER(BT29),BT29>=Settings!$B$19,BT29<=Settings!$B$20))+(AND(ISNUMBER(AS29),AS29>0))+(AND(ISNUMBER(T29),ISNUMBER(M29),T29>=Settings!$B$21,M29>0))+(AND(ISNUMBER(AD29),ISNUMBER(M29),AD29>=Settings!$B$22,M29>0))+(AY29>=1)) | BW29: =IF(OR(AY29=0,BF29<>"Y",BG29<>"Y"),"",1+SUMPRODUCT(($A$6:$A$2604=A29)*($AY$6:$AY$2604>0)*($BF$6:$BF$2604="Y")*($BG$6:$BG$2604="Y")*(($AY$6:$AY$2604>AY29)+($AY$6:$AY$2604=AY29)*($AD$6:$AD$2604>AD29))))
A30: 46296 | B30: BEL | C30: INE263A01024 | D30: Capital Goods | E30: Nifty 50 | F30: 280038 | G30: N | I30: N | J30: =IF(K30="","N","Y") | K30: =_xlfn.TEXTJOIN("; ",TRUE,IF(P30="52-wk low","52-wk low",""),IF(AND(AD30>=Settings!$B$12,M30<0),"Distribution",""),IF(AND(AJ30="Y",M30<0,AK30<-Settings!$B$13),"Long unwinding",""),IF(AND(AJ30="Y",M30<0,AK30>Settings!$B$13),"Short buildup","")) | L30: 383.1 | M30: -1.34 | N30: 1220 | O30: None | P30: 52-wk low | Q30: 102.5 | R30: 100.67 | S30: 1.01 | T30: 0.92 | U30: 0.88 | V30: 0.86 | W30: 3 | Y30: None | Z30: 55.07 | AA30: 0.97 | AB30: 0.95 | AC30: 0.99 | AD30: 0.88 | AE30: 0.88 | AF30: 1.02 | AG30: Normal | AH30: 0 | AI30: 0 | AJ30: Y | AK30: -0.58 | AL30: Long unwinding | AM30: 71 | AN30: 500 Multicap MQ 50; TotalMkt MQ 50 | AO30: 2 | AP30: 0.66 | AQ30: 32 | AR30: Y | AS30: 5.9 | AT30: =IF(AND(P30="52-wk high",T30>=Settings!$B$7),"Y","N") | AU30: =IF(AND(AD30>=Settings!$B$8,M30>0),"Y","N") | AV30: =IF(OR(AH30>Settings!$B$9,AI30>Settings!$B$9),"Y","N") | AW30: =IF(AJ30<>"Y","n/a",IF(AND(M30>0,AK30>Settings!$B$10),"Y","N")) | AX30: =IF(AO30>=Settings!$B$11,"Y","N") | AY30: =(AT30="Y")+(AU30="Y")+(AV30="Y")+(AW30="Y")+(AX30="Y") | AZ30: =IF(AY30=0,"None",_xlfn.TEXTJOIN(", ",TRUE(),IF(AT30="Y","Breakout",""),IF(AU30="Y","Accumulation",""),IF(AV30="Y","Institutional buying",""),IF(AW30="Y","Long buildup",""),IF(AX30="Y","Momentum leader",""))) | BA30: =IF(BW30="","","Passes "&AY30&" of 5 buy-side scans"&IF(G30="Y","; RED FLAG: filter out using Red flag column","")) | BB30: None | BC30: N | BF30: =IF(R30*100000>=Settings!$B$5,"Y","N") | BG30: =IF(F30>Settings!$B$6,"Y","N") | BH30: -19.08 | BI30: -2.27 | BJ30: -6.83 | BK30: -7.96 | BL30: -8.5 | BM30: -5.76 | BN30: -2.96 | BO30: -4.5 | BP30: -5.95 | BQ30: -6.82 | BR30: Stacked down | BS30: None | BT30: 33 | BU30: N | BV30: =IF(OR(BF30<>"Y",BG30<>"Y"),"",(AND(ISNUMBER(BQ30),BQ30>0))+(BR30="Stacked up")+(AND(ISNUMBER(BH30),BH30>=-Settings!$B$17))+(AND(ISNUMBER(BK30),ISNUMBER(BM30),BK30>0,BM30>0))+(AND(ISNUMBER(AQ30),AQ30>=Settings!$B$18))+(AND(ISNUMBER(BT30),BT30>=Settings!$B$19,BT30<=Settings!$B$20))+(AND(ISNUMBER(AS30),AS30>0))+(AND(ISNUMBER(T30),ISNUMBER(M30),T30>=Settings!$B$21,M30>0))+(AND(ISNUMBER(AD30),ISNUMBER(M30),AD30>=Settings!$B$22,M30>0))+(AY30>=1)) | BW30: =IF(OR(AY30=0,BF30<>"Y",BG30<>"Y"),"",1+SUMPRODUCT(($A$6:$A$2604=A30)*($AY$6:$AY$2604>0)*($BF$6:$BF$2604="Y")*($BG$6:$BG$2604="Y")*(($AY$6:$AY$2604>AY30)+($AY$6:$AY$2604=AY30)*($AD$6:$AD$2604>AD30))))
A31: 46296 | B31: ONGC | C31: INE213A01029 | D31: Oil Gas & Consumable Fuels | E31: Nifty 50 | F31: 279748 | G31: N | I31: N | J31: =IF(K31="","N","Y") | K31: =_xlfn.TEXTJOIN("; ",TRUE,IF(P31="52-wk low","52-wk low",""),IF(AND(AD31>=Settings!$B$12,M31<0),"Distribution",""),IF(AND(AJ31="Y",M31<0,AK31<-Settings!$B$13),"Long unwinding",""),IF(AND(AJ31="Y",M31<0,AK31>Settings!$B$13),"Short buildup","")) | L31: 222.37 | M31: -1.52 | N31: 1342 | O31: None | P31: 52-wk low | Q31: 131 | R31: 103.09 | S31: 1.27 | T31: 1.15 | U31: 0.93 | V31: 0.73 | W31: 1 | Y31: None | Z31: 62.87 | AA31: 1.09 | AB31: 1.09 | AC31: 1.44 | AD31: 1.28 | AE31: 1.06 | AF31: 1.02 | AG31: Normal | AH31: 0 | AI31: 0 | AJ31: Y | AK31: 1.42 | AL31: Short buildup | AM31: 141 | AN31: None | AO31: 0 | AP31: 0.53 | AQ31: 8 | AR31: Y | AS31: 2.69 | AT31: =IF(AND(P31="52-wk high",T31>=Settings!$B$7),"Y","N") | AU31: =IF(AND(AD31>=Settings!$B$8,M31>0),"Y","N") | AV31: =IF(OR(AH31>Settings!$B$9,AI31>Settings!$B$9),"Y","N") | AW31: =IF(AJ31<>"Y","n/a",IF(AND(M31>0,AK31>Settings!$B$10),"Y","N")) | AX31: =IF(AO31>=Settings!$B$11,"Y","N") | AY31: =(AT31="Y")+(AU31="Y")+(AV31="Y")+(AW31="Y")+(AX31="Y") | AZ31: =IF(AY31=0,"None",_xlfn.TEXTJOIN(", ",TRUE(),IF(AT31="Y","Breakout",""),IF(AU31="Y","Accumulation",""),IF(AV31="Y","Institutional buying",""),IF(AW31="Y","Long buildup",""),IF(AX31="Y","Momentum leader",""))) | BA31: =IF(BW31="","","Passes "&AY31&" of 5 buy-side scans"&IF(G31="Y","; RED FLAG: filter out using Red flag column","")) | BB31: None | BC31: N | BF31: =IF(R31*100000>=Settings!$B$5,"Y","N") | BG31: =IF(F31>Settings!$B$6,"Y","N") | BH31: -27.68 | BI31: -6.96 | BJ31: -5.95 | BK31: -5.37 | BL31: -22.8 | BM31: -8.5 | BN31: -4.51 | BO31: -6.38 | BP31: -9.16 | BQ31: -10.96 | BR31: Stacked down | BS31: None | BT31: 25.3 | BU31: N | BV31: =IF(OR(BF31<>"Y",BG31<>"Y"),"",(AND(ISNUMBER(BQ31),BQ31>0))+(BR31="Stacked up")+(AND(ISNUMBER(BH31),BH31>=-Settings!$B$17))+(AND(ISNUMBER(BK31),ISNUMBER(BM31),BK31>0,BM31>0))+(AND(ISNUMBER(AQ31),AQ31>=Settings!$B$18))+(AND(ISNUMBER(BT31),BT31>=Settings!$B$19,BT31<=Settings!$B$20))+(AND(ISNUMBER(AS31),AS31>0))+(AND(ISNUMBER(T31),ISNUMBER(M31),T31>=Settings!$B$21,M31>0))+(AND(ISNUMBER(AD31),ISNUMBER(M31),AD31>=Settings!$B$22,M31>0))+(AY31>=1)) | BW31: =IF(OR(AY31=0,BF31<>"Y",BG31<>"Y"),"",1+SUMPRODUCT(($A$6:$A$2604=A31)*($AY$6:$AY$2604>0)*($BF$6:$BF$2604="Y")*($BG$6:$BG$2604="Y")*(($AY$6:$AY$2604>AY31)+($AY$6:$AY$2604=AY31)*($AD$6:$AD$2604>AD31))))
A32: 46296 | B32: BAJAJFINSV | C32: INE918I01026 | D32: Financial Services | E32: Nifty 50 | F32: 277573 | G32: N | I32: N | J32: =IF(K32="","N","Y") | K32: =_xlfn.TEXTJOIN("; ",TRUE,IF(P32="52-wk low","52-wk low",""),IF(AND(AD32>=Settings!$B$12,M32<0),"Distribution",""),IF(AND(AJ32="Y",M32<0,AK32<-Settings!$B$13),"Long unwinding",""),IF(AND(AJ32="Y",M32<0,AK32>Settings!$B$13),"Short buildup","")) | L32: 1732.6 | M32: 0.09 | N32: 553 | O32: None | P32: None | Q32: 22.92 | R32: 7.77 | S32: 3.28 | T32: 2.35 | U32: 2.18 | V32: 0.73 | W32: 4 | X32: 53 | Y32: None | Z32: 73.62 | AA32: 1.31 | AB32: 1.3 | AC32: 4.26 | AD32: 3.07 | AE32: 2.8 | AF32: 1.02 | AG32: Normal | AH32: 0 | AI32: 0 | AJ32: Y | AK32: -0.15 | AL32: Short covering | AM32: 121 | AN32: None | AO32: 0 | AP32: 0.74 | AQ32: 42 | AR32: Y | AS32: 0.6 | AT32: =IF(AND(P32="52-wk high",T32>=Settings!$B$7),"Y","N") | AU32: =IF(AND(AD32>=Settings!$B$8,M32>0),"Y","N") | AV32: =IF(OR(AH32>Settings!$B$9,AI32>Settings!$B$9),"Y","N") | AW32: =IF(AJ32<>"Y","n/a",IF(AND(M32>0,AK32>Settings!$B$10),"Y","N")) | AX32: =IF(AO32>=Settings!$B$11,"Y","N") | AY32: =(AT32="Y")+(AU32="Y")+(AV32="Y")+(AW32="Y")+(AX32="Y") | AZ32: =IF(AY32=0,"None",_xlfn.TEXTJOIN(", ",TRUE(),IF(AT32="Y","Breakout",""),IF(AU32="Y","Accumulation",""),IF(AV32="Y","Institutional buying",""),IF(AW32="Y","Long buildup",""),IF(AX32="Y","Momentum leader",""))) | BA32: =IF(BW32="","","Passes "&AY32&" of 5 buy-side scans"&IF(G32="Y","; RED FLAG: filter out using Red flag column","")) | BB32: None | BC32: N | BF32: =IF(R32*100000>=Settings!$B$5,"Y","N") | BG32: =IF(F32>Settings!$B$6,"Y","N") | BH32: -21.07 | BI32: -1.69 | BJ32: -12.14 | BK32: -3.62 | BL32: 5.2 | BM32: -13.67 | BN32: -5.56 | BO32: -8.11 | BP32: -8.21 | BQ32: -9.08 | BR32: Stacked down | BS32: None | BT32: 20.6 | BU32: N | BV32: =IF(OR(BF32<>"Y",BG32<>"Y"),"",(AND(ISNUMBER(BQ32),BQ32>0))+(BR32="Stacked up")+(AND(ISNUMBER(BH32),BH32>=-Settings!$B$17))+(AND(ISNUMBER(BK32),ISNUMBER(BM32),BK32>0,BM32>0))+(AND(ISNUMBER(AQ32),AQ32>=Settings!$B$18))+(AND(ISNUMBER(BT32),BT32>=Settings!$B$19,BT32<=Settings!$B$20))+(AND(ISNUMBER(AS32),AS32>0))+(AND(ISNUMBER(T32),ISNUMBER(M32),T32>=Settings!$B$21,M32>0))+(AND(ISNUMBER(AD32),ISNUMBER(M32),AD32>=Settings!$B$22,M32>0))+(AY32>=1)) | BW32: =IF(OR(AY32=0,BF32<>"Y",BG32<>"Y"),"",1+SUMPRODUCT(($A$6:$A$2604=A32)*($AY$6:$AY$2604>0)*($BF$6:$BF$2604="Y")*($BG$6:$BG$2604="Y")*(($AY$6:$AY$2604>AY32)+($AY$6:$AY$2604=AY32)*($AD$6:$AD$2604>AD32))))
A33: 46296 | B33: BAJAJ-AUTO | C33: INE917I01010 | D33: Automobile and Auto Components | E33: Nifty 50 | F33: 276040 | G33: N | I33: N | J33: =IF(K33="","N","Y") | K33: =_xlfn.TEXTJOIN("; ",TRUE,IF(P33="52-wk low","52-wk low",""),IF(AND(AD33>=Settings!$B$12,M33<0),"Distribution",""),IF(AND(AJ33="Y",M33<0,AK33<-Settings!$B$13),"Long unwinding",""),IF(AND(AJ33="Y",M33<0,AK33>Settings!$B$13),"Short buildup","")) | L33: 10045 | M33: -7.62 | N33: 2569 | O33: Top loser | P33: None | Q33: 14.91 | R33: 2.7 | S33: 7.05 | T33: 5.27 | U33: 4.4 | V33: 0.77 | W33: 2 | X33: 19 | Y33: By value | Z33: 26.54 | AA33: 0.47 | AB33: 0.48 | AC33: 3.25 | AD33: 2.63 | AE33: 2.17 | AF33: 0.93 | AG33: Normal | AH33: 0 | AI33: 0 | AJ33: Y | AK33: -4.46 | AL33: Long unwinding | AM33: 4 | AN33: TotalMkt MQ 50 | AO33: 1 | AP33: 1.37 | AQ33: 75 | AR33: Y | AS33: 0.56 | AT33: =IF(AND(P33="52-wk high",T33>=Settings!$B$7),"Y","N") | AU33: =IF(AND(AD33>=Settings!$B$8,M33>0),"Y","N") | AV33: =IF(OR(AH33>Settings!$B$9,AI33>Settings!$B$9),"Y","N") | AW33: =IF(AJ33<>"Y","n/a",IF(AND(M33>0,AK33>Settings!$B$10),"Y","N")) | AX33: =IF(AO33>=Settings!$B$11,"Y","N") | AY33: =(AT33="Y")+(AU33="Y")+(AV33="Y")+(AW33="Y")+(AX33="Y") | AZ33: =IF(AY33=0,"None",_xlfn.TEXTJOIN(", ",TRUE(),IF(AT33="Y","Breakout",""),IF(AU33="Y","Accumulation",""),IF(AV33="Y","Institutional buying",""),IF(AW33="Y","Long buildup",""),IF(AX33="Y","Momentum leader",""))) | BA33: =IF(BW33="","","Passes "&AY33&" of 5 buy-side scans"&IF(G33="Y","; RED FLAG: filter out using Red flag column","")) | BB33: Upper | BC33: N | BF33: =IF(R33*100000>=Settings!$B$5,"Y","N") | BG33: =IF(F33>Settings!$B$6,"Y","N") | BH33: -19.45 | BI33: -10.38 | BJ33: -18.74 | BK33: 2.06 | BL33: 12.92 | BM33: 16.44 | BN33: -10.73 | BO33: -11.05 | BP33: -8.26 | BQ33: -3.46 | BR33: Mixed | BS33: Bearish cross | BT33: 14.8 | BU33: N | BV33: =IF(OR(BF33<>"Y",BG33<>"Y"),"",(AND(ISNUMBER(BQ33),BQ33>0))+(BR33="Stacked up")+(AND(ISNUMBER(BH33),BH33>=-Settings!$B$17))+(AND(ISNUMBER(BK33),ISNUMBER(BM33),BK33>0,BM33>0))+(AND(ISNUMBER(AQ33),AQ33>=Settings!$B$18))+(AND(ISNUMBER(BT33),BT33>=Settings!$B$19,BT33<=Settings!$B$20))+(AND(ISNUMBER(AS33),AS33>0))+(AND(ISNUMBER(T33),ISNUMBER(M33),T33>=Settings!$B$21,M33>0))+(AND(ISNUMBER(AD33),ISNUMBER(M33),AD33>=Settings!$B$22,M33>0))+(AY33>=1)) | BW33: =IF(OR(AY33=0,BF33<>"Y",BG33<>"Y"),"",1+SUMPRODUCT(($A$6:$A$2604=A33)*($AY$6:$AY$2604>0)*($BF$6:$BF$2604="Y")*($BG$6:$BG$2604="Y")*(($AY$6:$AY$2604>AY33)+($AY$6:$AY$2604=AY33)*($AD$6:$AD$2604>AD33))))
A34: 46296 | B34: COALINDIA | C34: INE522F01014 | D34: Oil Gas & Consumable Fuels | E34: Nifty 50 | F34: 259081 | G34: N | I34: N | J34: =IF(K34="","N","Y") | K34: =_xlfn.TEXTJOIN("; ",TRUE,IF(P34="52-wk low","52-wk low",""),IF(AND(AD34>=Settings!$B$12,M34<0),"Distribution",""),IF(AND(AJ34="Y",M34<0,AK34<-Settings!$B$13),"Long unwinding",""),IF(AND(AJ34="Y",M34<0,AK34>Settings!$B$13),"Short buildup","")) | L34: 420.4 | M34: -1.08 | N34: 1086 | O34: None | P34: None | Q34: 75.15 | R34: 82.15 | S34: 0.79 | T34: 0.87 | U34: 0.71 | V34: 0.77 | W34: 4 | Y34: None | Z34: 52.92 | AA34: 0.94 | AB34: 0.86 | AC34: 0.82 | AD34: 0.77 | AE34: 0.69 | AF34: 1.02 | AG34: Normal | AH34: 0 | AI34: 0 | AJ34: Y | AK34: -1.05 | AL34: Long unwinding | AM34: 45 | AN34: 500 Multicap MQ 50; TotalMkt MQ 50 | AO34: 2 | AP34: 0.83 | AQ34: 51 | AR34: Y | AS34: 2.69 | AT34: =IF(AND(P34="52-wk high",T34>=Settings!$B$7),"Y","N") | AU34: =IF(AND(AD34>=Settings!$B$8,M34>0),"Y","N") | AV34: =IF(OR(AH34>Settings!$B$9,AI34>Settings!$B$9),"Y","N") | AW34: =IF(AJ34<>"Y","n/a",IF(AND(M34>0,AK34>Settings!$B$10),"Y","N")) | AX34: =IF(AO34>=Settings!$B$11,"Y","N") | AY34: =(AT34="Y")+(AU34="Y")+(AV34="Y")+(AW34="Y")+(AX34="Y") | AZ34: =IF(AY34=0,"None",_xlfn.TEXTJOIN(", ",TRUE(),IF(AT34="Y","Breakout",""),IF(AU34="Y","Accumulation",""),IF(AV34="Y","Institutional buying",""),IF(AW34="Y","Long buildup",""),IF(AX34="Y","Momentum leader",""))) | BA34: =IF(BW34="","","Passes "&AY34&" of 5 buy-side scans"&IF(G34="Y","; RED FLAG: filter out using Red flag column","")) | BB34: None | BC34: N | BF34: =IF(R34*100000>=Settings!$B$5,"Y","N") | BG34: =IF(F34>Settings!$B$6,"Y","N") | BH34: -14.42 | BI34: -0.38 | BJ34: 4.68 | BK34: -3.3 | BL34: -6.45 | BM34: 8.21 | BN34: -0.03 | BO34: -0.08 | BP34: -1.2 | BQ34: -1.04 | BR34: Mixed | BS34: None | BT34: 49 | BU34: N | BV34: =IF(OR(BF34<>"Y",BG34<>"Y"),"",(AND(ISNUMBER(BQ34),BQ34>0))+(BR34="Stacked up")+(AND(ISNUMBER(BH34),BH34>=-Settings!$B$17))+(AND(ISNUMBER(BK34),ISNUMBER(BM34),BK34>0,BM34>0))+(AND(ISNUMBER(AQ34),AQ34>=Settings!$B$18))+(AND(ISNUMBER(BT34),BT34>=Settings!$B$19,BT34<=Settings!$B$20))+(AND(ISNUMBER(AS34),AS34>0))+(AND(ISNUMBER(T34),ISNUMBER(M34),T34>=Settings!$B$21,M34>0))+(AND(ISNUMBER(AD34),ISNUMBER(M34),AD34>=Settings!$B$22,M34>0))+(AY34>=1)) | BW34: =IF(OR(AY34=0,BF34<>"Y",BG34<>"Y"),"",1+SUMPRODUCT(($A$6:$A$2604=A34)*($AY$6:$AY$2604>0)*($BF$6:$BF$2604="Y")*($BG$6:$BG$2604="Y")*(($AY$6:$AY$2604>AY34)+($AY$6:$AY$2604=AY34)*($AD$6:$AD$2604>AD34))))
A35: 46296 | B35: NESTLEIND | C35: INE239A01024 | D35: Fast Moving Consumer Goods | E35: Nifty 50 | F35: 252166 | G35: N | I35: N | J35: =IF(K35="","N","Y") | K35: =_xlfn.TEXTJOIN("; ",TRUE,IF(P35="52-wk low","52-wk low",""),IF(AND(AD35>=Settings!$B$12,M35<0),"Distribution",""),IF(AND(AJ35="Y",M35<0,AK35<-Settings!$B$13),"Long unwinding",""),IF(AND(AJ35="Y",M35<0,AK35>Settings!$B$13),"Short buildup","")) | L35: 1307.7 | M35: -0.18 | N35: 670 | O35: None | P35: None | Q35: 16.27 | R35: 11.42 | S35: 1.47 | T35: 0.9 | U35: 0.87 | V35: 0.61 | W35: 1 | Y35: None | Z35: 64.34 | AA35: 1.04 | AB35: 1.06 | AC35: 1.53 | AD35: 0.98 | AE35: 0.93 | AF35: 1.03 | AG35: Normal | AH35: 0 | AI35: 0 | AJ35: Y | AK35: 2.45 | AL35: Short buildup | AM35: 108 | AN35: None | AO35: 0 | AP35: 1.32 | AQ35: 74 | AR35: Y | AS35: 2.11 | AT35: =IF(AND(P35="52-wk high",T35>=Settings!$B$7),"Y","N") | AU35: =IF(AND(AD35>=Settings!$B$8,M35>0),"Y","N") | AV35: =IF(OR(AH35>Settings!$B$9,AI35>Settings!$B$9),"Y","N") | AW35: =IF(AJ35<>"Y","n/a",IF(AND(M35>0,AK35>Settings!$B$10),"Y","N")) | AX35: =IF(AO35>=Settings!$B$11,"Y","N") | AY35: =(AT35="Y")+(AU35="Y")+(AV35="Y")+(AW35="Y")+(AX35="Y") | AZ35: =IF(AY35=0,"None",_xlfn.TEXTJOIN(", ",TRUE(),IF(AT35="Y","Breakout",""),IF(AU35="Y","Accumulation",""),IF(AV35="Y","Institutional buying",""),IF(AW35="Y","Long buildup",""),IF(AX35="Y","Momentum leader",""))) | BA35: =IF(BW35="","","Passes "&AY35&" of 5 buy-side scans"&IF(G35="Y","; RED FLAG: filter out using Red flag column","")) | BB35: None | BC35: Y | BD35: PE > 50 | BF35: =IF(R35*100000>=Settings!$B$5,"Y","N") | BG35: =IF(F35>Settings!$B$6,"Y","N") | BH35: -15.8 | BI35: -3.21 | BJ35: -9.07 | BK35: -10.05 | BL35: 10.75 | BM35: 12.11 | BN35: -4.7 | BO35: -7.15 | BP35: -7.05 | BQ35: -4.43 | BR35: Mixed | BS35: None | BT35: 26.5 | BU35: N | BV35: =IF(OR(BF35<>"Y",BG35<>"Y"),"",(AND(ISNUMBER(BQ35),BQ35>0))+(BR35="Stacked up")+(AND(ISNUMBER(BH35),BH35>=-Settings!$B$17))+(AND(ISNUMBER(BK35),ISNUMBER(BM35),BK35>0,BM35>0))+(AND(ISNUMBER(AQ35),AQ35>=Settings!$B$18))+(AND(ISNUMBER(BT35),BT35>=Settings!$B$19,BT35<=Settings!$B$20))+(AND(ISNUMBER(AS35),AS35>0))+(AND(ISNUMBER(T35),ISNUMBER(M35),T35>=Settings!$B$21,M35>0))+(AND(ISNUMBER(AD35),ISNUMBER(M35),AD35>=Settings!$B$22,M35>0))+(AY35>=1)) | BW35: =IF(OR(AY35=0,BF35<>"Y",BG35<>"Y"),"",1+SUMPRODUCT(($A$6:$A$2604=A35)*($AY$6:$AY$2604>0)*($BF$6:$BF$2604="Y")*($BG$6:$BG$2604="Y")*(($AY$6:$AY$2604>AY35)+($AY$6:$AY$2604=AY35)*($AD$6:$AD$2604>AD35))))
A36: 46296 | B36: POWERGRID | C36: INE752E01010 | D36: Power | E36: Nifty 50 | F36: 236747 | G36: N | I36: N | J36: =IF(K36="","N","Y") | K36: =_xlfn.TEXTJOIN("; ",TRUE,IF(P36="52-wk low","52-wk low",""),IF(AND(AD36>=Settings!$B$12,M36<0),"Distribution",""),IF(AND(AJ36="Y",M36<0,AK36<-Settings!$B$13),"Long unwinding",""),IF(AND(AJ36="Y",M36<0,AK36>Settings!$B$13),"Short buildup","")) | L36: 254.55 | M36: -2.28 | N36: 1781 | O36: None | P36: None | Q36: 109.77 | R36: 100.7 | S36: 1.1 | T36: 1.21 | U36: 1.06 | V36: 0.97 | W36: 8 | X36: 280 | Y36: None | Z36: 66.25 | AA36: 1.05 | AB36: 1.08 | AC36: 1.15 | AD36: 1.31 | AE36: 1.13 | AF36: 1.03 | AG36: Normal | AH36: 0 | AI36: 0 | AJ36: Y | AK36: 0.84 | AL36: Short buildup | AM36: 118 | AN36: None | AO36: 0 | AP36: 0.57 | AQ36: 13 | AR36: Y | AS36: 3.38 | AT36: =IF(AND(P36="52-wk high",T36>=Settings!$B$7),"Y","N") | AU36: =IF(AND(AD36>=Settings!$B$8,M36>0),"Y","N") | AV36: =IF(OR(AH36>Settings!$B$9,AI36>Settings!$B$9),"Y","N") | AW36: =IF(AJ36<>"Y","n/a",IF(AND(M36>0,AK36>Settings!$B$10),"Y","N")) | AX36: =IF(AO36>=Settings!$B$11,"Y","N") | AY36: =(AT36="Y")+(AU36="Y")+(AV36="Y")+(AW36="Y")+(AX36="Y") | AZ36: =IF(AY36=0,"None",_xlfn.TEXTJOIN(", ",TRUE(),IF(AT36="Y","Breakout",""),IF(AU36="Y","Accumulation",""),IF(AV36="Y","Institutional buying",""),IF(AW36="Y","Long buildup",""),IF(AX36="Y","Momentum leader",""))) | BA36: =IF(BW36="","","Passes "&AY36&" of 5 buy-side scans"&IF(G36="Y","; RED FLAG: filter out using Red flag column","")) | BB36: None | BC36: N | BF36: =IF(R36*100000>=Settings!$B$5,"Y","N") | BG36: =IF(F36>Settings!$B$6,"Y","N") | BH36: -21.66 | BI36: -4.45 | BJ36: -3.78 | BK36: -11.48 | BL36: -13.06 | BM36: -9.3 | BN36: -3.88 | BO36: -5.79 | BP36: -8.05 | BQ36: -9.74 | BR36: Stacked down | BS36: None | BT36: 30.7 | BU36: N | BV36: =IF(OR(BF36<>"Y",BG36<>"Y"),"",(AND(ISNUMBER(BQ36),BQ36>0))+(BR36="Stacked up")+(AND(ISNUMBER(BH36),BH36>=-Settings!$B$17))+(AND(ISNUMBER(BK36),ISNUMBER(BM36),BK36>0,BM36>0))+(AND(ISNUMBER(AQ36),AQ36>=Settings!$B$18))+(AND(ISNUMBER(BT36),BT36>=Settings!$B$19,BT36<=Settings!$B$20))+(AND(ISNUMBER(AS36),AS36>0))+(AND(ISNUMBER(T36),ISNUMBER(M36),T36>=Settings!$B$21,M36>0))+(AND(ISNUMBER(AD36),ISNUMBER(M36),AD36>=Settings!$B$22,M36>0))+(AY36>=1)) | BW36: =IF(OR(AY36=0,BF36<>"Y",BG36<>"Y"),"",1+SUMPRODUCT(($A$6:$A$2604=A36)*($AY$6:$AY$2604>0)*($BF$6:$BF$2604="Y")*($BG$6:$BG$2604="Y")*(($AY$6:$AY$2604>AY36)+($AY$6:$AY$2604=AY36)*($AD$6:$AD$2604>AD36))))
A37: 46296 | B37: ASIANPAINT | C37: INE021A01026 | D37: Consumer Durables | E37: Nifty 50 | F37: 230879 | G37: N | I37: N | J37: =IF(K37="","N","Y") | K37: =_xlfn.TEXTJOIN("; ",TRUE,IF(P37="52-wk low","52-wk low",""),IF(AND(AD37>=Settings!$B$12,M37<0),"Distribution",""),IF(AND(AJ37="Y",M37<0,AK37<-Settings!$B$13),"Long unwinding",""),IF(AND(AJ37="Y",M37<0,AK37>Settings!$B$13),"Short buildup","")) | L37: 2407 | M37: 0.18 | N37: 529 | O37: None | P37: None | Q37: 10.06 | R37: 5.6 | S37: 1.88 | T37: 1.35 | U37: 1 | V37: 0.56 | W37: 1 | Y37: None | Z37: 70.4 | AA37: 1.19 | AB37: 1.26 | AC37: 2.19 | AD37: 1.77 | AE37: 1.27 | AF37: 1.12 | AG37: Normal | AH37: 0 | AI37: 0 | AJ37: Y | AK37: -0.33 | AL37: Short covering | AM37: 140 | AN37: 500 Multicap MQ 50 | AO37: 1 | AP37: 1.02 | AQ37: 63 | AR37: Y | AS37: 0.75 | AT37: =IF(AND(P37="52-wk high",T37>=Settings!$B$7),"Y","N") | AU37: =IF(AND(AD37>=Settings!$B$8,M37>0),"Y","N") | AV37: =IF(OR(AH37>Settings!$B$9,AI37>Settings!$B$9),"Y","N") | AW37: =IF(AJ37<>"Y","n/a",IF(AND(M37>0,AK37>Settings!$B$10),"Y","N")) | AX37: =IF(AO37>=Settings!$B$11,"Y","N") | AY37: =(AT37="Y")+(AU37="Y")+(AV37="Y")+(AW37="Y")+(AX37="Y") | AZ37: =IF(AY37=0,"None",_xlfn.TEXTJOIN(", ",TRUE(),IF(AT37="Y","Breakout",""),IF(AU37="Y","Accumulation",""),IF(AV37="Y","Institutional buying",""),IF(AW37="Y","Long buildup",""),IF(AX37="Y","Momentum leader",""))) | BA37: =IF(BW37="","","Passes "&AY37&" of 5 buy-side scans"&IF(G37="Y","; RED FLAG: filter out using Red flag column","")) | BB37: None | BC37: N | BF37: =IF(R37*100000>=Settings!$B$5,"Y","N") | BG37: =IF(F37>Settings!$B$6,"Y","N") | BH37: -19.38 | BI37: 0.6 | BJ37: -6.54 | BK37: -11.39 | BL37: 8.14 | BM37: 3.05 | BN37: -2.31 | BO37: -5.36 | BP37: -6.46 | BQ37: -6.25 | BR37: Mixed | BS37: None | BT37: 36.5 | BU37: N | BV37: =IF(OR(BF37<>"Y",BG37<>"Y"),"",(AND(ISNUMBER(BQ37),BQ37>0))+(BR37="Stacked up")+(AND(ISNUMBER(BH37),BH37>=-Settings!$B$17))+(AND(ISNUMBER(BK37),ISNUMBER(BM37),BK37>0,BM37>0))+(AND(ISNUMBER(AQ37),AQ37>=Settings!$B$18))+(AND(ISNUMBER(BT37),BT37>=Settings!$B$19,BT37<=Settings!$B$20))+(AND(ISNUMBER(AS37),AS37>0))+(AND(ISNUMBER(T37),ISNUMBER(M37),T37>=Settings!$B$21,M37>0))+(AND(ISNUMBER(AD37),ISNUMBER(M37),AD37>=Settings!$B$22,M37>0))+(AY37>=1)) | BW37: =IF(OR(AY37=0,BF37<>"Y",BG37<>"Y"),"",1+SUMPRODUCT(($A$6:$A$2604=A37)*($AY$6:$AY$2604>0)*($BF$6:$BF$2604="Y")*($BG$6:$BG$2604="Y")*(($AY$6:$AY$2604>AY37)+($AY$6:$AY$2604=AY37)*($AD$6:$AD$2604>AD37))))
A38: 46296 | B38: SHRIRAMFIN | C38: INE721A01047 | D38: Financial Services | E38: Nifty 50 | F38: 222363 | G38: N | I38: N | J38: =IF(K38="","N","Y") | K38: =_xlfn.TEXTJOIN("; ",TRUE,IF(P38="52-wk low","52-wk low",""),IF(AND(AD38>=Settings!$B$12,M38<0),"Distribution",""),IF(AND(AJ38="Y",M38<0,AK38<-Settings!$B$13),"Long unwinding",""),IF(AND(AJ38="Y",M38<0,AK38>Settings!$B$13),"Short buildup","")) | L38: 945 | M38: -3.84 | N38: 2310 | O38: None | P38: None | Q38: 56 | R38: 42.3 | S38: 1.31 | T38: 1.22 | U38: 1.07 | V38: 0.81 | W38: 6 | X38: 266 | Y38: None | Z38: 63.51 | AA38: 0.99 | AB38: 1.06 | AC38: 1.28 | AD38: 1.3 | AE38: 1.16 | AF38: 1.11 | AG38: Normal | AH38: 0 | AI38: 0 | AJ38: Y | AK38: 3.4 | AL38: Short buildup | AM38: 35 | AN38: 200 Mom 30; 500 Mom 50 | AO38: 2 | AP38: 1.43 | AQ38: 77 | AR38: Y | AS38: 0.6 | AT38: =IF(AND(P38="52-wk high",T38>=Settings!$B$7),"Y","N") | AU38: =IF(AND(AD38>=Settings!$B$8,M38>0),"Y","N") | AV38: =IF(OR(AH38>Settings!$B$9,AI38>Settings!$B$9),"Y","N") | AW38: =IF(AJ38<>"Y","n/a",IF(AND(M38>0,AK38>Settings!$B$10),"Y","N")) | AX38: =IF(AO38>=Settings!$B$11,"Y","N") | AY38: =(AT38="Y")+(AU38="Y")+(AV38="Y")+(AW38="Y")+(AX38="Y") | AZ38: =IF(AY38=0,"None",_xlfn.TEXTJOIN(", ",TRUE(),IF(AT38="Y","Breakout",""),IF(AU38="Y","Accumulation",""),IF(AV38="Y","Institutional buying",""),IF(AW38="Y","Long buildup",""),IF(AX38="Y","Momentum leader",""))) | BA38: =IF(BW38="","","Passes "&AY38&" of 5 buy-side scans"&IF(G38="Y","; RED FLAG: filter out using Red flag column","")) | BB38: Upper | BC38: N | BF38: =IF(R38*100000>=Settings!$B$5,"Y","N") | BG38: =IF(F38>Settings!$B$6,"Y","N") | BH38: -18.09 | BI38: -4.55 | BJ38: -10.77 | BK38: -9.84 | BL38: 4.94 | BM38: 45.68 | BN38: -6.1 | BO38: -8.39 | BP38: -7.64 | BQ38: -2.92 | BR38: Mixed | BS38: None | BT38: 25.6 | BU38: N | BV38: =IF(OR(BF38<>"Y",BG38<>"Y"),"",(AND(ISNUMBER(BQ38),BQ38>0))+(BR38="Stacked up")+(AND(ISNUMBER(BH38),BH38>=-Settings!$B$17))+(AND(ISNUMBER(BK38),ISNUMBER(BM38),BK38>0,BM38>0))+(AND(ISNUMBER(AQ38),AQ38>=Settings!$B$18))+(AND(ISNUMBER(BT38),BT38>=Settings!$B$19,BT38<=Settings!$B$20))+(AND(ISNUMBER(AS38),AS38>0))+(AND(ISNUMBER(T38),ISNUMBER(M38),T38>=Settings!$B$21,M38>0))+(AND(ISNUMBER(AD38),ISNUMBER(M38),AD38>=Settings!$B$22,M38>0))+(AY38>=1)) | BW38: =IF(OR(AY38=0,BF38<>"Y",BG38<>"Y"),"",1+SUMPRODUCT(($A$6:$A$2604=A38)*($AY$6:$AY$2604>0)*($BF$6:$BF$2604="Y")*($BG$6:$BG$2604="Y")*(($AY$6:$AY$2604>AY38)+($AY$6:$AY$2604=AY38)*($AD$6:$AD$2604>AD38))))
A39: 46296 | B39: TATASTEEL | C39: INE081A01020 | D39: Metals & Mining | E39: Nifty 50 | F39: 222207 | G39: N | I39: N | J39: =IF(K39="","N","Y") | K39: =_xlfn.TEXTJOIN("; ",TRUE,IF(P39="52-wk low","52-wk low",""),IF(AND(AD39>=Settings!$B$12,M39<0),"Distribution",""),IF(AND(AJ39="Y",M39<0,AK39<-Settings!$B$13),"Long unwinding",""),IF(AND(AJ39="Y",M39<0,AK39>Settings!$B$13),"Short buildup","")) | L39: 178 | M39: -3.42 | N39: 2203 | O39: None | P39: None | Q39: 476.6 | R39: 273.84 | S39: 1.83 | T39: 1.9 | U39: 1.71 | V39: 0.97 | W39: 8 | X39: 129 | Y39: Both | Z39: 52.38 | AA39: 1.09 | AB39: 1.02 | AC39: 1.98 | AD39: 1.92 | AE39: 1.73 | AF39: 0.94 | AG39: Normal | AH39: 0 | AI39: 0 | AJ39: Y | AK39: -0.86 | AL39: Long unwinding | AM39: 13 | AN39: 200 Mom 30 | AO39: 1 | AP39: 0.78 | AQ39: 47 | AR39: Y | AS39: -1.09 | AT39: =IF(AND(P39="52-wk high",T39>=Settings!$B$7),"Y","N") | AU39: =IF(AND(AD39>=Settings!$B$8,M39>0),"Y","N") | AV39: =IF(OR(AH39>Settings!$B$9,AI39>Settings!$B$9),"Y","N") | AW39: =IF(AJ39<>"Y","n/a",IF(AND(M39>0,AK39>Settings!$B$10),"Y","N")) | AX39: =IF(AO39>=Settings!$B$11,"Y","N") | AY39: =(AT39="Y")+(AU39="Y")+(AV39="Y")+(AW39="Y")+(AX39="Y") | AZ39: =IF(AY39=0,"None",_xlfn.TEXTJOIN(", ",TRUE(),IF(AT39="Y","Breakout",""),IF(AU39="Y","Accumulation",""),IF(AV39="Y","Institutional buying",""),IF(AW39="Y","Long buildup",""),IF(AX39="Y","Momentum leader",""))) | BA39: =IF(BW39="","","Passes "&AY39&" of 5 buy-side scans"&IF(G39="Y","; RED FLAG: filter out using Red flag column","")) | BB39: Upper | BC39: N | BF39: =IF(R39*100000>=Settings!$B$5,"Y","N") | BG39: =IF(F39>Settings!$B$6,"Y","N") | BH39: -20.68 | BI39: -5.33 | BJ39: -3.3 | BK39: -3.87 | BL39: -8.53 | BM39: 6.26 | BN39: -4.01 | BO39: -4.83 | BP39: -6.24 | BQ39: -6.23 | BR39: Mixed | BS39: None | BT39: 33.2 | BU39: N | BV39: =IF(OR(BF39<>"Y",BG39<>"Y"),"",(AND(ISNUMBER(BQ39),BQ39>0))+(BR39="Stacked up")+(AND(ISNUMBER(BH39),BH39>=-Settings!$B$17))+(AND(ISNUMBER(BK39),ISNUMBER(BM39),BK39>0,BM39>0))+(AND(ISNUMBER(AQ39),AQ39>=Settings!$B$18))+(AND(ISNUMBER(BT39),BT39>=Settings!$B$19,BT39<=Settings!$B$20))+(AND(ISNUMBER(AS39),AS39>0))+(AND(ISNUMBER(T39),ISNUMBER(M39),T39>=Settings!$B$21,M39>0))+(AND(ISNUMBER(AD39),ISNUMBER(M39),AD39>=Settings!$B$22,M39>0))+(AY39>=1)) | BW39: =IF(OR(AY39=0,BF39<>"Y",BG39<>"Y"),"",1+SUMPRODUCT(($A$6:$A$2604=A39)*($AY$6:$AY$2604>0)*($BF$6:$BF$2604="Y")*($BG$6:$BG$2604="Y")*(($AY$6:$AY$2604>AY39)+($AY$6:$AY$2604=AY39)*($AD$6:$AD$2604>AD39))))
A40: 46296 | B40: HINDALCO | C40: INE038A01020 | D40: Metals & Mining | E40: Nifty 50 | F40: 211655 | G40: N | I40: N | J40: =IF(K40="","N","Y") | K40: =_xlfn.TEXTJOIN("; ",TRUE,IF(P40="52-wk low","52-wk low",""),IF(AND(AD40>=Settings!$B$12,M40<0),"Distribution",""),IF(AND(AJ40="Y",M40<0,AK40<-Settings!$B$13),"Long unwinding",""),IF(AND(AJ40="Y",M40<0,AK40>Settings!$B$13),"Short buildup","")) | L40: 941.85 | M40: 0.01 | N40: 575 | O40: None | P40: None | Q40: 58.78 | R40: 37.19 | S40: 1.67 | T40: 1.44 | U40: 1.14 | V40: 0.72 | W40: 3 | X40: 212 | Y40: None | Z40: 56.41 | AA40: 0.95 | AB40: 1.01 | AC40: 1.57 | AD40: 1.47 | AE40: 1.16 | AF40: 1.08 | AG40: Normal | AH40: 0 | AI40: 0 | AJ40: Y | AK40: -0.74 | AL40: Short covering | AM40: 24 | AN40: 200 Mom 30; 500 Mom 50 | AO40: 2 | AP40: 1.21 | AQ40: 70 | AR40: Y | AS40: -1.09 | AT40: =IF(AND(P40="52-wk high",T40>=Settings!$B$7),"Y","N") | AU40: =IF(AND(AD40>=Settings!$B$8,M40>0),"Y","N") | AV40: =IF(OR(AH40>Settings!$B$9,AI40>Settings!$B$9),"Y","N") | AW40: =IF(AJ40<>"Y","n/a",IF(AND(M40>0,AK40>Settings!$B$10),"Y","N")) | AX40: =IF(AO40>=Settings!$B$11,"Y","N") | AY40: =(AT40="Y")+(AU40="Y")+(AV40="Y")+(AW40="Y")+(AX40="Y") | AZ40: =IF(AY40=0,"None",_xlfn.TEXTJOIN(", ",TRUE(),IF(AT40="Y","Breakout",""),IF(AU40="Y","Accumulation",""),IF(AV40="Y","Institutional buying",""),IF(AW40="Y","Long buildup",""),IF(AX40="Y","Momentum leader",""))) | BA40: =IF(BW40="","","Passes "&AY40&" of 5 buy-side scans"&IF(G40="Y","; RED FLAG: filter out using Red flag column","")) | BB40: None | BC40: N | BF40: =IF(R40*100000>=Settings!$B$5,"Y","N") | BG40: =IF(F40>Settings!$B$6,"Y","N") | BH40: -19.91 | BI40: -4.09 | BJ40: -7.15 | BK40: 0.23 | BL40: 4.12 | BM40: 22.96 | BN40: -3.87 | BO40: -5.38 | BP40: -5.3 | BQ40: -2.13 | BR40: Mixed | BS40: None | BT40: 31 | BU40: N | BV40: =IF(OR(BF40<>"Y",BG40<>"Y"),"",(AND(ISNUMBER(BQ40),BQ40>0))+(BR40="Stacked up")+(AND(ISNUMBER(BH40),BH40>=-Settings!$B$17))+(AND(ISNUMBER(BK40),ISNUMBER(BM40),BK40>0,BM40>0))+(AND(ISNUMBER(AQ40),AQ40>=Settings!$B$18))+(AND(ISNUMBER(BT40),BT40>=Settings!$B$19,BT40<=Settings!$B$20))+(AND(ISNUMBER(AS40),AS40>0))+(AND(ISNUMBER(T40),ISNUMBER(M40),T40>=Settings!$B$21,M40>0))+(AND(ISNUMBER(AD40),ISNUMBER(M40),AD40>=Settings!$B$22,M40>0))+(AY40>=1)) | BW40: =IF(OR(AY40=0,BF40<>"Y",BG40<>"Y"),"",1+SUMPRODUCT(($A$6:$A$2604=A40)*($AY$6:$AY$2604>0)*($BF$6:$BF$2604="Y")*($BG$6:$BG$2604="Y")*(($AY$6:$AY$2604>AY40)+($AY$6:$AY$2604=AY40)*($AD$6:$AD$2604>AD40))))
A41: 46296 | B41: GRASIM | C41: INE047A01021 | D41: Construction Materials | E41: Nifty 50 | F41: 201575 | G41: N | I41: N | J41: =IF(K41="","N","Y") | K41: =_xlfn.TEXTJOIN("; ",TRUE,IF(P41="52-wk low","52-wk low",""),IF(AND(AD41>=Settings!$B$12,M41<0),"Distribution",""),IF(AND(AJ41="Y",M41<0,AK41<-Settings!$B$13),"Long unwinding",""),IF(AND(AJ41="Y",M41<0,AK41>Settings!$B$13),"Short buildup","")) | L41: 2962 | M41: -3.26 | N41: 2171 | O41: None | P41: None | Q41: 13.86 | R41: 8.78 | S41: 1.61 | T41: 1.56 | U41: 1.63 | V41: 1.02 | W41: 4 | X41: 168 | Y41: None | Z41: 53.67 | AA41: 0.87 | AB41: 0.93 | AC41: 1.39 | AD41: 1.45 | AE41: 1.55 | AF41: 1.09 | AG41: Normal | AH41: 0 | AI41: 0 | AJ41: Y | AK41: 0.78 | AL41: Short buildup | AM41: 44 | AN41: None | AO41: 0 | AP41: 1.22 | AQ41: 70 | AR41: Y | AS41: -0.71 | AT41: =IF(AND(P41="52-wk high",T41>=Settings!$B$7),"Y","N") | AU41: =IF(AND(AD41>=Settings!$B$8,M41>0),"Y","N") | AV41: =IF(OR(AH41>Settings!$B$9,AI41>Settings!$B$9),"Y","N") | AW41: =IF(AJ41<>"Y","n/a",IF(AND(M41>0,AK41>Settings!$B$10),"Y","N")) | AX41: =IF(AO41>=Settings!$B$11,"Y","N") | AY41: =(AT41="Y")+(AU41="Y")+(AV41="Y")+(AW41="Y")+(AX41="Y") | AZ41: =IF(AY41=0,"None",_xlfn.TEXTJOIN(", ",TRUE(),IF(AT41="Y","Breakout",""),IF(AU41="Y","Accumulation",""),IF(AV41="Y","Institutional buying",""),IF(AW41="Y","Long buildup",""),IF(AX41="Y","Momentum leader",""))) | BA41: =IF(BW41="","","Passes "&AY41&" of 5 buy-side scans"&IF(G41="Y","; RED FLAG: filter out using Red flag column","")) | BB41: None | BC41: N | BF41: =IF(R41*100000>=Settings!$B$5,"Y","N") | BG41: =IF(F41>Settings!$B$6,"Y","N") | BH41: -13.17 | BI41: -6.46 | BJ41: -10.38 | BK41: -5.68 | BL41: 14.24 | BM41: 6.18 | BN41: -6.53 | BO41: -7.22 | BP41: -5.56 | BQ41: -2.44 | BR41: Mixed | BS41: None | BT41: 21.7 | BU41: N | BV41: =IF(OR(BF41<>"Y",BG41<>"Y"),"",(AND(ISNUMBER(BQ41),BQ41>0))+(BR41="Stacked up")+(AND(ISNUMBER(BH41),BH41>=-Settings!$B$17))+(AND(ISNUMBER(BK41),ISNUMBER(BM41),BK41>0,BM41>0))+(AND(ISNUMBER(AQ41),AQ41>=Settings!$B$18))+(AND(ISNUMBER(BT41),BT41>=Settings!$B$19,BT41<=Settings!$B$20))+(AND(ISNUMBER(AS41),AS41>0))+(AND(ISNUMBER(T41),ISNUMBER(M41),T41>=Settings!$B$21,M41>0))+(AND(ISNUMBER(AD41),ISNUMBER(M41),AD41>=Settings!$B$22,M41>0))+(AY41>=1)) | BW41: =IF(OR(AY41=0,BF41<>"Y",BG41<>"Y"),"",1+SUMPRODUCT(($A$6:$A$2604=A41)*($AY$6:$AY$2604>0)*($BF$6:$BF$2604="Y")*($BG$6:$BG$2604="Y")*(($AY$6:$AY$2604>AY41)+($AY$6:$AY$2604=AY41)*($AD$6:$AD$2604>AD41))))
A42: 46296 | B42: INDIGO | C42: INE646L01027 | D42: Services | E42: Nifty 50 | F42: 190623 | G42: N | I42: N | J42: =IF(K42="","N","Y") | K42: =_xlfn.TEXTJOIN("; ",TRUE,IF(P42="52-wk low","52-wk low",""),IF(AND(AD42>=Settings!$B$12,M42<0),"Distribution",""),IF(AND(AJ42="Y",M42<0,AK42<-Settings!$B$13),"Long unwinding",""),IF(AND(AJ42="Y",M42<0,AK42>Settings!$B$13),"Short buildup","")) | L42: 4929.9 | M42: -1.09 | N42: 1094 | O42: None | P42: None | Q42: 5.93 | R42: 5.93 | S42: 0.93 | T42: 0.88 | U42: 0.65 | V42: 0.66 | W42: 0 | Y42: None | Z42: 48.94 | AA42: 0.88 | AB42: 0.93 | AC42: 0.83 | AD42: 0.82 | AE42: 0.61 | AF42: 1.05 | AG42: Normal | AH42: 0 | AI42: 0 | AJ42: Y | AK42: -0.13 | AL42: Long unwinding | AM42: 31 | AN42: None | AO42: 0 | AP42: 0.91 | AQ42: 57 | AR42: Y | AS42: 5.23 | AT42: =IF(AND(P42="52-wk high",T42>=Settings!$B$7),"Y","N") | AU42: =IF(AND(AD42>=Settings!$B$8,M42>0),"Y","N") | AV42: =IF(OR(AH42>Settings!$B$9,AI42>Settings!$B$9),"Y","N") | AW42: =IF(AJ42<>"Y","n/a",IF(AND(M42>0,AK42>Settings!$B$10),"Y","N")) | AX42: =IF(AO42>=Settings!$B$11,"Y","N") | AY42: =(AT42="Y")+(AU42="Y")+(AV42="Y")+(AW42="Y")+(AX42="Y") | AZ42: =IF(AY42=0,"None",_xlfn.TEXTJOIN(", ",TRUE(),IF(AT42="Y","Breakout",""),IF(AU42="Y","Accumulation",""),IF(AV42="Y","Institutional buying",""),IF(AW42="Y","Long buildup",""),IF(AX42="Y","Momentum leader",""))) | BA42: =IF(BW42="","","Passes "&AY42&" of 5 buy-side scans"&IF(G42="Y","; RED FLAG: filter out using Red flag column","")) | BB42: None | BC42: Y | BD42: EPS zero | BF42: =IF(R42*100000>=Settings!$B$5,"Y","N") | BG42: =IF(F42>Settings!$B$6,"Y","N") | BH42: -17.42 | BI42: 0.82 | BJ42: -2.42 | BK42: -8.69 | BL42: 17.92 | BM42: -12.06 | BN42: -0.65 | BO42: -1.86 | BP42: -1.24 | BQ42: -1.65 | BR42: Mixed | BS42: None | BT42: 47.9 | BU42: N | BV42: =IF(OR(BF42<>"Y",BG42<>"Y"),"",(AND(ISNUMBER(BQ42),BQ42>0))+(BR42="Stacked up")+(AND(ISNUMBER(BH42),BH42>=-Settings!$B$17))+(AND(ISNUMBER(BK42),ISNUMBER(BM42),BK42>0,BM42>0))+(AND(ISNUMBER(AQ42),AQ42>=Settings!$B$18))+(AND(ISNUMBER(BT42),BT42>=Settings!$B$19,BT42<=Settings!$B$20))+(AND(ISNUMBER(AS42),AS42>0))+(AND(ISNUMBER(T42),ISNUMBER(M42),T42>=Settings!$B$21,M42>0))+(AND(ISNUMBER(AD42),ISNUMBER(M42),AD42>=Settings!$B$22,M42>0))+(AY42>=1)) | BW42: =IF(OR(AY42=0,BF42<>"Y",BG42<>"Y"),"",1+SUMPRODUCT(($A$6:$A$2604=A42)*($AY$6:$AY$2604>0)*($BF$6:$BF$2604="Y")*($BG$6:$BG$2604="Y")*(($AY$6:$AY$2604>AY42)+($AY$6:$AY$2604=AY42)*($AD$6:$AD$2604>AD42))))
A43: 46296 | B43: EICHERMOT | C43: INE066A01021 | D43: Automobile and Auto Components | E43: Nifty 50 | F43: 189969 | G43: N | I43: N | J43: =IF(K43="","N","Y") | K43: =_xlfn.TEXTJOIN("; ",TRUE,IF(P43="52-wk low","52-wk low",""),IF(AND(AD43>=Settings!$B$12,M43<0),"Distribution",""),IF(AND(AJ43="Y",M43<0,AK43<-Settings!$B$13),"Long unwinding",""),IF(AND(AJ43="Y",M43<0,AK43>Settings!$B$13),"Short buildup","")) | L43: 6920 | M43: -3.22 | N43: 2157 | O43: None | P43: None | Q43: 8.17 | R43: 3.89 | S43: 2.03 | T43: 1.86 | U43: 1.57 | V43: 0.74 | W43: 2 | X43: 126 | Y43: None | Z43: 49.18 | AA43: 0.81 | AB43: 0.83 | AC43: 1.67 | AD43: 1.59 | AE43: 1.41 | AF43: 1.11 | AG43: Normal | AH43: 0 | AI43: 0 | AJ43: Y | AK43: 6.23 | AL43: Short buildup | AM43: 28 | AN43: 500 Multicap MQ 50; TotalMkt MQ 50 | AO43: 2 | AP43: 0.82 | AQ43: 51 | AR43: Y | AS43: 0.56 | AT43: =IF(AND(P43="52-wk high",T43>=Settings!$B$7),"Y","N") | AU43: =IF(AND(AD43>=Settings!$B$8,M43>0),"Y","N") | AV43: =IF(OR(AH43>Settings!$B$9,AI43>Settings!$B$9),"Y","N") | AW43: =IF(AJ43<>"Y","n/a",IF(AND(M43>0,AK43>Settings!$B$10),"Y","N")) | AX43: =IF(AO43>=Settings!$B$11,"Y","N") | AY43: =(AT43="Y")+(AU43="Y")+(AV43="Y")+(AW43="Y")+(AX43="Y") | AZ43: =IF(AY43=0,"None",_xlfn.TEXTJOIN(", ",TRUE(),IF(AT43="Y","Breakout",""),IF(AU43="Y","Accumulation",""),IF(AV43="Y","Institutional buying",""),IF(AW43="Y","Long buildup",""),IF(AX43="Y","Momentum leader",""))) | BA43: =IF(BW43="","","Passes "&AY43&" of 5 buy-side scans"&IF(G43="Y","; RED FLAG: filter out using Red flag column","")) | BB43: None | BC43: N | BF43: =IF(R43*100000>=Settings!$B$5,"Y","N") | BG43: =IF(F43>Settings!$B$6,"Y","N") | BH43: -15.92 | BI43: -5.7 | BJ43: -13.17 | BK43: -3.07 | BL43: 1.38 | BM43: -1.45 | BN43: -6.86 | BO43: -8.74 | BP43: -8.29 | BQ43: -6.8 | BR43: Mixed | BS43: None | BT43: 12.6 | BU43: N | BV43: =IF(OR(BF43<>"Y",BG43<>"Y"),"",(AND(ISNUMBER(BQ43),BQ43>0))+(BR43="Stacked up")+(AND(ISNUMBER(BH43),BH43>=-Settings!$B$17))+(AND(ISNUMBER(BK43),ISNUMBER(BM43),BK43>0,BM43>0))+(AND(ISNUMBER(AQ43),AQ43>=Settings!$B$18))+(AND(ISNUMBER(BT43),BT43>=Settings!$B$19,BT43<=Settings!$B$20))+(AND(ISNUMBER(AS43),AS43>0))+(AND(ISNUMBER(T43),ISNUMBER(M43),T43>=Settings!$B$21,M43>0))+(AND(ISNUMBER(AD43),ISNUMBER(M43),AD43>=Settings!$B$22,M43>0))+(AY43>=1)) | BW43: =IF(OR(AY43=0,BF43<>"Y",BG43<>"Y"),"",1+SUMPRODUCT(($A$6:$A$2604=A43)*($AY$6:$AY$2604>0)*($BF$6:$BF$2604="Y")*($BG$6:$BG$2604="Y")*(($AY$6:$AY$2604>AY43)+($AY$6:$AY$2604=AY43)*($AD$6:$AD$2604>AD43))))
A44: 46296 | B44: SBILIFE | C44: INE123W01016 | D44: Financial Services | E44: Nifty 50 | F44: 172746 | G44: N | I44: N | J44: =IF(K44="","N","Y") | K44: =_xlfn.TEXTJOIN("; ",TRUE,IF(P44="52-wk low","52-wk low",""),IF(AND(AD44>=Settings!$B$12,M44<0),"Distribution",""),IF(AND(AJ44="Y",M44<0,AK44<-Settings!$B$13),"Long unwinding",""),IF(AND(AJ44="Y",M44<0,AK44>Settings!$B$13),"Short buildup","")) | L44: 1721.6 | M44: 1.49 | N44: 254 | O44: None | P44: None | Q44: 33.3 | R44: 12.5 | S44: 2.98 | T44: 3.38 | U44: 3.4 | V44: 1.24 | W44: 10 | X44: 38 | Y44: None | Z44: 63.76 | AA44: 1.03 | AB44: 1.03 | AC44: 3.14 | AD44: 3.5 | AE44: 3.58 | AF44: 1 | AG44: Normal | AH44: 0 | AI44: 0 | AJ44: Y | AK44: 1.72 | AL44: Long buildup | AM44: 112 | AN44: None | AO44: 0 | AP44: 0.71 | AQ44: 38 | AR44: Y | AS44: 0.6 | AT44: =IF(AND(P44="52-wk high",T44>=Settings!$B$7),"Y","N") | AU44: =IF(AND(AD44>=Settings!$B$8,M44>0),"Y","N") | AV44: =IF(OR(AH44>Settings!$B$9,AI44>Settings!$B$9),"Y","N") | AW44: =IF(AJ44<>"Y","n/a",IF(AND(M44>0,AK44>Settings!$B$10),"Y","N")) | AX44: =IF(AO44>=Settings!$B$11,"Y","N") | AY44: =(AT44="Y")+(AU44="Y")+(AV44="Y")+(AW44="Y")+(AX44="Y") | AZ44: =IF(AY44=0,"None",_xlfn.TEXTJOIN(", ",TRUE(),IF(AT44="Y","Breakout",""),IF(AU44="Y","Accumulation",""),IF(AV44="Y","Institutional buying",""),IF(AW44="Y","Long buildup",""),IF(AX44="Y","Momentum leader",""))) | BA44: =IF(BW44="","","Passes "&AY44&" of 5 buy-side scans"&IF(G44="Y","; RED FLAG: filter out using Red flag column","")) | BB44: None | BC44: Y | BD44: PE > 50 | BF44: =IF(R44*100000>=Settings!$B$5,"Y","N") | BG44: =IF(F44>Settings!$B$6,"Y","N") | BH44: -19.25 | BI44: -1.9 | BJ44: -1.02 | BK44: -3.87 | BL44: -3.85 | BM44: -4.41 | BN44: -0.76 | BO44: -2.34 | BP44: -4.24 | BQ44: -6.2 | BR44: Stacked down | BS44: None | BT44: 46.8 | BU44: N | BV44: =IF(OR(BF44<>"Y",BG44<>"Y"),"",(AND(ISNUMBER(BQ44),BQ44>0))+(BR44="Stacked up")+(AND(ISNUMBER(BH44),BH44>=-Settings!$B$17))+(AND(ISNUMBER(BK44),ISNUMBER(BM44),BK44>0,BM44>0))+(AND(ISNUMBER(AQ44),AQ44>=Settings!$B$18))+(AND(ISNUMBER(BT44),BT44>=Settings!$B$19,BT44<=Settings!$B$20))+(AND(ISNUMBER(AS44),AS44>0))+(AND(ISNUMBER(T44),ISNUMBER(M44),T44>=Settings!$B$21,M44>0))+(AND(ISNUMBER(AD44),ISNUMBER(M44),AD44>=Settings!$B$22,M44>0))+(AY44>=1)) | BW44: =IF(OR(AY44=0,BF44<>"Y",BG44<>"Y"),"",1+SUMPRODUCT(($A$6:$A$2604=A44)*($AY$6:$AY$2604>0)*($BF$6:$BF$2604="Y")*($BG$6:$BG$2604="Y")*(($AY$6:$AY$2604>AY44)+($AY$6:$AY$2604=AY44)*($AD$6:$AD$2604>AD44))))
A45: 46296 | B45: TECHM | C45: INE669C01036 | D45: Information Technology | E45: Nifty 50 | F45: 150258 | G45: N | I45: N | J45: =IF(K45="","N","Y") | K45: =_xlfn.TEXTJOIN("; ",TRUE,IF(P45="52-wk low","52-wk low",""),IF(AND(AD45>=Settings!$B$12,M45<0),"Distribution",""),IF(AND(AJ45="Y",M45<0,AK45<-Settings!$B$13),"Long unwinding",""),IF(AND(AJ45="Y",M45<0,AK45>Settings!$B$13),"Short buildup","")) | L45: 1533 | M45: 0.59 | N45: 423 | O45: None | P45: None | Q45: 26.63 | R45: 18.24 | S45: 1.51 | T45: 1.17 | U45: 1.06 | V45: 0.72 | W45: 5 | X45: 249 | Y45: None | Z45: 48.36 | AA45: 0.9 | AB45: 0.84 | AC45: 1.34 | AD45: 0.96 | AE45: 0.99 | AF45: 1.04 | AG45: Normal | AH45: 0 | AI45: 0 | AJ45: Y | AK45: 2.36 | AL45: Long buildup | AM45: 26 | AN45: None | AO45: 0 | AP45: 1.09 | AQ45: 66 | AR45: Y | AS45: -0.75 | AT45: =IF(AND(P45="52-wk high",T45>=Settings!$B$7),"Y","N") | AU45: =IF(AND(AD45>=Settings!$B$8,M45>0),"Y","N") | AV45: =IF(OR(AH45>Settings!$B$9,AI45>Settings!$B$9),"Y","N") | AW45: =IF(AJ45<>"Y","n/a",IF(AND(M45>0,AK45>Settings!$B$10),"Y","N")) | AX45: =IF(AO45>=Settings!$B$11,"Y","N") | AY45: =(AT45="Y")+(AU45="Y")+(AV45="Y")+(AW45="Y")+(AX45="Y") | AZ45: =IF(AY45=0,"None",_xlfn.TEXTJOIN(", ",TRUE(),IF(AT45="Y","Breakout",""),IF(AU45="Y","Accumulation",""),IF(AV45="Y","Institutional buying",""),IF(AW45="Y","Long buildup",""),IF(AX45="Y","Momentum leader",""))) | BA45: =IF(BW45="","","Passes "&AY45&" of 5 buy-side scans"&IF(G45="Y","; RED FLAG: filter out using Red flag column","")) | BB45: None | BC45: N | BF45: =IF(R45*100000>=Settings!$B$5,"Y","N") | BG45: =IF(F45>Settings!$B$6,"Y","N") | BH45: -17.31 | BI45: -0.65 | BJ45: -6.41 | BK45: 12.54 | BL45: 9.15 | BM45: 8.26 | BN45: -1.2 | BO45: -1.6 | BP45: -0.39 | BQ45: 1.08 | BR45: Mixed | BS45: None | BT45: 43.6 | BU45: N | BV45: =IF(OR(BF45<>"Y",BG45<>"Y"),"",(AND(ISNUMBER(BQ45),BQ45>0))+(BR45="Stacked up")+(AND(ISNUMBER(BH45),BH45>=-Settings!$B$17))+(AND(ISNUMBER(BK45),ISNUMBER(BM45),BK45>0,BM45>0))+(AND(ISNUMBER(AQ45),AQ45>=Settings!$B$18))+(AND(ISNUMBER(BT45),BT45>=Settings!$B$19,BT45<=Settings!$B$20))+(AND(ISNUMBER(AS45),AS45>0))+(AND(ISNUMBER(T45),ISNUMBER(M45),T45>=Settings!$B$21,M45>0))+(AND(ISNUMBER(AD45),ISNUMBER(M45),AD45>=Settings!$B$22,M45>0))+(AY45>=1)) | BW45: =IF(OR(AY45=0,BF45<>"Y",BG45<>"Y"),"",1+SUMPRODUCT(($A$6:$A$2604=A45)*($AY$6:$AY$2604>0)*($BF$6:$BF$2604="Y")*($BG$6:$BG$2604="Y")*(($AY$6:$AY$2604>AY45)+($AY$6:$AY$2604=AY45)*($AD$6:$AD$2604>AD45))))
A46: 46296 | B46: JIOFIN | C46: INE758E01017 | D46: Financial Services | E46: Nifty 50 | F46: 140317 | G46: N | I46: N | J46: =IF(K46="","N","Y") | K46: =_xlfn.TEXTJOIN("; ",TRUE,IF(P46="52-wk low","52-wk low",""),IF(AND(AD46>=Settings!$B$12,M46<0),"Distribution",""),IF(AND(AJ46="Y",M46<0,AK46<-Settings!$B$13),"Long unwinding",""),IF(AND(AJ46="Y",M46<0,AK46>Settings!$B$13),"Short buildup","")) | L46: 212.5 | M46: -2.02 | N46: 1663 | O46: None | P46: 52-wk low | Q46: 280.82 | R46: 124.73 | S46: 2.37 | T46: 1.96 | U46: 1.92 | V46: 0.85 | W46: 4 | X46: 100 | Y46: None | Z46: 41.21 | AA46: 0.81 | AB46: 0.86 | AC46: 1.94 | AD46: 1.74 | AE46: 1.78 | AF46: 1.11 | AG46: Normal | AH46: 0 | AI46: 0 | AJ46: Y | AK46: 0.87 | AL46: Short buildup | AM46: 30 | AN46: None | AO46: 0 | AP46: 0.54 | AQ46: 9 | AR46: Y | AS46: 0.6 | AT46: =IF(AND(P46="52-wk high",T46>=Settings!$B$7),"Y","N") | AU46: =IF(AND(AD46>=Settings!$B$8,M46>0),"Y","N") | AV46: =IF(OR(AH46>Settings!$B$9,AI46>Settings!$B$9),"Y","N") | AW46: =IF(AJ46<>"Y","n/a",IF(AND(M46>0,AK46>Settings!$B$10),"Y","N")) | AX46: =IF(AO46>=Settings!$B$11,"Y","N") | AY46: =(AT46="Y")+(AU46="Y")+(AV46="Y")+(AW46="Y")+(AX46="Y") | AZ46: =IF(AY46=0,"None",_xlfn.TEXTJOIN(", ",TRUE(),IF(AT46="Y","Breakout",""),IF(AU46="Y","Accumulation",""),IF(AV46="Y","Institutional buying",""),IF(AW46="Y","Long buildup",""),IF(AX46="Y","Momentum leader",""))) | BA46: =IF(BW46="","","Passes "&AY46&" of 5 buy-side scans"&IF(G46="Y","; RED FLAG: filter out using Red flag column","")) | BB46: None | BC46: Y | BD46: PE > 50 | BF46: =IF(R46*100000>=Settings!$B$5,"Y","N") | BG46: =IF(F46>Settings!$B$6,"Y","N") | BH46: -32.93 | BI46: -6.47 | BJ46: -9.9 | BK46: -11.46 | BL46: -8.38 | BM46: -29.18 | BN46: -6.5 | BO46: -9.36 | BP46: -11.39 | BQ46: -15.4 | BR46: Stacked down | BS46: None | BT46: 16.4 | BU46: N | BV46: =IF(OR(BF46<>"Y",BG46<>"Y"),"",(AND(ISNUMBER(BQ46),BQ46>0))+(BR46="Stacked up")+(AND(ISNUMBER(BH46),BH46>=-Settings!$B$17))+(AND(ISNUMBER(BK46),ISNUMBER(BM46),BK46>0,BM46>0))+(AND(ISNUMBER(AQ46),AQ46>=Settings!$B$18))+(AND(ISNUMBER(BT46),BT46>=Settings!$B$19,BT46<=Settings!$B$20))+(AND(ISNUMBER(AS46),AS46>0))+(AND(ISNUMBER(T46),ISNUMBER(M46),T46>=Settings!$B$21,M46>0))+(AND(ISNUMBER(AD46),ISNUMBER(M46),AD46>=Settings!$B$22,M46>0))+(AY46>=1)) | BW46: =IF(OR(AY46=0,BF46<>"Y",BG46<>"Y"),"",1+SUMPRODUCT(($A$6:$A$2604=A46)*($AY$6:$AY$2604>0)*($BF$6:$BF$2604="Y")*($BG$6:$BG$2604="Y")*(($AY$6:$AY$2604>AY46)+($AY$6:$AY$2604=AY46)*($AD$6:$AD$2604>AD46))))
A47: 46296 | B47: TRENT | C47: INE849A01020 | D47: Consumer Services | E47: Nifty 50 | F47: 137579 | G47: N | I47: N | J47: =IF(K47="","N","Y") | K47: =_xlfn.TEXTJOIN("; ",TRUE,IF(P47="52-wk low","52-wk low",""),IF(AND(AD47>=Settings!$B$12,M47<0),"Distribution",""),IF(AND(AJ47="Y",M47<0,AK47<-Settings!$B$13),"Long unwinding",""),IF(AND(AJ47="Y",M47<0,AK47>Settings!$B$13),"Short buildup","")) | L47: 2580 | M47: -1.59 | N47: 1396 | O47: None | P47: None | Q47: 8.97 | R47: 7.33 | S47: 1.22 | T47: 1.06 | U47: 0.78 | V47: 0.64 | W47: 1 | Y47: None | Z47: 56.42 | AA47: 1.05 | AB47: 1.12 | AC47: 1.26 | AD47: 1.25 | AE47: 1.03 | AF47: 1.27 | AG47: Normal | AH47: 0 | AI47: 0 | AJ47: Y | AK47: 0.29 | AL47: Short buildup | AM47: 113 | AN47: None | AO47: 0 | AP47: 0.53 | AQ47: 8 | AR47: Y | AS47: 2.34 | AT47: =IF(AND(P47="52-wk high",T47>=Settings!$B$7),"Y","N") | AU47: =IF(AND(AD47>=Settings!$B$8,M47>0),"Y","N") | AV47: =IF(OR(AH47>Settings!$B$9,AI47>Settings!$B$9),"Y","N") | AW47: =IF(AJ47<>"Y","n/a",IF(AND(M47>0,AK47>Settings!$B$10),"Y","N")) | AX47: =IF(AO47>=Settings!$B$11,"Y","N") | AY47: =(AT47="Y")+(AU47="Y")+(AV47="Y")+(AW47="Y")+(AX47="Y") | AZ47: =IF(AY47=0,"None",_xlfn.TEXTJOIN(", ",TRUE(),IF(AT47="Y","Breakout",""),IF(AU47="Y","Accumulation",""),IF(AV47="Y","Institutional buying",""),IF(AW47="Y","Long buildup",""),IF(AX47="Y","Momentum leader",""))) | BA47: =IF(BW47="","","Passes "&AY47&" of 5 buy-side scans"&IF(G47="Y","; RED FLAG: filter out using Red flag column","")) | BB47: None | BC47: Y | BD47: PE > 50 | BE47: BONUS 1:2, ex 04-Jun-2026 | BF47: =IF(R47*100000>=Settings!$B$5,"Y","N") | BG47: =IF(F47>Settings!$B$6,"Y","N") | BH47: -24.11 | BI47: -4.44 | BJ47: -9.63 | BK47: -21.59 | BL47: -26.84 | BM47: -46.61 | BN47: -5.84 | BO47: -10.28 | BP47: -16.92 | BQ47: -25.87 | BR47: Stacked down | BS47: None | BT47: 19.3 | BU47: N | BV47: =IF(OR(BF47<>"Y",BG47<>"Y"),"",(AND(ISNUMBER(BQ47),BQ47>0))+(BR47="Stacked up")+(AND(ISNUMBER(BH47),BH47>=-Settings!$B$17))+(AND(ISNUMBER(BK47),ISNUMBER(BM47),BK47>0,BM47>0))+(AND(ISNUMBER(AQ47),AQ47>=Settings!$B$18))+(AND(ISNUMBER(BT47),BT47>=Settings!$B$19,BT47<=Settings!$B$20))+(AND(ISNUMBER(AS47),AS47>0))+(AND(ISNUMBER(T47),ISNUMBER(M47),T47>=Settings!$B$21,M47>0))+(AND(ISNUMBER(AD47),ISNUMBER(M47),AD47>=Settings!$B$22,M47>0))+(AY47>=1)) | BW47: =IF(OR(AY47=0,BF47<>"Y",BG47<>"Y"),"",1+SUMPRODUCT(($A$6:$A$2604=A47)*($AY$6:$AY$2604>0)*($BF$6:$BF$2604="Y")*($BG$6:$BG$2604="Y")*(($AY$6:$AY$2604>AY47)+($AY$6:$AY$2604=AY47)*($AD$6:$AD$2604>AD47))))
A48: 46296 | B48: BSE | C48: INE118H01025 | D48: Financial Services | E48: Nifty 50 | F48: 124241 | G48: N | I48: N | J48: =IF(K48="","N","Y") | K48: =_xlfn.TEXTJOIN("; ",TRUE,IF(P48="52-wk low","52-wk low",""),IF(AND(AD48>=Settings!$B$12,M48<0),"Distribution",""),IF(AND(AJ48="Y",M48<0,AK48<-Settings!$B$13),"Long unwinding",""),IF(AND(AJ48="Y",M48<0,AK48>Settings!$B$13),"Short buildup","")) | L48: 3046 | M48: -1.49 | N48: 1315 | O48: None | P48: None | Q48: 62.73 | R48: 56.48 | S48: 1.11 | T48: 1.36 | U48: 1.51 | V48: 1.35 | W48: 8 | X48: 231 | Y48: By value | Z48: 48.18 | AA48: 1.17 | AB48: 1.17 | AC48: 1.1 | AD48: 1.45 | AE48: 1.83 | AF48: 1.23 | AG48: Normal | AH48: 0 | AI48: 0 | AJ48: Y | AK48: 6.51 | AL48: Short buildup | AM48: 7 | AN48: 200 Mom 30; 500 Mom 50; Mid150 Mom 50; MidSmall400 MQ 100; 500 Multicap MQ 50; TotalMkt MQ 50 | AO48: 6 | AP48: 1.42 | AQ48: 77 | AR48: Y | AS48: 0.6 | AT48: =IF(AND(P48="52-wk high",T48>=Settings!$B$7),"Y","N") | AU48: =IF(AND(AD48>=Settings!$B$8,M48>0),"Y","N") | AV48: =IF(OR(AH48>Settings!$B$9,AI48>Settings!$B$9),"Y","N") | AW48: =IF(AJ48<>"Y","n/a",IF(AND(M48>0,AK48>Settings!$B$10),"Y","N")) | AX48: =IF(AO48>=Settings!$B$11,"Y","N") | AY48: =(AT48="Y")+(AU48="Y")+(AV48="Y")+(AW48="Y")+(AX48="Y") | AZ48: =IF(AY48=0,"None",_xlfn.TEXTJOIN(", ",TRUE(),IF(AT48="Y","Breakout",""),IF(AU48="Y","Accumulation",""),IF(AV48="Y","Institutional buying",""),IF(AW48="Y","Long buildup",""),IF(AX48="Y","Momentum leader",""))) | BA48: =IF(BW48="","","Passes "&AY48&" of 5 buy-side scans"&IF(G48="Y","; RED FLAG: filter out using Red flag column","")) | BB48: Upper | BC48: N | BF48: =IF(R48*100000>=Settings!$B$5,"Y","N") | BG48: =IF(F48>Settings!$B$6,"Y","N") | BH48: -31.5 | BI48: -4.33 | BJ48: -6.05 | BK48: -22.77 | BL48: 6.22 | BM48: 46.34 | BN48: -5.54 | BO48: -9.3 | BP48: -10.94 | BQ48: -6.76 | BR48: Mixed | BS48: None | BT48: 34.9 | BU48: N | BV48: =IF(OR(BF48<>"Y",BG48<>"Y"),"",(AND(ISNUMBER(BQ48),BQ48>0))+(BR48="Stacked up")+(AND(ISNUMBER(BH48),BH48>=-Settings!$B$17))+(AND(ISNUMBER(BK48),ISNUMBER(BM48),BK48>0,BM48>0))+(AND(ISNUMBER(AQ48),AQ48>=Settings!$B$18))+(AND(ISNUMBER(BT48),BT48>=Settings!$B$19,BT48<=Settings!$B$20))+(AND(ISNUMBER(AS48),AS48>0))+(AND(ISNUMBER(T48),ISNUMBER(M48),T48>=Settings!$B$21,M48>0))+(AND(ISNUMBER(AD48),ISNUMBER(M48),AD48>=Settings!$B$22,M48>0))+(AY48>=1)) | BW48: =IF(OR(AY48=0,BF48<>"Y",BG48<>"Y"),"",1+SUMPRODUCT(($A$6:$A$2604=A48)*($AY$6:$AY$2604>0)*($BF$6:$BF$2604="Y")*($BG$6:$BG$2604="Y")*(($AY$6:$AY$2604>AY48)+($AY$6:$AY$2604=AY48)*($AD$6:$AD$2604>AD48))))
A49: 46296 | B49: APOLLOHOSP | C49: INE437A01024 | D49: Healthcare | E49: Nifty 50 | F49: 116947 | G49: N | I49: N | J49: =IF(K49="","N","Y") | K49: =_xlfn.TEXTJOIN("; ",TRUE,IF(P49="52-wk low","52-wk low",""),IF(AND(AD49>=Settings!$B$12,M49<0),"Distribution",""),IF(AND(AJ49="Y",M49<0,AK49<-Settings!$B$13),"Long unwinding",""),IF(AND(AJ49="Y",M49<0,AK49>Settings!$B$13),"Short buildup","")) | L49: 8133.5 | M49: -0.39 | N49: 745 | O49: None | P49: None | Q49: 9.39 | R49: 4.49 | S49: 2.29 | T49: 2.53 | U49: 2.46 | V49: 1.16 | W49: 7 | X49: 66 | Y49: None | Z49: 55.48 | AA49: 0.87 | AB49: 0.92 | AC49: 2.03 | AD49: 2.37 | AE49: 2.34 | AF49: 1.06 | AG49: Normal | AH49: 0 | AI49: 0 | AJ49: Y | AK49: -2.67 | AL49: Long unwinding | AM49: 39 | AN49: None | AO49: 0 | AP49: 1.3 | AQ49: 74 | AR49: Y | AS49: 3.79 | AT49: =IF(AND(P49="52-wk high",T49>=Settings!$B$7),"Y","N") | AU49: =IF(AND(AD49>=Settings!$B$8,M49>0),"Y","N") | AV49: =IF(OR(AH49>Settings!$B$9,AI49>Settings!$B$9),"Y","N") | AW49: =IF(AJ49<>"Y","n/a",IF(AND(M49>0,AK49>Settings!$B$10),"Y","N")) | AX49: =IF(AO49>=Settings!$B$11,"Y","N") | AY49: =(AT49="Y")+(AU49="Y")+(AV49="Y")+(AW49="Y")+(AX49="Y") | AZ49: =IF(AY49=0,"None",_xlfn.TEXTJOIN(", ",TRUE(),IF(AT49="Y","Breakout",""),IF(AU49="Y","Accumulation",""),IF(AV49="Y","Institutional buying",""),IF(AW49="Y","Long buildup",""),IF(AX49="Y","Momentum leader",""))) | BA49: =IF(BW49="","","Passes "&AY49&" of 5 buy-side scans"&IF(G49="Y","; RED FLAG: filter out using Red flag column","")) | BB49: None | BC49: Y | BD49: PE > 50 | BF49: =IF(R49*100000>=Settings!$B$5,"Y","N") | BG49: =IF(F49>Settings!$B$6,"Y","N") | BH49: -10.33 | BI49: -8.49 | BJ49: -7.1 | BK49: -5.63 | BL49: 11.33 | BM49: 9.31 | BN49: -6.6 | BO49: -6.84 | BP49: -5.04 | BQ49: -1.53 | BR49: Mixed | BS49: Bearish cross | BT49: 23.4 | BU49: N | BV49: =IF(OR(BF49<>"Y",BG49<>"Y"),"",(AND(ISNUMBER(BQ49),BQ49>0))+(BR49="Stacked up")+(AND(ISNUMBER(BH49),BH49>=-Settings!$B$17))+(AND(ISNUMBER(BK49),ISNUMBER(BM49),BK49>0,BM49>0))+(AND(ISNUMBER(AQ49),AQ49>=Settings!$B$18))+(AND(ISNUMBER(BT49),BT49>=Settings!$B$19,BT49<=Settings!$B$20))+(AND(ISNUMBER(AS49),AS49>0))+(AND(ISNUMBER(T49),ISNUMBER(M49),T49>=Settings!$B$21,M49>0))+(AND(ISNUMBER(AD49),ISNUMBER(M49),AD49>=Settings!$B$22,M49>0))+(AY49>=1)) | BW49: =IF(OR(AY49=0,BF49<>"Y",BG49<>"Y"),"",1+SUMPRODUCT(($A$6:$A$2604=A49)*($AY$6:$AY$2604>0)*($BF$6:$BF$2604="Y")*($BG$6:$BG$2604="Y")*(($AY$6:$AY$2604>AY49)+($AY$6:$AY$2604=AY49)*($AD$6:$AD$2604>AD49))))
A50: 46296 | B50: HDFCLIFE | C50: INE795G01014 | D50: Financial Services | E50: Nifty 50 | F50: 116060 | G50: N | I50: N | J50: =IF(K50="","N","Y") | K50: =_xlfn.TEXTJOIN("; ",TRUE,IF(P50="52-wk low","52-wk low",""),IF(AND(AD50>=Settings!$B$12,M50<0),"Distribution",""),IF(AND(AJ50="Y",M50<0,AK50<-Settings!$B$13),"Long unwinding",""),IF(AND(AJ50="Y",M50<0,AK50>Settings!$B$13),"Short buildup","")) | L50: 534.2 | M50: 2.49 | N50: 153 | O50: None | P50: None | Q50: 40.09 | R50: 50.34 | S50: 0.82 | T50: 1.05 | U50: 1.1 | V50: 1.38 | W50: 10 | Y50: None | Z50: 44.22 | AA50: 0.86 | AB50: 0.8 | AC50: 0.73 | AD50: 0.84 | AE50: 0.87 | AF50: 0.88 | AG50: Normal | AH50: 0 | AI50: 0 | AJ50: Y | AK50: -0.48 | AL50: Short covering | AM50: 73 | AN50: None | AO50: 0 | AP50: 0.52 | AQ50: 7 | AR50: Y | AS50: 0.6 | AT50: =IF(AND(P50="52-wk high",T50>=Settings!$B$7),"Y","N") | AU50: =IF(AND(AD50>=Settings!$B$8,M50>0),"Y","N") | AV50: =IF(OR(AH50>Settings!$B$9,AI50>Settings!$B$9),"Y","N") | AW50: =IF(AJ50<>"Y","n/a",IF(AND(M50>0,AK50>Settings!$B$10),"Y","N")) | AX50: =IF(AO50>=Settings!$B$11,"Y","N") | AY50: =(AT50="Y")+(AU50="Y")+(AV50="Y")+(AW50="Y")+(AX50="Y") | AZ50: =IF(AY50=0,"None",_xlfn.TEXTJOIN(", ",TRUE(),IF(AT50="Y","Breakout",""),IF(AU50="Y","Accumulation",""),IF(AV50="Y","Institutional buying",""),IF(AW50="Y","Long buildup",""),IF(AX50="Y","Momentum leader",""))) | BA50: =IF(BW50="","","Passes "&AY50&" of 5 buy-side scans"&IF(G50="Y","; RED FLAG: filter out using Red flag column","")) | BB50: Lower | BC50: Y | BD50: PE > 50 | BF50: =IF(R50*100000>=Settings!$B$5,"Y","N") | BG50: =IF(F50>Settings!$B$6,"Y","N") | BH50: -32.25 | BI50: 1.39 | BJ50: -1.13 | BK50: -6.27 | BL50: -6.76 | BM50: -30.08 | BN50: -0.48 | BO50: -1.94 | BP50: -5.59 | BQ50: -12.37 | BR50: Stacked down | BS50: None | BT50: 48.6 | BU50: N | BV50: =IF(OR(BF50<>"Y",BG50<>"Y"),"",(AND(ISNUMBER(BQ50),BQ50>0))+(BR50="Stacked up")+(AND(ISNUMBER(BH50),BH50>=-Settings!$B$17))+(AND(ISNUMBER(BK50),ISNUMBER(BM50),BK50>0,BM50>0))+(AND(ISNUMBER(AQ50),AQ50>=Settings!$B$18))+(AND(ISNUMBER(BT50),BT50>=Settings!$B$19,BT50<=Settings!$B$20))+(AND(ISNUMBER(AS50),AS50>0))+(AND(ISNUMBER(T50),ISNUMBER(M50),T50>=Settings!$B$21,M50>0))+(AND(ISNUMBER(AD50),ISNUMBER(M50),AD50>=Settings!$B$22,M50>0))+(AY50>=1)) | BW50: =IF(OR(AY50=0,BF50<>"Y",BG50<>"Y"),"",1+SUMPRODUCT(($A$6:$A$2604=A50)*($AY$6:$AY$2604>0)*($BF$6:$BF$2604="Y")*($BG$6:$BG$2604="Y")*(($AY$6:$AY$2604>AY50)+($AY$6:$AY$2604=AY50)*($AD$6:$AD$2604>AD50))))
A51: 46296 | B51: CIPLA | C51: INE059A01026 | D51: Healthcare | E51: Nifty 50 | F51: 108576 | G51: N | I51: N | J51: =IF(K51="","N","Y") | K51: =_xlfn.TEXTJOIN("; ",TRUE,IF(P51="52-wk low","52-wk low",""),IF(AND(AD51>=Settings!$B$12,M51<0),"Distribution",""),IF(AND(AJ51="Y",M51<0,AK51<-Settings!$B$13),"Long unwinding",""),IF(AND(AJ51="Y",M51<0,AK51>Settings!$B$13),"Short buildup","")) | L51: 1344 | M51: -0.15 | N51: 660 | O51: None | P51: None | Q51: 9.22 | R51: 10.01 | S51: 0.94 | T51: 0.88 | U51: 0.65 | V51: 0.71 | W51: 3 | Y51: None | Z51: 52.66 | AA51: 0.93 | AB51: 0.96 | AC51: 0.89 | AD51: 0.88 | AE51: 0.67 | AF51: 1.08 | AG51: Normal | AH51: 0 | AI51: 0 | AJ51: Y | AK51: -0.24 | AL51: Long unwinding | AM51: 187 | AN51: None | AO51: 0 | AP51: 0.87 | AQ51: 55 | AR51: Y | AS51: 3.79 | AT51: =IF(AND(P51="52-wk high",T51>=Settings!$B$7),"Y","N") | AU51: =IF(AND(AD51>=Settings!$B$8,M51>0),"Y","N") | AV51: =IF(OR(AH51>Settings!$B$9,AI51>Settings!$B$9),"Y","N") | AW51: =IF(AJ51<>"Y","n/a",IF(AND(M51>0,AK51>Settings!$B$10),"Y","N")) | AX51: =IF(AO51>=Settings!$B$11,"Y","N") | AY51: =(AT51="Y")+(AU51="Y")+(AV51="Y")+(AW51="Y")+(AX51="Y") | AZ51: =IF(AY51=0,"None",_xlfn.TEXTJOIN(", ",TRUE(),IF(AT51="Y","Breakout",""),IF(AU51="Y","Accumulation",""),IF(AV51="Y","Institutional buying",""),IF(AW51="Y","Long buildup",""),IF(AX51="Y","Momentum leader",""))) | BA51: =IF(BW51="","","Passes "&AY51&" of 5 buy-side scans"&IF(G51="Y","; RED FLAG: filter out using Red flag column","")) | BB51: None | BC51: N | BF51: =IF(R51*100000>=Settings!$B$5,"Y","N") | BG51: =IF(F51>Settings!$B$6,"Y","N") | BH51: -19.67 | BI51: -3.93 | BJ51: -5.55 | BK51: -7.74 | BL51: 12.38 | BM51: -11.17 | BN51: -2.76 | BO51: -3.94 | BP51: -4.01 | BQ51: -4.63 | BR51: Stacked down | BS51: None | BT51: 30.3 | BU51: N | BV51: =IF(OR(BF51<>"Y",BG51<>"Y"),"",(AND(ISNUMBER(BQ51),BQ51>0))+(BR51="Stacked up")+(AND(ISNUMBER(BH51),BH51>=-Settings!$B$17))+(AND(ISNUMBER(BK51),ISNUMBER(BM51),BK51>0,BM51>0))+(AND(ISNUMBER(AQ51),AQ51>=Settings!$B$18))+(AND(ISNUMBER(BT51),BT51>=Settings!$B$19,BT51<=Settings!$B$20))+(AND(ISNUMBER(AS51),AS51>0))+(AND(ISNUMBER(T51),ISNUMBER(M51),T51>=Settings!$B$21,M51>0))+(AND(ISNUMBER(AD51),ISNUMBER(M51),AD51>=Settings!$B$22,M51>0))+(AY51>=1)) | BW51: =IF(OR(AY51=0,BF51<>"Y",BG51<>"Y"),"",1+SUMPRODUCT(($A$6:$A$2604=A51)*($AY$6:$AY$2604>0)*($BF$6:$BF$2604="Y")*($BG$6:$BG$2604="Y")*(($AY$6:$AY$2604>AY51)+($AY$6:$AY$2604=AY51)*($AD$6:$AD$2604>AD51))))
A52: 46296 | B52: TMPV | C52: INE155A01022 | D52: Automobile and Auto Components | E52: Nifty 50 | F52: 102907 | G52: N | I52: N | J52: =IF(K52="","N","Y") | K52: =_xlfn.TEXTJOIN("; ",TRUE,IF(P52="52-wk low","52-wk low",""),IF(AND(AD52>=Settings!$B$12,M52<0),"Distribution",""),IF(AND(AJ52="Y",M52<0,AK52<-Settings!$B$13),"Long unwinding",""),IF(AND(AJ52="Y",M52<0,AK52>Settings!$B$13),"Short buildup","")) | L52: 279.4 | M52: -1.45 | N52: 1284 | O52: None | P52: None | Q52: 152.58 | R52: 108.82 | S52: 1.46 | T52: 1.6 | U52: 1.37 | V52: 0.97 | W52: 9 | X52: 192 | Y52: None | Z52: 50.67 | AA52: 1.06 | AB52: 1.04 | AC52: 1.54 | AD52: 1.66 | AE52: 1.52 | AF52: 1.05 | AG52: Normal | AH52: 0 | AI52: 0 | AJ52: Y | AK52: -1.43 | AL52: Long unwinding | AM52: 63 | AN52: None | AO52: 0 | AP52: 0.57 | AQ52: 14 | AR52: Y | AS52: 0.56 | AT52: =IF(AND(P52="52-wk high",T52>=Settings!$B$7),"Y","N") | AU52: =IF(AND(AD52>=Settings!$B$8,M52>0),"Y","N") | AV52: =IF(OR(AH52>Settings!$B$9,AI52>Settings!$B$9),"Y","N") | AW52: =IF(AJ52<>"Y","n/a",IF(AND(M52>0,AK52>Settings!$B$10),"Y","N")) | AX52: =IF(AO52>=Settings!$B$11,"Y","N") | AY52: =(AT52="Y")+(AU52="Y")+(AV52="Y")+(AW52="Y")+(AX52="Y") | AZ52: =IF(AY52=0,"None",_xlfn.TEXTJOIN(", ",TRUE(),IF(AT52="Y","Breakout",""),IF(AU52="Y","Accumulation",""),IF(AV52="Y","Institutional buying",""),IF(AW52="Y","Long buildup",""),IF(AX52="Y","Momentum leader",""))) | BA52: =IF(BW52="","","Passes "&AY52&" of 5 buy-side scans"&IF(G52="Y","; RED FLAG: filter out using Red flag column","")) | BB52: None | BC52: N | BF52: =IF(R52*100000>=Settings!$B$5,"Y","N") | BG52: =IF(F52>Settings!$B$6,"Y","N") | BH52: -62.23 | BI52: -5.29 | BJ52: -9.87 | BK52: -19.67 | BL52: -7.77 | BM52: -61.11 | BN52: -6.11 | BO52: -10.87 | BP52: -15.44 | BQ52: -24.49 | BR52: Stacked down | BS52: None | BT52: 24.2 | BU52: N | BV52: =IF(OR(BF52<>"Y",BG52<>"Y"),"",(AND(ISNUMBER(BQ52),BQ52>0))+(BR52="Stacked up")+(AND(ISNUMBER(BH52),BH52>=-Settings!$B$17))+(AND(ISNUMBER(BK52),ISNUMBER(BM52),BK52>0,BM52>0))+(AND(ISNUMBER(AQ52),AQ52>=Settings!$B$18))+(AND(ISNUMBER(BT52),BT52>=Settings!$B$19,BT52<=Settings!$B$20))+(AND(ISNUMBER(AS52),AS52>0))+(AND(ISNUMBER(T52),ISNUMBER(M52),T52>=Settings!$B$21,M52>0))+(AND(ISNUMBER(AD52),ISNUMBER(M52),AD52>=Settings!$B$22,M52>0))+(AY52>=1)) | BW52: =IF(OR(AY52=0,BF52<>"Y",BG52<>"Y"),"",1+SUMPRODUCT(($A$6:$A$2604=A52)*($AY$6:$AY$2604>0)*($BF$6:$BF$2604="Y")*($BG$6:$BG$2604="Y")*(($AY$6:$AY$2604>AY52)+($AY$6:$AY$2604=AY52)*($AD$6:$AD$2604>AD52))))
A53: 46296 | B53: DRREDDY | C53: INE089A01031 | D53: Healthcare | E53: Nifty 50 | F53: 100679 | G53: N | I53: N | J53: =IF(K53="","N","Y") | K53: =_xlfn.TEXTJOIN("; ",TRUE,IF(P53="52-wk low","52-wk low",""),IF(AND(AD53>=Settings!$B$12,M53<0),"Distribution",""),IF(AND(AJ53="Y",M53<0,AK53<-Settings!$B$13),"Long unwinding",""),IF(AND(AJ53="Y",M53<0,AK53>Settings!$B$13),"Short buildup","")) | L53: 1206.2 | M53: -2.17 | N53: 1732 | O53: None | P53: None | Q53: 26.08 | R53: 19.45 | S53: 1.42 | T53: 1.38 | U53: 1.23 | V53: 0.91 | W53: 8 | X53: 226 | Y53: None | Z53: 65.2 | AA53: 1.16 | AB53: 1.17 | AC53: 1.7 | AD53: 1.65 | AE53: 1.52 | AF53: 1.04 | AG53: Normal | AH53: 0 | AI53: 0 | AJ53: Y | AK53: -1.99 | AL53: Long unwinding | AM53: 102 | AN53: None | AO53: 0 | AP53: 0.78 | AQ53: 47 | AR53: Y | AS53: 3.79 | AT53: =IF(AND(P53="52-wk high",T53>=Settings!$B$7),"Y","N") | AU53: =IF(AND(AD53>=Settings!$B$8,M53>0),"Y","N") | AV53: =IF(OR(AH53>Settings!$B$9,AI53>Settings!$B$9),"Y","N") | AW53: =IF(AJ53<>"Y","n/a",IF(AND(M53>0,AK53>Settings!$B$10),"Y","N")) | AX53: =IF(AO53>=Settings!$B$11,"Y","N") | AY53: =(AT53="Y")+(AU53="Y")+(AV53="Y")+(AW53="Y")+(AX53="Y") | AZ53: =IF(AY53=0,"None",_xlfn.TEXTJOIN(", ",TRUE(),IF(AT53="Y","Breakout",""),IF(AU53="Y","Accumulation",""),IF(AV53="Y","Institutional buying",""),IF(AW53="Y","Long buildup",""),IF(AX53="Y","Momentum leader",""))) | BA53: =IF(BW53="","","Passes "&AY53&" of 5 buy-side scans"&IF(G53="Y","; RED FLAG: filter out using Red flag column","")) | BB53: None | BC53: N | BF53: =IF(R53*100000>=Settings!$B$5,"Y","N") | BG53: =IF(F53>Settings!$B$6,"Y","N") | BH53: -14.75 | BI53: 0.48 | BJ53: 3.01 | BK53: -9.98 | BL53: -0.28 | BM53: -3.09 | BN53: 0.88 | BO53: 0.81 | BP53: -0.84 | BQ53: -2.58 | BR53: Mixed | BS53: None | BT53: 53.1 | BU53: N | BV53: =IF(OR(BF53<>"Y",BG53<>"Y"),"",(AND(ISNUMBER(BQ53),BQ53>0))+(BR53="Stacked up")+(AND(ISNUMBER(BH53),BH53>=-Settings!$B$17))+(AND(ISNUMBER(BK53),ISNUMBER(BM53),BK53>0,BM53>0))+(AND(ISNUMBER(AQ53),AQ53>=Settings!$B$18))+(AND(ISNUMBER(BT53),BT53>=Settings!$B$19,BT53<=Settings!$B$20))+(AND(ISNUMBER(AS53),AS53>0))+(AND(ISNUMBER(T53),ISNUMBER(M53),T53>=Settings!$B$21,M53>0))+(AND(ISNUMBER(AD53),ISNUMBER(M53),AD53>=Settings!$B$22,M53>0))+(AY53>=1)) | BW53: =IF(OR(AY53=0,BF53<>"Y",BG53<>"Y"),"",1+SUMPRODUCT(($A$6:$A$2604=A53)*($AY$6:$AY$2604>0)*($BF$6:$BF$2604="Y")*($BG$6:$BG$2604="Y")*(($AY$6:$AY$2604>AY53)+($AY$6:$AY$2604=AY53)*($AD$6:$AD$2604>AD53))))
A54: 46296 | B54: TATACONSUM | C54: INE192A01025 | D54: Fast Moving Consumer Goods | E54: Nifty 50 | F54: 94714 | G54: N | I54: N | J54: =IF(K54="","N","Y") | K54: =_xlfn.TEXTJOIN("; ",TRUE,IF(P54="52-wk low","52-wk low",""),IF(AND(AD54>=Settings!$B$12,M54<0),"Distribution",""),IF(AND(AJ54="Y",M54<0,AK54<-Settings!$B$13),"Long unwinding",""),IF(AND(AJ54="Y",M54<0,AK54>Settings!$B$13),"Short buildup","")) | L54: 957 | M54: 0.79 | N54: 381 | O54: None | P54: 52-wk low | Q54: 18.29 | R54: 12.74 | S54: 1.48 | T54: 1.38 | U54: 1.04 | V54: 0.8 | W54: 4 | X54: 233 | Y54: None | Z54: 62.53 | AA54: 1.01 | AB54: 1.05 | AC54: 1.49 | AD54: 1.45 | AE54: 1.16 | AF54: 1.05 | AG54: Normal | AH54: 0 | AI54: 0 | AJ54: Y | AK54: -0.73 | AL54: Short covering | AM54: 159 | AN54: None | AO54: 0 | AP54: 0.59 | AQ54: 18 | AR54: Y | AS54: 2.11 | AT54: =IF(AND(P54="52-wk high",T54>=Settings!$B$7),"Y","N") | AU54: =IF(AND(AD54>=Settings!$B$8,M54>0),"Y","N") | AV54: =IF(OR(AH54>Settings!$B$9,AI54>Settings!$B$9),"Y","N") | AW54: =IF(AJ54<>"Y","n/a",IF(AND(M54>0,AK54>Settings!$B$10),"Y","N")) | AX54: =IF(AO54>=Settings!$B$11,"Y","N") | AY54: =(AT54="Y")+(AU54="Y")+(AV54="Y")+(AW54="Y")+(AX54="Y") | AZ54: =IF(AY54=0,"None",_xlfn.TEXTJOIN(", ",TRUE(),IF(AT54="Y","Breakout",""),IF(AU54="Y","Accumulation",""),IF(AV54="Y","Institutional buying",""),IF(AW54="Y","Long buildup",""),IF(AX54="Y","Momentum leader",""))) | BA54: =IF(BW54="","","Passes "&AY54&" of 5 buy-side scans"&IF(G54="Y","; RED FLAG: filter out using Red flag column","")) | BB54: None | BC54: Y | BD54: PE > 50 | BF54: =IF(R54*100000>=Settings!$B$5,"Y","N") | BG54: =IF(F54>Settings!$B$6,"Y","N") | BH54: -25.39 | BI54: -2.97 | BJ54: -7.13 | BK54: -12.27 | BL54: -6.52 | BM54: -16.4 | BN54: -3.49 | BO54: -7.03 | BP54: -10.09 | BQ54: -12.63 | BR54: Stacked down | BS54: None | BT54: 32.8 | BU54: N | BV54: =IF(OR(BF54<>"Y",BG54<>"Y"),"",(AND(ISNUMBER(BQ54),BQ54>0))+(BR54="Stacked up")+(AND(ISNUMBER(BH54),BH54>=-Settings!$B$17))+(AND(ISNUMBER(BK54),ISNUMBER(BM54),BK54>0,BM54>0))+(AND(ISNUMBER(AQ54),AQ54>=Settings!$B$18))+(AND(ISNUMBER(BT54),BT54>=Settings!$B$19,BT54<=Settings!$B$20))+(AND(ISNUMBER(AS54),AS54>0))+(AND(ISNUMBER(T54),ISNUMBER(M54),T54>=Settings!$B$21,M54>0))+(AND(ISNUMBER(AD54),ISNUMBER(M54),AD54>=Settings!$B$22,M54>0))+(AY54>=1)) | BW54: =IF(OR(AY54=0,BF54<>"Y",BG54<>"Y"),"",1+SUMPRODUCT(($A$6:$A$2604=A54)*($AY$6:$AY$2604>0)*($BF$6:$BF$2604="Y")*($BG$6:$BG$2604="Y")*(($AY$6:$AY$2604>AY54)+($AY$6:$AY$2604=AY54)*($AD$6:$AD$2604>AD54))))
A55: 46296 | B55: MAXHEALTH | C55: INE027H01010 | D55: Healthcare | E55: Nifty 50 | F55: 91584 | G55: N | I55: N | J55: =IF(K55="","N","Y") | K55: =_xlfn.TEXTJOIN("; ",TRUE,IF(P55="52-wk low","52-wk low",""),IF(AND(AD55>=Settings!$B$12,M55<0),"Distribution",""),IF(AND(AJ55="Y",M55<0,AK55<-Settings!$B$13),"Long unwinding",""),IF(AND(AJ55="Y",M55<0,AK55>Settings!$B$13),"Short buildup","")) | L55: 940.95 | M55: 1.2 | N55: 294 | O55: None | P55: 52-wk low | Q55: 54.64 | R55: 27.56 | S55: 2.15 | T55: 2.58 | U55: 2.24 | V55: 1.12 | W55: 9 | X55: 75 | Y55: None | Z55: 52.55 | AA55: 0.94 | AB55: 0.94 | AC55: 2.04 | AD55: 2.45 | AE55: 2.15 | AF55: 1.01 | AG55: Normal | AH55: 0 | AI55: 0 | AJ55: Y | AK55: -0.89 | AL55: Short covering | AM55: 72 | AN55: None | AO55: 0 | AP55: 0.66 | AQ55: 30 | AR55: Y | AS55: 3.79 | AT55: =IF(AND(P55="52-wk high",T55>=Settings!$B$7),"Y","N") | AU55: =IF(AND(AD55>=Settings!$B$8,M55>0),"Y","N") | AV55: =IF(OR(AH55>Settings!$B$9,AI55>Settings!$B$9),"Y","N") | AW55: =IF(AJ55<>"Y","n/a",IF(AND(M55>0,AK55>Settings!$B$10),"Y","N")) | AX55: =IF(AO55>=Settings!$B$11,"Y","N") | AY55: =(AT55="Y")+(AU55="Y")+(AV55="Y")+(AW55="Y")+(AX55="Y") | AZ55: =IF(AY55=0,"None",_xlfn.TEXTJOIN(", ",TRUE(),IF(AT55="Y","Breakout",""),IF(AU55="Y","Accumulation",""),IF(AV55="Y","Institutional buying",""),IF(AW55="Y","Long buildup",""),IF(AX55="Y","Momentum leader",""))) | BA55: =IF(BW55="","","Passes "&AY55&" of 5 buy-side scans"&IF(G55="Y","; RED FLAG: filter out using Red flag column","")) | BB55: Lower | BC55: Y | BD55: PE > 50 | BF55: =IF(R55*100000>=Settings!$B$5,"Y","N") | BG55: =IF(F55>Settings!$B$6,"Y","N") | BH55: -22.99 | BI55: -10.04 | BJ55: -6.19 | BK55: -17.45 | BL55: -1.87 | BM55: -15.47 | BN55: -6.77 | BO55: -8.37 | BP55: -9.19 | BQ55: -10.27 | BR55: Stacked down | BS55: None | BT55: 26.5 | BU55: N | BV55: =IF(OR(BF55<>"Y",BG55<>"Y"),"",(AND(ISNUMBER(BQ55),BQ55>0))+(BR55="Stacked up")+(AND(ISNUMBER(BH55),BH55>=-Settings!$B$17))+(AND(ISNUMBER(BK55),ISNUMBER(BM55),BK55>0,BM55>0))+(AND(ISNUMBER(AQ55),AQ55>=Settings!$B$18))+(AND(ISNUMBER(BT55),BT55>=Settings!$B$19,BT55<=Settings!$B$20))+(AND(ISNUMBER(AS55),AS55>0))+(AND(ISNUMBER(T55),ISNUMBER(M55),T55>=Settings!$B$21,M55>0))+(AND(ISNUMBER(AD55),ISNUMBER(M55),AD55>=Settings!$B$22,M55>0))+(AY55>=1)) | BW55: =IF(OR(AY55=0,BF55<>"Y",BG55<>"Y"),"",1+SUMPRODUCT(($A$6:$A$2604=A55)*($AY$6:$AY$2604>0)*($BF$6:$BF$2604="Y")*($BG$6:$BG$2604="Y")*(($AY$6:$AY$2604>AY55)+($AY$6:$AY$2604=AY55)*($AD$6:$AD$2604>AD55))))
A56: 46296 | B56: ADANIPOWER | C56: INE814H01029 | D56: Power | E56: Nifty Next 50 | F56: 378385 | G56: N | I56: N | J56: =IF(K56="","N","Y") | K56: =_xlfn.TEXTJOIN("; ",TRUE,IF(P56="52-wk low","52-wk low",""),IF(AND(AD56>=Settings!$B$12,M56<0),"Distribution",""),IF(AND(AJ56="Y",M56<0,AK56<-Settings!$B$13),"Long unwinding",""),IF(AND(AJ56="Y",M56<0,AK56>Settings!$B$13),"Short buildup","")) | L56: 196.21 | M56: -3.82 | N56: 2305 | O56: None | P56: None | Q56: 335.48 | R56: 180.51 | S56: 1.94 | T56: 1.74 | U56: 1.21 | V56: 0.65 | W56: 2 | X56: 161 | Y56: None | Z56: 41.4 | AA56: 1.02 | AB56: 1.05 | AC56: 1.93 | AD56: 1.8 | AE56: 1.4 | AF56: 1.18 | AG56: Normal | AH56: 0 | AI56: 0 | AJ56: Y | AK56: 0.59 | AL56: Short buildup | AM56: 47 | AN56: 200 Mom 30; 500 Mom 50 | AO56: 2 | AP56: 1.53 | AQ56: 80 | AR56: Y | AS56: 3.38 | AT56: =IF(AND(P56="52-wk high",T56>=Settings!$B$7),"Y","N") | AU56: =IF(AND(AD56>=Settings!$B$8,M56>0),"Y","N") | AV56: =IF(OR(AH56>Settings!$B$9,AI56>Settings!$B$9),"Y","N") | AW56: =IF(AJ56<>"Y","n/a",IF(AND(M56>0,AK56>Settings!$B$10),"Y","N")) | AX56: =IF(AO56>=Settings!$B$11,"Y","N") | AY56: =(AT56="Y")+(AU56="Y")+(AV56="Y")+(AW56="Y")+(AX56="Y") | AZ56: =IF(AY56=0,"None",_xlfn.TEXTJOIN(", ",TRUE(),IF(AT56="Y","Breakout",""),IF(AU56="Y","Accumulation",""),IF(AV56="Y","Institutional buying",""),IF(AW56="Y","Long buildup",""),IF(AX56="Y","Momentum leader",""))) | BA56: =IF(BW56="","","Passes "&AY56&" of 5 buy-side scans"&IF(G56="Y","; RED FLAG: filter out using Red flag column","")) | BB56: Upper | BC56: N | BF56: =IF(R56*100000>=Settings!$B$5,"Y","N") | BG56: =IF(F56>Settings!$B$6,"Y","N") | BH56: -22.81 | BI56: -1.64 | BJ56: -3.99 | BK56: -13.51 | BL56: 24.89 | BM56: 28.65 | BN56: -3.53 | BO56: -5.19 | BP56: -4.37 | BQ56: 1.61 | BR56: Mixed | BS56: None | BT56: 39.5 | BU56: N | BV56: =IF(OR(BF56<>"Y",BG56<>"Y"),"",(AND(ISNUMBER(BQ56),BQ56>0))+(BR56="Stacked up")+(AND(ISNUMBER(BH56),BH56>=-Settings!$B$17))+(AND(ISNUMBER(BK56),ISNUMBER(BM56),BK56>0,BM56>0))+(AND(ISNUMBER(AQ56),AQ56>=Settings!$B$18))+(AND(ISNUMBER(BT56),BT56>=Settings!$B$19,BT56<=Settings!$B$20))+(AND(ISNUMBER(AS56),AS56>0))+(AND(ISNUMBER(T56),ISNUMBER(M56),T56>=Settings!$B$21,M56>0))+(AND(ISNUMBER(AD56),ISNUMBER(M56),AD56>=Settings!$B$22,M56>0))+(AY56>=1)) | BW56: =IF(OR(AY56=0,BF56<>"Y",BG56<>"Y"),"",1+SUMPRODUCT(($A$6:$A$2604=A56)*($AY$6:$AY$2604>0)*($BF$6:$BF$2604="Y")*($BG$6:$BG$2604="Y")*(($AY$6:$AY$2604>AY56)+($AY$6:$AY$2604=AY56)*($AD$6:$AD$2604>AD56))))
A57: 46296 | B57: HAL | C57: INE066F01020 | D57: Capital Goods | E57: Nifty Next 50 | F57: 307703 | G57: N | I57: N | J57: =IF(K57="","N","Y") | K57: =_xlfn.TEXTJOIN("; ",TRUE,IF(P57="52-wk low","52-wk low",""),IF(AND(AD57>=Settings!$B$12,M57<0),"Distribution",""),IF(AND(AJ57="Y",M57<0,AK57<-Settings!$B$13),"Long unwinding",""),IF(AND(AJ57="Y",M57<0,AK57>Settings!$B$13),"Short buildup","")) | L57: 4601 | M57: -1.44 | N57: 1279 | O57: None | P57: None | Q57: 7.4 | R57: 8.73 | S57: 0.86 | T57: 0.8 | U57: 0.77 | V57: 0.91 | W57: 5 | Y57: None | Z57: 42.55 | AA57: 0.88 | AB57: 0.91 | AC57: 0.76 | AD57: 0.74 | AE57: 0.69 | AF57: 1.01 | AG57: Normal | AH57: 0 | AI57: 0 | AJ57: Y | AK57: -0.99 | AL57: Long unwinding | AM57: 94 | AN57: None | AO57: 0 | AP57: 1.19 | AQ57: 69 | AR57: Y | AS57: 5.9 | AT57: =IF(AND(P57="52-wk high",T57>=Settings!$B$7),"Y","N") | AU57: =IF(AND(AD57>=Settings!$B$8,M57>0),"Y","N") | AV57: =IF(OR(AH57>Settings!$B$9,AI57>Settings!$B$9),"Y","N") | AW57: =IF(AJ57<>"Y","n/a",IF(AND(M57>0,AK57>Settings!$B$10),"Y","N")) | AX57: =IF(AO57>=Settings!$B$11,"Y","N") | AY57: =(AT57="Y")+(AU57="Y")+(AV57="Y")+(AW57="Y")+(AX57="Y") | AZ57: =IF(AY57=0,"None",_xlfn.TEXTJOIN(", ",TRUE(),IF(AT57="Y","Breakout",""),IF(AU57="Y","Accumulation",""),IF(AV57="Y","Institutional buying",""),IF(AW57="Y","Long buildup",""),IF(AX57="Y","Momentum leader",""))) | BA57: =IF(BW57="","","Passes "&AY57&" of 5 buy-side scans"&IF(G57="Y","; RED FLAG: filter out using Red flag column","")) | BB57: None | BC57: N | BF57: =IF(R57*100000>=Settings!$B$5,"Y","N") | BG57: =IF(F57>Settings!$B$6,"Y","N") | BH57: -10.66 | BI57: -3.63 | BJ57: -4.3 | BK57: 3.76 | BL57: 25.34 | BM57: -4.21 | BN57: -3.42 | BO57: -3.14 | BP57: -0.92 | BQ57: 0.97 | BR57: Mixed | BS57: None | BT57: 36.5 | BU57: N | BV57: =IF(OR(BF57<>"Y",BG57<>"Y"),"",(AND(ISNUMBER(BQ57),BQ57>0))+(BR57="Stacked up")+(AND(ISNUMBER(BH57),BH57>=-Settings!$B$17))+(AND(ISNUMBER(BK57),ISNUMBER(BM57),BK57>0,BM57>0))+(AND(ISNUMBER(AQ57),AQ57>=Settings!$B$18))+(AND(ISNUMBER(BT57),BT57>=Settings!$B$19,BT57<=Settings!$B$20))+(AND(ISNUMBER(AS57),AS57>0))+(AND(ISNUMBER(T57),ISNUMBER(M57),T57>=Settings!$B$21,M57>0))+(AND(ISNUMBER(AD57),ISNUMBER(M57),AD57>=Settings!$B$22,M57>0))+(AY57>=1)) | BW57: =IF(OR(AY57=0,BF57<>"Y",BG57<>"Y"),"",1+SUMPRODUCT(($A$6:$A$2604=A57)*($AY$6:$AY$2604>0)*($BF$6:$BF$2604="Y")*($BG$6:$BG$2604="Y")*(($AY$6:$AY$2604>AY57)+($AY$6:$AY$2604=AY57)*($AD$6:$AD$2604>AD57))))
A58: 46296 | B58: DMART | C58: INE192R01011 | D58: Consumer Services | E58: Nifty Next 50 | F58: 248701 | G58: N | I58: N | J58: =IF(K58="","N","Y") | K58: =_xlfn.TEXTJOIN("; ",TRUE,IF(P58="52-wk low","52-wk low",""),IF(AND(AD58>=Settings!$B$12,M58<0),"Distribution",""),IF(AND(AJ58="Y",M58<0,AK58<-Settings!$B$13),"Long unwinding",""),IF(AND(AJ58="Y",M58<0,AK58>Settings!$B$13),"Short buildup","")) | L58: 3813 | M58: 0.31 | N58: 493 | O58: None | P58: None | Q58: 6.52 | R58: 4.61 | S58: 1.49 | T58: 1.29 | U58: 1.22 | V58: 0.86 | W58: 6 | X58: 228 | Y58: None | Z58: 49.44 | AA58: 0.8 | AB58: 0.9 | AC58: 1.17 | AD58: 1.21 | AE58: 1.13 | AF58: 1.16 | AG58: Normal | AH58: 0 | AI58: 0 | AJ58: Y | AK58: -1.26 | AL58: Short covering | AM58: 83 | AN58: None | AO58: 0 | AP58: 0.58 | AQ58: 16 | AR58: Y | AS58: 2.34 | AT58: =IF(AND(P58="52-wk high",T58>=Settings!$B$7),"Y","N") | AU58: =IF(AND(AD58>=Settings!$B$8,M58>0),"Y","N") | AV58: =IF(OR(AH58>Settings!$B$9,AI58>Settings!$B$9),"Y","N") | AW58: =IF(AJ58<>"Y","n/a",IF(AND(M58>0,AK58>Settings!$B$10),"Y","N")) | AX58: =IF(AO58>=Settings!$B$11,"Y","N") | AY58: =(AT58="Y")+(AU58="Y")+(AV58="Y")+(AW58="Y")+(AX58="Y") | AZ58: =IF(AY58=0,"None",_xlfn.TEXTJOIN(", ",TRUE(),IF(AT58="Y","Breakout",""),IF(AU58="Y","Accumulation",""),IF(AV58="Y","Institutional buying",""),IF(AW58="Y","Long buildup",""),IF(AX58="Y","Momentum leader",""))) | BA58: =IF(BW58="","","Passes "&AY58&" of 5 buy-side scans"&IF(G58="Y","; RED FLAG: filter out using Red flag column","")) | BB58: None | BC58: Y | BD58: PE > 50 | BF58: =IF(R58*100000>=Settings!$B$5,"Y","N") | BG58: =IF(F58>Settings!$B$6,"Y","N") | BH58: -17.89 | BI58: 0.67 | BJ58: -0.29 | BK58: -11.91 | BL58: -10.73 | BM58: -14.31 | BN58: 0.52 | BO58: -1.36 | BP58: -3.54 | BQ58: -5.85 | BR58: Mixed | BS58: None | BT58: 54.1 | BU58: N | BV58: =IF(OR(BF58<>"Y",BG58<>"Y"),"",(AND(ISNUMBER(BQ58),BQ58>0))+(BR58="Stacked up")+(AND(ISNUMBER(BH58),BH58>=-Settings!$B$17))+(AND(ISNUMBER(BK58),ISNUMBER(BM58),BK58>0,BM58>0))+(AND(ISNUMBER(AQ58),AQ58>=Settings!$B$18))+(AND(ISNUMBER(BT58),BT58>=Settings!$B$19,BT58<=Settings!$B$20))+(AND(ISNUMBER(AS58),AS58>0))+(AND(ISNUMBER(T58),ISNUMBER(M58),T58>=Settings!$B$21,M58>0))+(AND(ISNUMBER(AD58),ISNUMBER(M58),AD58>=Settings!$B$22,M58>0))+(AY58>=1)) | BW58: =IF(OR(AY58=0,BF58<>"Y",BG58<>"Y"),"",1+SUMPRODUCT(($A$6:$A$2604=A58)*($AY$6:$AY$2604>0)*($BF$6:$BF$2604="Y")*($BG$6:$BG$2604="Y")*(($AY$6:$AY$2604>AY58)+($AY$6:$AY$2604=AY58)*($AD$6:$AD$2604>AD58))))
A59: 46296 | B59: DIVISLAB | C59: INE361B01024 | D59: Healthcare | E59: Nifty Next 50 | F59: 245532 | G59: N | I59: N | J59: =IF(K59="","N","Y") | K59: =_xlfn.TEXTJOIN("; ",TRUE,IF(P59="52-wk low","52-wk low",""),IF(AND(AD59>=Settings!$B$12,M59<0),"Distribution",""),IF(AND(AJ59="Y",M59<0,AK59<-Settings!$B$13),"Long unwinding",""),IF(AND(AJ59="Y",M59<0,AK59>Settings!$B$13),"Short buildup","")) | L59: 9249 | M59: -0.46 | N59: 776 | O59: None | P59: None | Q59: 5.67 | R59: 5.07 | S59: 1.14 | T59: 1.11 | U59: 1.25 | V59: 1.11 | W59: 10 | X59: 272 | Y59: None | Z59: 67.14 | AA59: 1.06 | AB59: 1.12 | AC59: 1.2 | AD59: 1.28 | AE59: 1.46 | AF59: 1.11 | AG59: Normal | AH59: 0 | AI59: 0 | AJ59: Y | AK59: 0.99 | AL59: Short buildup | AM59: 50 | AN59: None | AO59: 0 | AP59: 3.21 | AQ59: 97 | AR59: Y | AS59: 3.79 | AT59: =IF(AND(P59="52-wk high",T59>=Settings!$B$7),"Y","N") | AU59: =IF(AND(AD59>=Settings!$B$8,M59>0),"Y","N") | AV59: =IF(OR(AH59>Settings!$B$9,AI59>Settings!$B$9),"Y","N") | AW59: =IF(AJ59<>"Y","n/a",IF(AND(M59>0,AK59>Settings!$B$10),"Y","N")) | AX59: =IF(AO59>=Settings!$B$11,"Y","N") | AY59: =(AT59="Y")+(AU59="Y")+(AV59="Y")+(AW59="Y")+(AX59="Y") | AZ59: =IF(AY59=0,"None",_xlfn.TEXTJOIN(", ",TRUE(),IF(AT59="Y","Breakout",""),IF(AU59="Y","Accumulation",""),IF(AV59="Y","Institutional buying",""),IF(AW59="Y","Long buildup",""),IF(AX59="Y","Momentum leader",""))) | BA59: =IF(BW59="","","Passes "&AY59&" of 5 buy-side scans"&IF(G59="Y","; RED FLAG: filter out using Red flag column","")) | BB59: None | BC59: Y | BD59: PE > 50 | BF59: =IF(R59*100000>=Settings!$B$5,"Y","N") | BG59: =IF(F59>Settings!$B$6,"Y","N") | BH59: -5.04 | BI59: -3.68 | BJ59: 0.92 | BK59: 41.3 | BL59: 56.59 | BM59: 61.98 | BN59: -0.67 | BO59: 5.17 | BP59: 14.03 | BQ59: 24.68 | BR59: Mixed | BS59: None | BT59: 43.6 | BU59: N | BV59: =IF(OR(BF59<>"Y",BG59<>"Y"),"",(AND(ISNUMBER(BQ59),BQ59>0))+(BR59="Stacked up")+(AND(ISNUMBER(BH59),BH59>=-Settings!$B$17))+(AND(ISNUMBER(BK59),ISNUMBER(BM59),BK59>0,BM59>0))+(AND(ISNUMBER(AQ59),AQ59>=Settings!$B$18))+(AND(ISNUMBER(BT59),BT59>=Settings!$B$19,BT59<=Settings!$B$20))+(AND(ISNUMBER(AS59),AS59>0))+(AND(ISNUMBER(T59),ISNUMBER(M59),T59>=Settings!$B$21,M59>0))+(AND(ISNUMBER(AD59),ISNUMBER(M59),AD59>=Settings!$B$22,M59>0))+(AY59>=1)) | BW59: =IF(OR(AY59=0,BF59<>"Y",BG59<>"Y"),"",1+SUMPRODUCT(($A$6:$A$2604=A59)*($AY$6:$AY$2604>0)*($BF$6:$BF$2604="Y")*($BG$6:$BG$2604="Y")*(($AY$6:$AY$2604>AY59)+($AY$6:$AY$2604=AY59)*($AD$6:$AD$2604>AD59))))
A60: 46296 | B60: HINDZINC | C60: INE267A01025 | D60: Metals & Mining | E60: Nifty Next 50 | F60: 234526 | G60: Y | H60: Promoter pledge / encumbrance > 50% | I60: N | J60: =IF(K60="","N","Y") | K60: =_xlfn.TEXTJOIN("; ",TRUE,IF(P60="52-wk low","52-wk low",""),IF(AND(AD60>=Settings!$B$12,M60<0),"Distribution",""),IF(AND(AJ60="Y",M60<0,AK60<-Settings!$B$13),"Long unwinding",""),IF(AND(AJ60="Y",M60<0,AK60>Settings!$B$13),"Short buildup","")) | L60: 555.05 | M60: -1.93 | N60: 1597 | O60: None | P60: None | Q60: 31.65 | R60: 43.23 | S60: 0.73 | T60: 0.58 | U60: 0.64 | V60: 0.87 | W60: 3 | Y60: None | Z60: 50.51 | AA60: 1.03 | AB60: 1.13 | AC60: 0.76 | AD60: 0.7 | AE60: 0.77 | AF60: 1.15 | AG60: Normal | AH60: 0 | AI60: 0 | AJ60: Y | AK60: -2.62 | AL60: Long unwinding | AM60: 128 | AN60: None | AO60: 0 | AP60: 1.04 | AQ60: 64 | AR60: Y | AS60: -1.09 | AT60: =IF(AND(P60="52-wk high",T60>=Settings!$B$7),"Y","N") | AU60: =IF(AND(AD60>=Settings!$B$8,M60>0),"Y","N") | AV60: =IF(OR(AH60>Settings!$B$9,AI60>Settings!$B$9),"Y","N") | AW60: =IF(AJ60<>"Y","n/a",IF(AND(M60>0,AK60>Settings!$B$10),"Y","N")) | AX60: =IF(AO60>=Settings!$B$11,"Y","N") | AY60: =(AT60="Y")+(AU60="Y")+(AV60="Y")+(AW60="Y")+(AX60="Y") | AZ60: =IF(AY60=0,"None",_xlfn.TEXTJOIN(", ",TRUE(),IF(AT60="Y","Breakout",""),IF(AU60="Y","Accumulation",""),IF(AV60="Y","Institutional buying",""),IF(AW60="Y","Long buildup",""),IF(AX60="Y","Momentum leader",""))) | BA60: =IF(BW60="","","Passes "&AY60&" of 5 buy-side scans"&IF(G60="Y","; RED FLAG: filter out using Red flag column","")) | BB60: None | BC60: N | BF60: =IF(R60*100000>=Settings!$B$5,"Y","N") | BG60: =IF(F60>Settings!$B$6,"Y","N") | BH60: -24.28 | BI60: -5.47 | BJ60: -7.03 | BK60: 5.84 | BL60: 5.83 | BM60: 15.31 | BN60: -4.21 | BO60: -3.96 | BP60: -3.5 | BQ60: -1.66 | BR60: Mixed | BS60: None | BT60: 33.5 | BU60: N | BV60: =IF(OR(BF60<>"Y",BG60<>"Y"),"",(AND(ISNUMBER(BQ60),BQ60>0))+(BR60="Stacked up")+(AND(ISNUMBER(BH60),BH60>=-Settings!$B$17))+(AND(ISNUMBER(BK60),ISNUMBER(BM60),BK60>0,BM60>0))+(AND(ISNUMBER(AQ60),AQ60>=Settings!$B$18))+(AND(ISNUMBER(BT60),BT60>=Settings!$B$19,BT60<=Settings!$B$20))+(AND(ISNUMBER(AS60),AS60>0))+(AND(ISNUMBER(T60),ISNUMBER(M60),T60>=Settings!$B$21,M60>0))+(AND(ISNUMBER(AD60),ISNUMBER(M60),AD60>=Settings!$B$22,M60>0))+(AY60>=1)) | BW60: =IF(OR(AY60=0,BF60<>"Y",BG60<>"Y"),"",1+SUMPRODUCT(($A$6:$A$2604=A60)*($AY$6:$AY$2604>0)*($BF$6:$BF$2604="Y")*($BG$6:$BG$2604="Y")*(($AY$6:$AY$2604>AY60)+($AY$6:$AY$2604=AY60)*($AD$6:$AD$2604>AD60))))
A61: 46296 | B61: ADANIGREEN | C61: INE364U01010 | D61: Power | E61: Nifty Next 50 | F61: 210196 | G61: N | I61: N | J61: =IF(K61="","N","Y") | K61: =_xlfn.TEXTJOIN("; ",TRUE,IF(P61="52-wk low","52-wk low",""),IF(AND(AD61>=Settings!$B$12,M61<0),"Distribution",""),IF(AND(AJ61="Y",M61<0,AK61<-Settings!$B$13),"Long unwinding",""),IF(AND(AJ61="Y",M61<0,AK61>Settings!$B$13),"Short buildup","")) | L61: 1276.1 | M61: -0.15 | N61: 660 | O61: None | P61: None | Q61: 63.55 | R61: 14.58 | S61: 5 | T61: 3.67 | U61: 2.43 | V61: 0.55 | W61: 1 | X61: 36 | Y61: By value | Z61: 66.77 | AA61: 1.76 | AB61: 1.86 | AC61: 8.58 | AD61: 6.89 | AE61: 5.36 | AF61: 1.48 | AG61: Normal | AH61: 0 | AI61: 0 | AJ61: Y | AK61: -5.24 | AL61: Long unwinding | AM61: 32 | AN61: 200 Mom 30 | AO61: 1 | AP61: 1.62 | AQ61: 82 | AR61: Y | AS61: 3.38 | AT61: =IF(AND(P61="52-wk high",T61>=Settings!$B$7),"Y","N") | AU61: =IF(AND(AD61>=Settings!$B$8,M61>0),"Y","N") | AV61: =IF(OR(AH61>Settings!$B$9,AI61>Settings!$B$9),"Y","N") | AW61: =IF(AJ61<>"Y","n/a",IF(AND(M61>0,AK61>Settings!$B$10),"Y","N")) | AX61: =IF(AO61>=Settings!$B$11,"Y","N") | AY61: =(AT61="Y")+(AU61="Y")+(AV61="Y")+(AW61="Y")+(AX61="Y") | AZ61: =IF(AY61=0,"None",_xlfn.TEXTJOIN(", ",TRUE(),IF(AT61="Y","Breakout",""),IF(AU61="Y","Accumulation",""),IF(AV61="Y","Institutional buying",""),IF(AW61="Y","Long buildup",""),IF(AX61="Y","Momentum leader",""))) | BA61: =IF(BW61="","","Passes "&AY61&" of 5 buy-side scans"&IF(G61="Y","; RED FLAG: filter out using Red flag column","")) | BB61: None | BC61: Y | BD61: PE > 50; High-low range >100% in 6 months | BF61: =IF(R61*100000>=Settings!$B$5,"Y","N") | BG61: =IF(F61>Settings!$B$6,"Y","N") | BH61: -21.78 | BI61: -0.31 | BJ61: 0.88 | BK61: -16.87 | BL61: 49.79 | BM61: 19.86 | BN61: -0.88 | BO61: -3.37 | BP61: -3.03 | BQ61: 1.8 | BR61: Mixed | BS61: None | BT61: 47.5 | BU61: N | BV61: =IF(OR(BF61<>"Y",BG61<>"Y"),"",(AND(ISNUMBER(BQ61),BQ61>0))+(BR61="Stacked up")+(AND(ISNUMBER(BH61),BH61>=-Settings!$B$17))+(AND(ISNUMBER(BK61),ISNUMBER(BM61),BK61>0,BM61>0))+(AND(ISNUMBER(AQ61),AQ61>=Settings!$B$18))+(AND(ISNUMBER(BT61),BT61>=Settings!$B$19,BT61<=Settings!$B$20))+(AND(ISNUMBER(AS61),AS61>0))+(AND(ISNUMBER(T61),ISNUMBER(M61),T61>=Settings!$B$21,M61>0))+(AND(ISNUMBER(AD61),ISNUMBER(M61),AD61>=Settings!$B$22,M61>0))+(AY61>=1)) | BW61: =IF(OR(AY61=0,BF61<>"Y",BG61<>"Y"),"",1+SUMPRODUCT(($A$6:$A$2604=A61)*($AY$6:$AY$2604>0)*($BF$6:$BF$2604="Y")*($BG$6:$BG$2604="Y")*(($AY$6:$AY$2604>AY61)+($AY$6:$AY$2604=AY61)*($AD$6:$AD$2604>AD61))))
A62: 46296 | B62: TVSMOTOR | C62: INE494B01023 | D62: Automobile and Auto Components | E62: Nifty Next 50 | F62: 191033 | G62: N | I62: N | J62: =IF(K62="","N","Y") | K62: =_xlfn.TEXTJOIN("; ",TRUE,IF(P62="52-wk low","52-wk low",""),IF(AND(AD62>=Settings!$B$12,M62<0),"Distribution",""),IF(AND(AJ62="Y",M62<0,AK62<-Settings!$B$13),"Long unwinding",""),IF(AND(AJ62="Y",M62<0,AK62>Settings!$B$13),"Short buildup","")) | L62: 4021 | M62: -2.07 | N62: 1685 | O62: None | P62: None | Q62: 12.35 | R62: 6.78 | S62: 1.77 | T62: 1.18 | U62: 1.11 | V62: 0.61 | W62: 2 | X62: 223 | Y62: None | Z62: 48.98 | AA62: 0.84 | AB62: 0.83 | AC62: 1.47 | AD62: 1 | AE62: 0.95 | AF62: 1.03 | AG62: Normal | AH62: 0 | AI62: 0 | AJ62: Y | AK62: -0.83 | AL62: Long unwinding | AM62: 11 | AN62: None | AO62: 0 | AP62: 1.38 | AQ62: 76 | AR62: Y | AS62: 0.56 | AT62: =IF(AND(P62="52-wk high",T62>=Settings!$B$7),"Y","N") | AU62: =IF(AND(AD62>=Settings!$B$8,M62>0),"Y","N") | AV62: =IF(OR(AH62>Settings!$B$9,AI62>Settings!$B$9),"Y","N") | AW62: =IF(AJ62<>"Y","n/a",IF(AND(M62>0,AK62>Settings!$B$10),"Y","N")) | AX62: =IF(AO62>=Settings!$B$11,"Y","N") | AY62: =(AT62="Y")+(AU62="Y")+(AV62="Y")+(AW62="Y")+(AX62="Y") | AZ62: =IF(AY62=0,"None",_xlfn.TEXTJOIN(", ",TRUE(),IF(AT62="Y","Breakout",""),IF(AU62="Y","Accumulation",""),IF(AV62="Y","Institutional buying",""),IF(AW62="Y","Long buildup",""),IF(AX62="Y","Momentum leader",""))) | BA62: =IF(BW62="","","Passes "&AY62&" of 5 buy-side scans"&IF(G62="Y","; RED FLAG: filter out using Red flag column","")) | BB62: None | BC62: Y | BD62: PE > 50 | BF62: =IF(R62*100000>=Settings!$B$5,"Y","N") | BG62: =IF(F62>Settings!$B$6,"Y","N") | BH62: -10.34 | BI62: -1.71 | BJ62: -4.33 | BK62: 15.08 | BL62: 17.37 | BM62: 16.29 | BN62: -2.69 | BO62: -1.97 | BP62: 1.35 | BQ62: 5.39 | BR62: Mixed | BS62: None | BT62: 33.8 | BU62: N | BV62: =IF(OR(BF62<>"Y",BG62<>"Y"),"",(AND(ISNUMBER(BQ62),BQ62>0))+(BR62="Stacked up")+(AND(ISNUMBER(BH62),BH62>=-Settings!$B$17))+(AND(ISNUMBER(BK62),ISNUMBER(BM62),BK62>0,BM62>0))+(AND(ISNUMBER(AQ62),AQ62>=Settings!$B$18))+(AND(ISNUMBER(BT62),BT62>=Settings!$B$19,BT62<=Settings!$B$20))+(AND(ISNUMBER(AS62),AS62>0))+(AND(ISNUMBER(T62),ISNUMBER(M62),T62>=Settings!$B$21,M62>0))+(AND(ISNUMBER(AD62),ISNUMBER(M62),AD62>=Settings!$B$22,M62>0))+(AY62>=1)) | BW62: =IF(OR(AY62=0,BF62<>"Y",BG62<>"Y"),"",1+SUMPRODUCT(($A$6:$A$2604=A62)*($AY$6:$AY$2604>0)*($BF$6:$BF$2604="Y")*($BG$6:$BG$2604="Y")*(($AY$6:$AY$2604>AY62)+($AY$6:$AY$2604=AY62)*($AD$6:$AD$2604>AD62))))
A63: 46296 | B63: IOC | C63: INE242A01010 | D63: Oil Gas & Consumable Fuels | E63: Nifty Next 50 | F63: 185468 | G63: N | I63: N | J63: =IF(K63="","N","Y") | K63: =_xlfn.TEXTJOIN("; ",TRUE,IF(P63="52-wk low","52-wk low",""),IF(AND(AD63>=Settings!$B$12,M63<0),"Distribution",""),IF(AND(AJ63="Y",M63<0,AK63<-Settings!$B$13),"Long unwinding",""),IF(AND(AJ63="Y",M63<0,AK63>Settings!$B$13),"Short buildup","")) | L63: 131.34 | M63: -2.66 | N63: 1965 | O63: None | P63: None | Q63: 122.4 | R63: 79.09 | S63: 1.59 | T63: 1.49 | U63: 1.03 | V63: 0.66 | W63: 1 | X63: 217 | Y63: None | Z63: 51.62 | AA63: 0.92 | AB63: 0.94 | AC63: 1.46 | AD63: 1.4 | AE63: 1.01 | AF63: 1.06 | AG63: Normal | AH63: 0 | AI63: 0 | AJ63: Y | AK63: 1.15 | AL63: Short buildup | AM63: 167 | AN63: None | AO63: 0 | AP63: 0.67 | AQ63: 33 | AR63: Y | AS63: 2.69 | AT63: =IF(AND(P63="52-wk high",T63>=Settings!$B$7),"Y","N") | AU63: =IF(AND(AD63>=Settings!$B$8,M63>0),"Y","N") | AV63: =IF(OR(AH63>Settings!$B$9,AI63>Settings!$B$9),"Y","N") | AW63: =IF(AJ63<>"Y","n/a",IF(AND(M63>0,AK63>Settings!$B$10),"Y","N")) | AX63: =IF(AO63>=Settings!$B$11,"Y","N") | AY63: =(AT63="Y")+(AU63="Y")+(AV63="Y")+(AW63="Y")+(AX63="Y") | AZ63: =IF(AY63=0,"None",_xlfn.TEXTJOIN(", ",TRUE(),IF(AT63="Y","Breakout",""),IF(AU63="Y","Accumulation",""),IF(AV63="Y","Institutional buying",""),IF(AW63="Y","Long buildup",""),IF(AX63="Y","Momentum leader",""))) | BA63: =IF(BW63="","","Passes "&AY63&" of 5 buy-side scans"&IF(G63="Y","; RED FLAG: filter out using Red flag column","")) | BB63: None | BC63: N | BF63: =IF(R63*100000>=Settings!$B$5,"Y","N") | BG63: =IF(F63>Settings!$B$6,"Y","N") | BH63: -30.49 | BI63: -3.62 | BJ63: -3.8 | BK63: -6.07 | BL63: -3.23 | BM63: -12.26 | BN63: -2.89 | BO63: -4.31 | BP63: -6.33 | BQ63: -9.12 | BR63: Stacked down | BS63: None | BT63: 37.9 | BU63: N | BV63: =IF(OR(BF63<>"Y",BG63<>"Y"),"",(AND(ISNUMBER(BQ63),BQ63>0))+(BR63="Stacked up")+(AND(ISNUMBER(BH63),BH63>=-Settings!$B$17))+(AND(ISNUMBER(BK63),ISNUMBER(BM63),BK63>0,BM63>0))+(AND(ISNUMBER(AQ63),AQ63>=Settings!$B$18))+(AND(ISNUMBER(BT63),BT63>=Settings!$B$19,BT63<=Settings!$B$20))+(AND(ISNUMBER(AS63),AS63>0))+(AND(ISNUMBER(T63),ISNUMBER(M63),T63>=Settings!$B$21,M63>0))+(AND(ISNUMBER(AD63),ISNUMBER(M63),AD63>=Settings!$B$22,M63>0))+(AY63>=1)) | BW63: =IF(OR(AY63=0,BF63<>"Y",BG63<>"Y"),"",1+SUMPRODUCT(($A$6:$A$2604=A63)*($AY$6:$AY$2604>0)*($BF$6:$BF$2604="Y")*($BG$6:$BG$2604="Y")*(($AY$6:$AY$2604>AY63)+($AY$6:$AY$2604=AY63)*($AD$6:$AD$2604>AD63))))
A64: 46296 | B64: TORNTPHARM | C64: INE685A01028 | D64: Healthcare | E64: Nifty Next 50 | F64: 181333 | G64: N | I64: N | J64: =IF(K64="","N","Y") | K64: =_xlfn.TEXTJOIN("; ",TRUE,IF(P64="52-wk low","52-wk low",""),IF(AND(AD64>=Settings!$B$12,M64<0),"Distribution",""),IF(AND(AJ64="Y",M64<0,AK64<-Settings!$B$13),"Long unwinding",""),IF(AND(AJ64="Y",M64<0,AK64>Settings!$B$13),"Short buildup","")) | L64: 4767.3 | M64: -0.68 | N64: 872 | O64: None | P64: None | Q64: 3.58 | R64: 3.57 | S64: 1.01 | T64: 0.88 | U64: 0.67 | V64: 0.67 | W64: 2 | Y64: None | Z64: 57.18 | AA64: 0.92 | AB64: 0.93 | AC64: 0.93 | AD64: 0.81 | AE64: 0.65 | AF64: 1.05 | AG64: Normal | AH64: 0 | AI64: 0 | AJ64: Y | AK64: 0.27 | AL64: Short buildup | AM64: 184 | AN64: 200 Mom 30; 500 Mom 50; TotalMkt MQ 50 | AO64: 3 | AP64: 1.84 | AQ64: 87 | AR64: Y | AS64: 3.79 | AT64: =IF(AND(P64="52-wk high",T64>=Settings!$B$7),"Y","N") | AU64: =IF(AND(AD64>=Settings!$B$8,M64>0),"Y","N") | AV64: =IF(OR(AH64>Settings!$B$9,AI64>Settings!$B$9),"Y","N") | AW64: =IF(AJ64<>"Y","n/a",IF(AND(M64>0,AK64>Settings!$B$10),"Y","N")) | AX64: =IF(AO64>=Settings!$B$11,"Y","N") | AY64: =(AT64="Y")+(AU64="Y")+(AV64="Y")+(AW64="Y")+(AX64="Y") | AZ64: =IF(AY64=0,"None",_xlfn.TEXTJOIN(", ",TRUE(),IF(AT64="Y","Breakout",""),IF(AU64="Y","Accumulation",""),IF(AV64="Y","Institutional buying",""),IF(AW64="Y","Long buildup",""),IF(AX64="Y","Momentum leader",""))) | BA64: =IF(BW64="","","Passes "&AY64&" of 5 buy-side scans"&IF(G64="Y","; RED FLAG: filter out using Red flag column","")) | BB64: None | BC64: Y | BD64: PE > 50 | BF64: =IF(R64*100000>=Settings!$B$5,"Y","N") | BG64: =IF(F64>Settings!$B$6,"Y","N") | BH64: -9.19 | BI64: -3.27 | BJ64: -3.99 | BK64: 2.73 | BL64: 15.96 | BM64: 33.65 | BN64: -2.65 | BO64: -2.34 | BP64: 0.32 | BQ64: 5.95 | BR64: Mixed | BS64: None | BT64: 37 | BU64: N | BV64: =IF(OR(BF64<>"Y",BG64<>"Y"),"",(AND(ISNUMBER(BQ64),BQ64>0))+(BR64="Stacked up")+(AND(ISNUMBER(BH64),BH64>=-Settings!$B$17))+(AND(ISNUMBER(BK64),ISNUMBER(BM64),BK64>0,BM64>0))+(AND(ISNUMBER(AQ64),AQ64>=Settings!$B$18))+(AND(ISNUMBER(BT64),BT64>=Settings!$B$19,BT64<=Settings!$B$20))+(AND(ISNUMBER(AS64),AS64>0))+(AND(ISNUMBER(T64),ISNUMBER(M64),T64>=Settings!$B$21,M64>0))+(AND(ISNUMBER(AD64),ISNUMBER(M64),AD64>=Settings!$B$22,M64>0))+(AY64>=1)) | BW64: =IF(OR(AY64=0,BF64<>"Y",BG64<>"Y"),"",1+SUMPRODUCT(($A$6:$A$2604=A64)*($AY$6:$AY$2604>0)*($BF$6:$BF$2604="Y")*($BG$6:$BG$2604="Y")*(($AY$6:$AY$2604>AY64)+($AY$6:$AY$2604=AY64)*($AD$6:$AD$2604>AD64))))
A65: 46296 | B65: SOLARINDS | C65: INE343H01029 | D65: Chemicals | E65: Nifty Next 50 | F65: 175551 | G65: N | I65: N | J65: =IF(K65="","N","Y") | K65: =_xlfn.TEXTJOIN("; ",TRUE,IF(P65="52-wk low","52-wk low",""),IF(AND(AD65>=Settings!$B$12,M65<0),"Distribution",""),IF(AND(AJ65="Y",M65<0,AK65<-Settings!$B$13),"Long unwinding",""),IF(AND(AJ65="Y",M65<0,AK65>Settings!$B$13),"Short buildup","")) | L65: 19400 | M65: -1.52 | N65: 1342 | O65: None | P65: None | Q65: 2.05 | R65: 2.83 | S65: 0.73 | T65: 1.09 | U65: 1.11 | V65: 1.54 | W65: 8 | Y65: None | Z65: 35.8 | AA65: 0.91 | AB65: 0.95 | AC65: 0.71 | AD65: 1.12 | AE65: 1.08 | AF65: 0.99 | AG65: Normal | AH65: 0 | AI65: 0 | AJ65: Y | AK65: 0.15 | AL65: Short buildup | AM65: 64 | AN65: 200 Mom 30; 500 Multicap MQ 50; TotalMkt MQ 50 | AO65: 3 | AP65: 2.09 | AQ65: 90 | AR65: Y | AS65: 1.93 | AT65: =IF(AND(P65="52-wk high",T65>=Settings!$B$7),"Y","N") | AU65: =IF(AND(AD65>=Settings!$B$8,M65>0),"Y","N") | AV65: =IF(OR(AH65>Settings!$B$9,AI65>Settings!$B$9),"Y","N") | AW65: =IF(AJ65<>"Y","n/a",IF(AND(M65>0,AK65>Settings!$B$10),"Y","N")) | AX65: =IF(AO65>=Settings!$B$11,"Y","N") | AY65: =(AT65="Y")+(AU65="Y")+(AV65="Y")+(AW65="Y")+(AX65="Y") | AZ65: =IF(AY65=0,"None",_xlfn.TEXTJOIN(", ",TRUE(),IF(AT65="Y","Breakout",""),IF(AU65="Y","Accumulation",""),IF(AV65="Y","Institutional buying",""),IF(AW65="Y","Long buildup",""),IF(AX65="Y","Momentum leader",""))) | BA65: =IF(BW65="","","Passes "&AY65&" of 5 buy-side scans"&IF(G65="Y","; RED FLAG: filter out using Red flag column","")) | BB65: Lower | BC65: Y | BD65: PE > 50 | BF65: =IF(R65*100000>=Settings!$B$5,"Y","N") | BG65: =IF(F65>Settings!$B$6,"Y","N") | BH65: -14.54 | BI65: -0.41 | BJ65: -3.29 | BK65: 4.25 | BL65: 51.48 | BM65: 45.06 | BN65: -1.84 | BO65: -0.83 | BP65: 4.15 | BQ65: 12.95 | BR65: Mixed | BS65: None | BT65: 46 | BU65: N | BV65: =IF(OR(BF65<>"Y",BG65<>"Y"),"",(AND(ISNUMBER(BQ65),BQ65>0))+(BR65="Stacked up")+(AND(ISNUMBER(BH65),BH65>=-Settings!$B$17))+(AND(ISNUMBER(BK65),ISNUMBER(BM65),BK65>0,BM65>0))+(AND(ISNUMBER(AQ65),AQ65>=Settings!$B$18))+(AND(ISNUMBER(BT65),BT65>=Settings!$B$19,BT65<=Settings!$B$20))+(AND(ISNUMBER(AS65),AS65>0))+(AND(ISNUMBER(T65),ISNUMBER(M65),T65>=Settings!$B$21,M65>0))+(AND(ISNUMBER(AD65),ISNUMBER(M65),AD65>=Settings!$B$22,M65>0))+(AY65>=1)) | BW65: =IF(OR(AY65=0,BF65<>"Y",BG65<>"Y"),"",1+SUMPRODUCT(($A$6:$A$2604=A65)*($AY$6:$AY$2604>0)*($BF$6:$BF$2604="Y")*($BG$6:$BG$2604="Y")*(($AY$6:$AY$2604>AY65)+($AY$6:$AY$2604=AY65)*($AD$6:$AD$2604>AD65))))
A66: 46296 | B66: MOTHERSON | C66: INE775A01035 | D66: Automobile and Auto Components | E66: Nifty Next 50 | F66: 165736 | G66: N | I66: N | J66: =IF(K66="","N","Y") | K66: =_xlfn.TEXTJOIN("; ",TRUE,IF(P66="52-wk low","52-wk low",""),IF(AND(AD66>=Settings!$B$12,M66<0),"Distribution",""),IF(AND(AJ66="Y",M66<0,AK66<-Settings!$B$13),"Long unwinding",""),IF(AND(AJ66="Y",M66<0,AK66>Settings!$B$13),"Short buildup","")) | L66: 157.03 | M66: -3.82 | N66: 2305 | O66: None | P66: None | Q66: 230.39 | R66: 118.28 | S66: 1.98 | T66: 1.46 | U66: 1.17 | V66: 0.6 | W66: 2 | X66: 181 | Y66: None | Z66: 45.97 | AA66: 0.83 | AB66: 0.89 | AC66: 1.61 | AD66: 1.42 | AE66: 1.14 | AF66: 1.19 | AG66: Normal | AH66: 0 | AI66: 0 | AJ66: Y | AK66: 1.41 | AL66: Short buildup | AM66: 49 | AN66: 200 Mom 30 | AO66: 1 | AP66: 2.13 | AQ66: 91 | AR66: Y | AS66: 0.56 | AT66: =IF(AND(P66="52-wk high",T66>=Settings!$B$7),"Y","N") | AU66: =IF(AND(AD66>=Settings!$B$8,M66>0),"Y","N") | AV66: =IF(OR(AH66>Settings!$B$9,AI66>Settings!$B$9),"Y","N") | AW66: =IF(AJ66<>"Y","n/a",IF(AND(M66>0,AK66>Settings!$B$10),"Y","N")) | AX66: =IF(AO66>=Settings!$B$11,"Y","N") | AY66: =(AT66="Y")+(AU66="Y")+(AV66="Y")+(AW66="Y")+(AX66="Y") | AZ66: =IF(AY66=0,"None",_xlfn.TEXTJOIN(", ",TRUE(),IF(AT66="Y","Breakout",""),IF(AU66="Y","Accumulation",""),IF(AV66="Y","Institutional buying",""),IF(AW66="Y","Long buildup",""),IF(AX66="Y","Momentum leader",""))) | BA66: =IF(BW66="","","Passes "&AY66&" of 5 buy-side scans"&IF(G66="Y","; RED FLAG: filter out using Red flag column","")) | BB66: Upper | BC66: N | BF66: =IF(R66*100000>=Settings!$B$5,"Y","N") | BG66: =IF(F66>Settings!$B$6,"Y","N") | BH66: -9.37 | BI66: -3.37 | BJ66: -5.18 | BK66: 6.45 | BL66: 45.91 | BM66: 48.14 | BN66: -3.11 | BO66: -1.54 | BP66: 3.4 | BQ66: 11.86 | BR66: Mixed | BS66: None | BT66: 39.6 | BU66: N | BV66: =IF(OR(BF66<>"Y",BG66<>"Y"),"",(AND(ISNUMBER(BQ66),BQ66>0))+(BR66="Stacked up")+(AND(ISNUMBER(BH66),BH66>=-Settings!$B$17))+(AND(ISNUMBER(BK66),ISNUMBER(BM66),BK66>0,BM66>0))+(AND(ISNUMBER(AQ66),AQ66>=Settings!$B$18))+(AND(ISNUMBER(BT66),BT66>=Settings!$B$19,BT66<=Settings!$B$20))+(AND(ISNUMBER(AS66),AS66>0))+(AND(ISNUMBER(T66),ISNUMBER(M66),T66>=Settings!$B$21,M66>0))+(AND(ISNUMBER(AD66),ISNUMBER(M66),AD66>=Settings!$B$22,M66>0))+(AY66>=1)) | BW66: =IF(OR(AY66=0,BF66<>"Y",BG66<>"Y"),"",1+SUMPRODUCT(($A$6:$A$2604=A66)*($AY$6:$AY$2604>0)*($BF$6:$BF$2604="Y")*($BG$6:$BG$2604="Y")*(($AY$6:$AY$2604>AY66)+($AY$6:$AY$2604=AY66)*($AD$6:$AD$2604>AD66))))
A67: 46296 | B67: HYUNDAI | C67: INE0V6F01027 | D67: Automobile and Auto Components | E67: Nifty Next 50 | F67: 164458 | G67: N | I67: N | J67: =IF(K67="","N","Y") | K67: =_xlfn.TEXTJOIN("; ",TRUE,IF(P67="52-wk low","52-wk low",""),IF(AND(AD67>=Settings!$B$12,M67<0),"Distribution",""),IF(AND(AJ67="Y",M67<0,AK67<-Settings!$B$13),"Long unwinding",""),IF(AND(AJ67="Y",M67<0,AK67>Settings!$B$13),"Short buildup","")) | L67: 2024 | M67: -0.34 | N67: 729 | O67: None | P67: None | Q67: 17.96 | R67: 6.9 | S67: 2.76 | T67: 2.37 | U67: 1.67 | V67: 0.65 | W67: 2 | X67: 85 | Y67: None | Z67: 52.25 | AA67: 1.04 | AB67: 1.04 | AC67: 2.93 | AD67: 2.66 | AE67: 1.71 | AF67: 0.97 | AG67: Normal | AH67: 0 | AI67: 0 | AJ67: Y | AK67: 11.8 | AL67: Short buildup | AM67: 57 | AN67: None | AO67: 0 | AP67: 0.83 | AQ67: 52 | AR67: N | AS67: 0.56 | AT67: =IF(AND(P67="52-wk high",T67>=Settings!$B$7),"Y","N") | AU67: =IF(AND(AD67>=Settings!$B$8,M67>0),"Y","N") | AV67: =IF(OR(AH67>Settings!$B$9,AI67>Settings!$B$9),"Y","N") | AW67: =IF(AJ67<>"Y","n/a",IF(AND(M67>0,AK67>Settings!$B$10),"Y","N")) | AX67: =IF(AO67>=Settings!$B$11,"Y","N") | AY67: =(AT67="Y")+(AU67="Y")+(AV67="Y")+(AW67="Y")+(AX67="Y") | AZ67: =IF(AY67=0,"None",_xlfn.TEXTJOIN(", ",TRUE(),IF(AT67="Y","Breakout",""),IF(AU67="Y","Accumulation",""),IF(AV67="Y","Institutional buying",""),IF(AW67="Y","Long buildup",""),IF(AX67="Y","Momentum leader",""))) | BA67: =IF(BW67="","","Passes "&AY67&" of 5 buy-side scans"&IF(G67="Y","; RED FLAG: filter out using Red flag column","")) | BB67: None | BC67: N | BF67: =IF(R67*100000>=Settings!$B$5,"Y","N") | BG67: =IF(F67>Settings!$B$6,"Y","N") | BH67: -24.69 | BI67: -1.78 | BJ67: -7.15 | BK67: 5.51 | BL67: 17.93 | BM67: -20.23 | BN67: -4.43 | BO67: -4.5 | BP67: -3.14 | BQ67: -5.2 | BR67: Mixed | BS67: Bearish cross | BT67: 35.2 | BU67: N | BV67: =IF(OR(BF67<>"Y",BG67<>"Y"),"",(AND(ISNUMBER(BQ67),BQ67>0))+(BR67="Stacked up")+(AND(ISNUMBER(BH67),BH67>=-Settings!$B$17))+(AND(ISNUMBER(BK67),ISNUMBER(BM67),BK67>0,BM67>0))+(AND(ISNUMBER(AQ67),AQ67>=Settings!$B$18))+(AND(ISNUMBER(BT67),BT67>=Settings!$B$19,BT67<=Settings!$B$20))+(AND(ISNUMBER(AS67),AS67>0))+(AND(ISNUMBER(T67),ISNUMBER(M67),T67>=Settings!$B$21,M67>0))+(AND(ISNUMBER(AD67),ISNUMBER(M67),AD67>=Settings!$B$22,M67>0))+(AY67>=1)) | BW67: =IF(OR(AY67=0,BF67<>"Y",BG67<>"Y"),"",1+SUMPRODUCT(($A$6:$A$2604=A67)*($AY$6:$AY$2604>0)*($BF$6:$BF$2604="Y")*($BG$6:$BG$2604="Y")*(($AY$6:$AY$2604>AY67)+($AY$6:$AY$2604=AY67)*($AD$6:$AD$2604>AD67))))
A68: 46296 | B68: DLF | C68: INE271C01023 | D68: Realty | E68: Nifty Next 50 | F68: 162975 | G68: N | I68: N | J68: =IF(K68="","N","Y") | K68: =_xlfn.TEXTJOIN("; ",TRUE,IF(P68="52-wk low","52-wk low",""),IF(AND(AD68>=Settings!$B$12,M68<0),"Distribution",""),IF(AND(AJ68="Y",M68<0,AK68<-Settings!$B$13),"Long unwinding",""),IF(AND(AJ68="Y",M68<0,AK68>Settings!$B$13),"Short buildup","")) | L68: 658.4 | M68: -2.31 | N68: 1793 | O68: None | P68: None | Q68: 62.64 | R68: 41.63 | S68: 1.55 | T68: 1.8 | U68: 1.54 | V68: 1.01 | W68: 7 | X68: 160 | Y68: None | Z68: 56.31 | AA68: 1.06 | AB68: 1.18 | AC68: 1.55 | AD68: 2 | AE68: 1.75 | AF68: 1.15 | AG68: Normal | AH68: 0 | AI68: 0 | AJ68: Y | AK68: 2.81 | AL68: Short buildup | AM68: 34 | AN68: None | AO68: 0 | AP68: 1.16 | AQ68: 68 | AR68: Y | AS68: 2.36 | AT68: =IF(AND(P68="52-wk high",T68>=Settings!$B$7),"Y","N") | AU68: =IF(AND(AD68>=Settings!$B$8,M68>0),"Y","N") | AV68: =IF(OR(AH68>Settings!$B$9,AI68>Settings!$B$9),"Y","N") | AW68: =IF(AJ68<>"Y","n/a",IF(AND(M68>0,AK68>Settings!$B$10),"Y","N")) | AX68: =IF(AO68>=Settings!$B$11,"Y","N") | AY68: =(AT68="Y")+(AU68="Y")+(AV68="Y")+(AW68="Y")+(AX68="Y") | AZ68: =IF(AY68=0,"None",_xlfn.TEXTJOIN(", ",TRUE(),IF(AT68="Y","Breakout",""),IF(AU68="Y","Accumulation",""),IF(AV68="Y","Institutional buying",""),IF(AW68="Y","Long buildup",""),IF(AX68="Y","Momentum leader",""))) | BA68: =IF(BW68="","","Passes "&AY68&" of 5 buy-side scans"&IF(G68="Y","; RED FLAG: filter out using Red flag column","")) | BB68: None | BC68: N | BF68: =IF(R68*100000>=Settings!$B$5,"Y","N") | BG68: =IF(F68>Settings!$B$6,"Y","N") | BH68: -16.29 | BI68: -1.79 | BJ68: -2.48 | BK68: 1.5 | BL68: 29.16 | BM68: -8.85 | BN68: -0.63 | BO68: -0.01 | BP68: 1.6 | BQ68: 1.33 | BR68: Mixed | BS68: None | BT68: 47.8 | BU68: N | BV68: =IF(OR(BF68<>"Y",BG68<>"Y"),"",(AND(ISNUMBER(BQ68),BQ68>0))+(BR68="Stacked up")+(AND(ISNUMBER(BH68),BH68>=-Settings!$B$17))+(AND(ISNUMBER(BK68),ISNUMBER(BM68),BK68>0,BM68>0))+(AND(ISNUMBER(AQ68),AQ68>=Settings!$B$18))+(AND(ISNUMBER(BT68),BT68>=Settings!$B$19,BT68<=Settings!$B$20))+(AND(ISNUMBER(AS68),AS68>0))+(AND(ISNUMBER(T68),ISNUMBER(M68),T68>=Settings!$B$21,M68>0))+(AND(ISNUMBER(AD68),ISNUMBER(M68),AD68>=Settings!$B$22,M68>0))+(AY68>=1)) | BW68: =IF(OR(AY68=0,BF68<>"Y",BG68<>"Y"),"",1+SUMPRODUCT(($A$6:$A$2604=A68)*($AY$6:$AY$2604>0)*($BF$6:$BF$2604="Y")*($BG$6:$BG$2604="Y")*(($AY$6:$AY$2604>AY68)+($AY$6:$AY$2604=AY68)*($AD$6:$AD$2604>AD68))))
A69: 46296 | B69: ADANIENSOL | C69: INE931S01010 | D69: Power | E69: Nifty Next 50 | F69: 162213 | G69: N | I69: N | J69: =IF(K69="","N","Y") | K69: =_xlfn.TEXTJOIN("; ",TRUE,IF(P69="52-wk low","52-wk low",""),IF(AND(AD69>=Settings!$B$12,M69<0),"Distribution",""),IF(AND(AJ69="Y",M69<0,AK69<-Settings!$B$13),"Long unwinding",""),IF(AND(AJ69="Y",M69<0,AK69>Settings!$B$13),"Short buildup","")) | L69: 1326.4 | M69: 0.9 | N69: 365 | O69: None | P69: None | Q69: 72.67 | R69: 17.92 | S69: 4.43 | T69: 2.56 | U69: 2.42 | V69: 0.59 | W69: 1 | X69: 40 | Y69: By value | Z69: 33.53 | AA69: 0.7 | AB69: 0.7 | AC69: 3.06 | AD69: 1.5 | AE69: 1.75 | AF69: 0.99 | AG69: Normal | AH69: 0 | AI69: 0 | AJ69: Y | AK69: 0.74 | AL69: Long buildup | AM69: 29 | AN69: 200 Mom 30; 500 Mom 50 | AO69: 2 | AP69: 1.84 | AQ69: 87 | AR69: Y | AS69: 3.38 | AT69: =IF(AND(P69="52-wk high",T69>=Settings!$B$7),"Y","N") | AU69: =IF(AND(AD69>=Settings!$B$8,M69>0),"Y","N") | AV69: =IF(OR(AH69>Settings!$B$9,AI69>Settings!$B$9),"Y","N") | AW69: =IF(AJ69<>"Y","n/a",IF(AND(M69>0,AK69>Settings!$B$10),"Y","N")) | AX69: =IF(AO69>=Settings!$B$11,"Y","N") | AY69: =(AT69="Y")+(AU69="Y")+(AV69="Y")+(AW69="Y")+(AX69="Y") | AZ69: =IF(AY69=0,"None",_xlfn.TEXTJOIN(", ",TRUE(),IF(AT69="Y","Breakout",""),IF(AU69="Y","Accumulation",""),IF(AV69="Y","Institutional buying",""),IF(AW69="Y","Long buildup",""),IF(AX69="Y","Momentum leader",""))) | BA69: =IF(BW69="","","Passes "&AY69&" of 5 buy-side scans"&IF(G69="Y","; RED FLAG: filter out using Red flag column","")) | BB69: Upper | BC69: Y | BD69: PE > 50 | BF69: =IF(R69*100000>=Settings!$B$5,"Y","N") | BG69: =IF(F69>Settings!$B$6,"Y","N") | BH69: -25.86 | BI69: -1.05 | BJ69: -4.02 | BK69: -12.82 | BL69: 38.66 | BM69: 47.98 | BN69: -3.74 | BO69: -8.57 | BP69: -7.82 | BQ69: -0.19 | BR69: Mixed | BS69: None | BT69: 38.9 | BU69: N | BV69: =IF(OR(BF69<>"Y",BG69<>"Y"),"",(AND(ISNUMBER(BQ69),BQ69>0))+(BR69="Stacked up")+(AND(ISNUMBER(BH69),BH69>=-Settings!$B$17))+(AND(ISNUMBER(BK69),ISNUMBER(BM69),BK69>0,BM69>0))+(AND(ISNUMBER(AQ69),AQ69>=Settings!$B$18))+(AND(ISNUMBER(BT69),BT69>=Settings!$B$19,BT69<=Settings!$B$20))+(AND(ISNUMBER(AS69),AS69>0))+(AND(ISNUMBER(T69),ISNUMBER(M69),T69>=Settings!$B$21,M69>0))+(AND(ISNUMBER(AD69),ISNUMBER(M69),AD69>=Settings!$B$22,M69>0))+(AY69>=1)) | BW69: =IF(OR(AY69=0,BF69<>"Y",BG69<>"Y"),"",1+SUMPRODUCT(($A$6:$A$2604=A69)*($AY$6:$AY$2604>0)*($BF$6:$BF$2604="Y")*($BG$6:$BG$2604="Y")*(($AY$6:$AY$2604>AY69)+($AY$6:$AY$2604=AY69)*($AD$6:$AD$2604>AD69))))
A70: 46296 | B70: WIPRO | C70: INE075A01022 | D70: Information Technology | E70: Nifty Next 50 | F70: 157840 | G70: N | I70: N | J70: =IF(K70="","N","Y") | K70: =_xlfn.TEXTJOIN("; ",TRUE,IF(P70="52-wk low","52-wk low",""),IF(AND(AD70>=Settings!$B$12,M70<0),"Distribution",""),IF(AND(AJ70="Y",M70<0,AK70<-Settings!$B$13),"Long unwinding",""),IF(AND(AJ70="Y",M70<0,AK70>Settings!$B$13),"Short buildup","")) | L70: 159.35 | M70: 0.54 | N70: 438 | O70: None | P70: None | Q70: 185.22 | R70: 188.73 | S70: 1 | T70: 1.28 | U70: 0.89 | V70: 0.91 | W70: 2 | Y70: None | Z70: 58.02 | AA70: 1.19 | AB70: 1.21 | AC70: 0.89 | AD70: 1.31 | AE70: 1.02 | AF70: 1.29 | AG70: Normal | AH70: 0 | AI70: 0 | AJ70: Y | AK70: -3.38 | AL70: Short covering | AM70: 67 | AN70: None | AO70: 0 | AP70: 0.46 | AQ70: 2 | AR70: Y | AS70: -0.75 | AT70: =IF(AND(P70="52-wk high",T70>=Settings!$B$7),"Y","N") | AU70: =IF(AND(AD70>=Settings!$B$8,M70>0),"Y","N") | AV70: =IF(OR(AH70>Settings!$B$9,AI70>Settings!$B$9),"Y","N") | AW70: =IF(AJ70<>"Y","n/a",IF(AND(M70>0,AK70>Settings!$B$10),"Y","N")) | AX70: =IF(AO70>=Settings!$B$11,"Y","N") | AY70: =(AT70="Y")+(AU70="Y")+(AV70="Y")+(AW70="Y")+(AX70="Y") | AZ70: =IF(AY70=0,"None",_xlfn.TEXTJOIN(", ",TRUE(),IF(AT70="Y","Breakout",""),IF(AU70="Y","Accumulation",""),IF(AV70="Y","Institutional buying",""),IF(AW70="Y","Long buildup",""),IF(AX70="Y","Momentum leader",""))) | BA70: =IF(BW70="","","Passes "&AY70&" of 5 buy-side scans"&IF(G70="Y","; RED FLAG: filter out using Red flag column","")) | BB70: None | BC70: N | BF70: =IF(R70*100000>=Settings!$B$5,"Y","N") | BG70: =IF(F70>Settings!$B$6,"Y","N") | BH70: -41.65 | BI70: -2.62 | BJ70: -12.3 | BK70: -6.34 | BL70: -16.65 | BM70: -33.9 | BN70: -4.06 | BO70: -7.83 | BP70: -12.09 | BQ70: -18.72 | BR70: Stacked down | BS70: None | BT70: 30.9 | BU70: N | BV70: =IF(OR(BF70<>"Y",BG70<>"Y"),"",(AND(ISNUMBER(BQ70),BQ70>0))+(BR70="Stacked up")+(AND(ISNUMBER(BH70),BH70>=-Settings!$B$17))+(AND(ISNUMBER(BK70),ISNUMBER(BM70),BK70>0,BM70>0))+(AND(ISNUMBER(AQ70),AQ70>=Settings!$B$18))+(AND(ISNUMBER(BT70),BT70>=Settings!$B$19,BT70<=Settings!$B$20))+(AND(ISNUMBER(AS70),AS70>0))+(AND(ISNUMBER(T70),ISNUMBER(M70),T70>=Settings!$B$21,M70>0))+(AND(ISNUMBER(AD70),ISNUMBER(M70),AD70>=Settings!$B$22,M70>0))+(AY70>=1)) | BW70: =IF(OR(AY70=0,BF70<>"Y",BG70<>"Y"),"",1+SUMPRODUCT(($A$6:$A$2604=A70)*($AY$6:$AY$2604>0)*($BF$6:$BF$2604="Y")*($BG$6:$BG$2604="Y")*(($AY$6:$AY$2604>AY70)+($AY$6:$AY$2604=AY70)*($AD$6:$AD$2604>AD70))))
A71: 46296 | B71: VAML | C71: INE1CDF01017 | D71: Metals & Mining | E71: Nifty Next 50 | F71: 157491 | G71: Y | H71: Promoter pledge / encumbrance > 50% | I71: N | J71: =IF(K71="","N","Y") | K71: =_xlfn.TEXTJOIN("; ",TRUE,IF(P71="52-wk low","52-wk low",""),IF(AND(AD71>=Settings!$B$12,M71<0),"Distribution",""),IF(AND(AJ71="Y",M71<0,AK71<-Settings!$B$13),"Long unwinding",""),IF(AND(AJ71="Y",M71<0,AK71>Settings!$B$13),"Short buildup","")) | L71: 402.75 | M71: -2.46 | N71: 1872 | O71: None | P71: 52-wk low | Q71: 69.86 | R71: 95.35 | S71: 0.74 | T71: 0.78 | Y71: None | Z71: 48.3 | AA71: 0.79 | AB71: 0.8 | AC71: 0.56 | AD71: 0.62 | AH71: 0 | AI71: 0 | AJ71: N | AL71: n/a | AN71: None | AO71: 0 | AR71: Y | AS71: -1.09 | AT71: =IF(AND(P71="52-wk high",T71>=Settings!$B$7),"Y","N") | AU71: =IF(AND(AD71>=Settings!$B$8,M71>0),"Y","N") | AV71: =IF(OR(AH71>Settings!$B$9,AI71>Settings!$B$9),"Y","N") | AW71: =IF(AJ71<>"Y","n/a",IF(AND(M71>0,AK71>Settings!$B$10),"Y","N")) | AX71: =IF(AO71>=Settings!$B$11,"Y","N") | AY71: =(AT71="Y")+(AU71="Y")+(AV71="Y")+(AW71="Y")+(AX71="Y") | AZ71: =IF(AY71=0,"None",_xlfn.TEXTJOIN(", ",TRUE(),IF(AT71="Y","Breakout",""),IF(AU71="Y","Accumulation",""),IF(AV71="Y","Institutional buying",""),IF(AW71="Y","Long buildup",""),IF(AX71="Y","Momentum leader",""))) | BA71: =IF(BW71="","","Passes "&AY71&" of 5 buy-side scans"&IF(G71="Y","; RED FLAG: filter out using Red flag column","")) | BB71: None | BC71: Y | BD71: EPS zero | BF71: =IF(R71*100000>=Settings!$B$5,"Y","N") | BG71: =IF(F71>Settings!$B$6,"Y","N") | BH71: -25 | BI71: -6.21 | BJ71: -7.34 | BK71: -10.89 | BN71: -5.25 | BO71: -7.9 | BS71: None | BT71: 36.4 | BV71: =IF(OR(BF71<>"Y",BG71<>"Y"),"",(AND(ISNUMBER(BQ71),BQ71>0))+(BR71="Stacked up")+(AND(ISNUMBER(BH71),BH71>=-Settings!$B$17))+(AND(ISNUMBER(BK71),ISNUMBER(BM71),BK71>0,BM71>0))+(AND(ISNUMBER(AQ71),AQ71>=Settings!$B$18))+(AND(ISNUMBER(BT71),BT71>=Settings!$B$19,BT71<=Settings!$B$20))+(AND(ISNUMBER(AS71),AS71>0))+(AND(ISNUMBER(T71),ISNUMBER(M71),T71>=Settings!$B$21,M71>0))+(AND(ISNUMBER(AD71),ISNUMBER(M71),AD71>=Settings!$B$22,M71>0))+(AY71>=1)) | BW71: =IF(OR(AY71=0,BF71<>"Y",BG71<>"Y"),"",1+SUMPRODUCT(($A$6:$A$2604=A71)*($AY$6:$AY$2604>0)*($BF$6:$BF$2604="Y")*($BG$6:$BG$2604="Y")*(($AY$6:$AY$2604>AY71)+($AY$6:$AY$2604=AY71)*($AD$6:$AD$2604>AD71))))
A72: 46296 | B72: TMCV | C72: INE1TAE01010 | D72: Capital Goods | E72: Nifty Next 50 | F72: 153020 | G72: N | I72: N | J72: =IF(K72="","N","Y") | K72: =_xlfn.TEXTJOIN("; ",TRUE,IF(P72="52-wk low","52-wk low",""),IF(AND(AD72>=Settings!$B$12,M72<0),"Distribution",""),IF(AND(AJ72="Y",M72<0,AK72<-Settings!$B$13),"Long unwinding",""),IF(AND(AJ72="Y",M72<0,AK72>Settings!$B$13),"Short buildup","")) | L72: 415.5 | M72: -1.46 | N72: 1296 | O72: None | P72: None | Q72: 74.09 | R72: 63.62 | S72: 1.13 | T72: 0.97 | U72: 0.86 | V72: 0.74 | W72: 3 | Y72: None | Z72: 44.51 | AA72: 0.83 | AB72: 0.86 | AC72: 0.91 | AD72: 0.83 | AE72: 0.77 | AF72: 1.1 | AG72: Normal | AH72: 0 | AI72: 0 | AJ72: N | AL72: n/a | AN72: None | AO72: 0 | AR72: N | AS72: 5.9 | AT72: =IF(AND(P72="52-wk high",T72>=Settings!$B$7),"Y","N") | AU72: =IF(AND(AD72>=Settings!$B$8,M72>0),"Y","N") | AV72: =IF(OR(AH72>Settings!$B$9,AI72>Settings!$B$9),"Y","N") | AW72: =IF(AJ72<>"Y","n/a",IF(AND(M72>0,AK72>Settings!$B$10),"Y","N")) | AX72: =IF(AO72>=Settings!$B$11,"Y","N") | AY72: =(AT72="Y")+(AU72="Y")+(AV72="Y")+(AW72="Y")+(AX72="Y") | AZ72: =IF(AY72=0,"None",_xlfn.TEXTJOIN(", ",TRUE(),IF(AT72="Y","Breakout",""),IF(AU72="Y","Accumulation",""),IF(AV72="Y","Institutional buying",""),IF(AW72="Y","Long buildup",""),IF(AX72="Y","Momentum leader",""))) | BA72: =IF(BW72="","","Passes "&AY72&" of 5 buy-side scans"&IF(G72="Y","; RED FLAG: filter out using Red flag column","")) | BB72: None | BC72: N | BF72: =IF(R72*100000>=Settings!$B$5,"Y","N") | BG72: =IF(F72>Settings!$B$6,"Y","N") | BH72: -18.37 | BI72: -4.95 | BJ72: -10.52 | BK72: -3.7 | BL72: 4.91 | BN72: -5.3 | BO72: -5.76 | BP72: -4.17 | BQ72: -0.66 | BR72: Mixed | BS72: None | BT72: 29.8 | BU72: N | BV72: =IF(OR(BF72<>"Y",BG72<>"Y"),"",(AND(ISNUMBER(BQ72),BQ72>0))+(BR72="Stacked up")+(AND(ISNUMBER(BH72),BH72>=-Settings!$B$17))+(AND(ISNUMBER(BK72),ISNUMBER(BM72),BK72>0,BM72>0))+(AND(ISNUMBER(AQ72),AQ72>=Settings!$B$18))+(AND(ISNUMBER(BT72),BT72>=Settings!$B$19,BT72<=Settings!$B$20))+(AND(ISNUMBER(AS72),AS72>0))+(AND(ISNUMBER(T72),ISNUMBER(M72),T72>=Settings!$B$21,M72>0))+(AND(ISNUMBER(AD72),ISNUMBER(M72),AD72>=Settings!$B$22,M72>0))+(AY72>=1)) | BW72: =IF(OR(AY72=0,BF72<>"Y",BG72<>"Y"),"",1+SUMPRODUCT(($A$6:$A$2604=A72)*($AY$6:$AY$2604>0)*($BF$6:$BF$2604="Y")*($BG$6:$BG$2604="Y")*(($AY$6:$AY$2604>AY72)+($AY$6:$AY$2604=AY72)*($AD$6:$AD$2604>AD72))))
A73: 46296 | B73: PIDILITIND | C73: INE318A01026 | D73: Chemicals | E73: Nifty Next 50 | F73: 149018 | G73: N | I73: N | J73: =IF(K73="","N","Y") | K73: =_xlfn.TEXTJOIN("; ",TRUE,IF(P73="52-wk low","52-wk low",""),IF(AND(AD73>=Settings!$B$12,M73<0),"Distribution",""),IF(AND(AJ73="Y",M73<0,AK73<-Settings!$B$13),"Long unwinding",""),IF(AND(AJ73="Y",M73<0,AK73>Settings!$B$13),"Short buildup","")) | L73: 1464 | M73: -0.08 | N73: 636 | O73: None | P73: None | Q73: 8.67 | R73: 6.34 | S73: 1.39 | T73: 0.96 | U73: 0.96 | V73: 0.7 | W73: 3 | Y73: None | Z73: 60.78 | AA73: 1.01 | AB73: 1 | AC73: 1.42 | AD73: 0.98 | AE73: 0.97 | AF73: 0.99 | AG73: Normal | AH73: 0 | AI73: 0 | AJ73: Y | AK73: -1.63 | AL73: Long unwinding | AM73: 197 | AN73: None | AO73: 0 | AP73: 1.05 | AQ73: 64 | AR73: Y | AS73: 1.93 | AT73: =IF(AND(P73="52-wk high",T73>=Settings!$B$7),"Y","N") | AU73: =IF(AND(AD73>=Settings!$B$8,M73>0),"Y","N") | AV73: =IF(OR(AH73>Settings!$B$9,AI73>Settings!$B$9),"Y","N") | AW73: =IF(AJ73<>"Y","n/a",IF(AND(M73>0,AK73>Settings!$B$10),"Y","N")) | AX73: =IF(AO73>=Settings!$B$11,"Y","N") | AY73: =(AT73="Y")+(AU73="Y")+(AV73="Y")+(AW73="Y")+(AX73="Y") | AZ73: =IF(AY73=0,"None",_xlfn.TEXTJOIN(", ",TRUE(),IF(AT73="Y","Breakout",""),IF(AU73="Y","Accumulation",""),IF(AV73="Y","Institutional buying",""),IF(AW73="Y","Long buildup",""),IF(AX73="Y","Momentum leader",""))) | BA73: =IF(BW73="","","Passes "&AY73&" of 5 buy-side scans"&IF(G73="Y","; RED FLAG: filter out using Red flag column","")) | BB73: None | BC73: Y | BD73: PE > 50 | BF73: =IF(R73*100000>=Settings!$B$5,"Y","N") | BG73: =IF(F73>Settings!$B$6,"Y","N") | BH73: -14.26 | BI73: -3.81 | BJ73: -10.92 | BK73: -7.45 | BL73: 12.01 | BM73: -0.77 | BN73: -5.14 | BO73: -7.07 | BP73: -6.2 | BQ73: -4.39 | BR73: Mixed | BS73: None | BT73: 24.3 | BU73: N | BV73: =IF(OR(BF73<>"Y",BG73<>"Y"),"",(AND(ISNUMBER(BQ73),BQ73>0))+(BR73="Stacked up")+(AND(ISNUMBER(BH73),BH73>=-Settings!$B$17))+(AND(ISNUMBER(BK73),ISNUMBER(BM73),BK73>0,BM73>0))+(AND(ISNUMBER(AQ73),AQ73>=Settings!$B$18))+(AND(ISNUMBER(BT73),BT73>=Settings!$B$19,BT73<=Settings!$B$20))+(AND(ISNUMBER(AS73),AS73>0))+(AND(ISNUMBER(T73),ISNUMBER(M73),T73>=Settings!$B$21,M73>0))+(AND(ISNUMBER(AD73),ISNUMBER(M73),AD73>=Settings!$B$22,M73>0))+(AY73>=1)) | BW73: =IF(OR(AY73=0,BF73<>"Y",BG73<>"Y"),"",1+SUMPRODUCT(($A$6:$A$2604=A73)*($AY$6:$AY$2604>0)*($BF$6:$BF$2604="Y")*($BG$6:$BG$2604="Y")*(($AY$6:$AY$2604>AY73)+($AY$6:$AY$2604=AY73)*($AD$6:$AD$2604>AD73))))
A74: 46296 | B74: ABB | C74: INE117A01022 | D74: Capital Goods | E74: Nifty Next 50 | F74: 146217 | G74: N | I74: N | J74: =IF(K74="","N","Y") | K74: =_xlfn.TEXTJOIN("; ",TRUE,IF(P74="52-wk low","52-wk low",""),IF(AND(AD74>=Settings!$B$12,M74<0),"Distribution",""),IF(AND(AJ74="Y",M74<0,AK74<-Settings!$B$13),"Long unwinding",""),IF(AND(AJ74="Y",M74<0,AK74>Settings!$B$13),"Short buildup","")) | L74: 6900 | M74: 1.83 | N74: 207 | O74: None | P74: None | Q74: 2.41 | R74: 1.82 | S74: 1.35 | T74: 1.04 | U74: 0.72 | V74: 0.58 | W74: 1 | Y74: None | Z74: 39.09 | AA74: 0.81 | AB74: 0.91 | AC74: 1.07 | AD74: 0.97 | AE74: 0.69 | AF74: 1.19 | AG74: Normal | AH74: 0 | AI74: 0 | AJ74: Y | AK74: -0.74 | AL74: Short covering | AM74: 119 | AN74: 200 Mom 30; 500 Mom 50; 500 Multicap MQ 50; TotalMkt MQ 50 | AO74: 4 | AP74: 1.5 | AQ74: 79 | AR74: N | AS74: 5.9 | AT74: =IF(AND(P74="52-wk high",T74>=Settings!$B$7),"Y","N") | AU74: =IF(AND(AD74>=Settings!$B$8,M74>0),"Y","N") | AV74: =IF(OR(AH74>Settings!$B$9,AI74>Settings!$B$9),"Y","N") | AW74: =IF(AJ74<>"Y","n/a",IF(AND(M74>0,AK74>Settings!$B$10),"Y","N")) | AX74: =IF(AO74>=Settings!$B$11,"Y","N") | AY74: =(AT74="Y")+(AU74="Y")+(AV74="Y")+(AW74="Y")+(AX74="Y") | AZ74: =IF(AY74=0,"None",_xlfn.TEXTJOIN(", ",TRUE(),IF(AT74="Y","Breakout",""),IF(AU74="Y","Accumulation",""),IF(AV74="Y","Institutional buying",""),IF(AW74="Y","Long buildup",""),IF(AX74="Y","Momentum leader",""))) | BA74: =IF(BW74="","","Passes "&AY74&" of 5 buy-side scans"&IF(G74="Y","; RED FLAG: filter out using Red flag column","")) | BB74: None | BC74: N | BF74: =IF(R74*100000>=Settings!$B$5,"Y","N") | BG74: =IF(F74>Settings!$B$6,"Y","N") | BH74: -12.93 | BI74: -3.21 | BJ74: -6.71 | BK74: -0.53 | BL74: 13.81 | BM74: 32.72 | BN74: -2.98 | BO74: -4.55 | BP74: -2.77 | BQ74: 3.11 | BR74: Mixed | BS74: None | BT74: 39.2 | BU74: N | BV74: =IF(OR(BF74<>"Y",BG74<>"Y"),"",(AND(ISNUMBER(BQ74),BQ74>0))+(BR74="Stacked up")+(AND(ISNUMBER(BH74),BH74>=-Settings!$B$17))+(AND(ISNUMBER(BK74),ISNUMBER(BM74),BK74>0,BM74>0))+(AND(ISNUMBER(AQ74),AQ74>=Settings!$B$18))+(AND(ISNUMBER(BT74),BT74>=Settings!$B$19,BT74<=Settings!$B$20))+(AND(ISNUMBER(AS74),AS74>0))+(AND(ISNUMBER(T74),ISNUMBER(M74),T74>=Settings!$B$21,M74>0))+(AND(ISNUMBER(AD74),ISNUMBER(M74),AD74>=Settings!$B$22,M74>0))+(AY74>=1)) | BW74: =IF(OR(AY74=0,BF74<>"Y",BG74<>"Y"),"",1+SUMPRODUCT(($A$6:$A$2604=A74)*($AY$6:$AY$2604>0)*($BF$6:$BF$2604="Y")*($BG$6:$BG$2604="Y")*(($AY$6:$AY$2604>AY74)+($AY$6:$AY$2604=AY74)*($AD$6:$AD$2604>AD74))))
A75: 46296 | B75: VBL | C75: INE200M01039 | D75: Fast Moving Consumer Goods | E75: Nifty Next 50 | F75: 143857 | G75: N | I75: N | J75: =IF(K75="","N","Y") | K75: =_xlfn.TEXTJOIN("; ",TRUE,IF(P75="52-wk low","52-wk low",""),IF(AND(AD75>=Settings!$B$12,M75<0),"Distribution",""),IF(AND(AJ75="Y",M75<0,AK75<-Settings!$B$13),"Long unwinding",""),IF(AND(AJ75="Y",M75<0,AK75>Settings!$B$13),"Short buildup","")) | L75: 425.3 | M75: -1.55 | N75: 1366 | O75: None | P75: None | Q75: 85.16 | R75: 59.32 | S75: 1.44 | T75: 1.27 | U75: 1.36 | V75: 0.94 | W75: 7 | X75: 222 | Y75: None | Z75: 55.87 | AA75: 0.95 | AB75: 0.98 | AC75: 1.38 | AD75: 1.3 | AE75: 1.39 | AF75: 1.08 | AG75: Normal | AH75: 0 | AI75: 0 | AJ75: Y | AK75: -1.97 | AL75: Long unwinding | AM75: 53 | AN75: None | AO75: 0 | AP75: 0.85 | AQ75: 53 | AR75: Y | AS75: 2.11 | AT75: =IF(AND(P75="52-wk high",T75>=Settings!$B$7),"Y","N") | AU75: =IF(AND(AD75>=Settings!$B$8,M75>0),"Y","N") | AV75: =IF(OR(AH75>Settings!$B$9,AI75>Settings!$B$9),"Y","N") | AW75: =IF(AJ75<>"Y","n/a",IF(AND(M75>0,AK75>Settings!$B$10),"Y","N")) | AX75: =IF(AO75>=Settings!$B$11,"Y","N") | AY75: =(AT75="Y")+(AU75="Y")+(AV75="Y")+(AW75="Y")+(AX75="Y") | AZ75: =IF(AY75=0,"None",_xlfn.TEXTJOIN(", ",TRUE(),IF(AT75="Y","Breakout",""),IF(AU75="Y","Accumulation",""),IF(AV75="Y","Institutional buying",""),IF(AW75="Y","Long buildup",""),IF(AX75="Y","Momentum leader",""))) | BA75: =IF(BW75="","","Passes "&AY75&" of 5 buy-side scans"&IF(G75="Y","; RED FLAG: filter out using Red flag column","")) | BB75: None | BC75: N | BF75: =IF(R75*100000>=Settings!$B$5,"Y","N") | BG75: =IF(F75>Settings!$B$6,"Y","N") | BH75: -23.48 | BI75: -1.38 | BJ75: 4.79 | BK75: -17.53 | BL75: 5.85 | BM75: -3.98 | BN75: 0.05 | BO75: -2.09 | BP75: -5.27 | BQ75: -7.07 | BR75: Mixed | BS75: None | BT75: 50 | BU75: N | BV75: =IF(OR(BF75<>"Y",BG75<>"Y"),"",(AND(ISNUMBER(BQ75),BQ75>0))+(BR75="Stacked up")+(AND(ISNUMBER(BH75),BH75>=-Settings!$B$17))+(AND(ISNUMBER(BK75),ISNUMBER(BM75),BK75>0,BM75>0))+(AND(ISNUMBER(AQ75),AQ75>=Settings!$B$18))+(AND(ISNUMBER(BT75),BT75>=Settings!$B$19,BT75<=Settings!$B$20))+(AND(ISNUMBER(AS75),AS75>0))+(AND(ISNUMBER(T75),ISNUMBER(M75),T75>=Settings!$B$21,M75>0))+(AND(ISNUMBER(AD75),ISNUMBER(M75),AD75>=Settings!$B$22,M75>0))+(AY75>=1)) | BW75: =IF(OR(AY75=0,BF75<>"Y",BG75<>"Y"),"",1+SUMPRODUCT(($A$6:$A$2604=A75)*($AY$6:$AY$2604>0)*($BF$6:$BF$2604="Y")*($BG$6:$BG$2604="Y")*(($AY$6:$AY$2604>AY75)+($AY$6:$AY$2604=AY75)*($AD$6:$AD$2604>AD75))))
A76: 46296 | B76: POWERINDIA | C76: INE07Y701011 | D76: Capital Goods | E76: Nifty Next 50 | F76: 139467 | G76: N | I76: N | J76: =IF(K76="","N","Y") | K76: =_xlfn.TEXTJOIN("; ",TRUE,IF(P76="52-wk low","52-wk low",""),IF(AND(AD76>=Settings!$B$12,M76<0),"Distribution",""),IF(AND(AJ76="Y",M76<0,AK76<-Settings!$B$13),"Long unwinding",""),IF(AND(AJ76="Y",M76<0,AK76>Settings!$B$13),"Short buildup","")) | L76: 31290 | M76: 2.15 | N76: 175 | O76: None | P76: None | Q76: 1.45 | R76: 1.1 | S76: 1.36 | T76: 1.26 | U76: 0.99 | V76: 0.75 | W76: 2 | Y76: None | Z76: 36.88 | AA76: 0.83 | AB76: 0.95 | AC76: 1.07 | AD76: 1.23 | AE76: 1.03 | AF76: 1.31 | AG76: Normal | AH76: 0 | AI76: 0 | AJ76: Y | AK76: -1.39 | AL76: Short covering | AM76: 59 | AN76: 200 Mom 30; 500 Mom 50; Mid150 Mom 50; MidSmall400 MQ 100; 500 Multicap MQ 50; TotalMkt MQ 50 | AO76: 6 | AP76: 1.82 | AQ76: 87 | AR76: Y | AS76: 5.9 | AT76: =IF(AND(P76="52-wk high",T76>=Settings!$B$7),"Y","N") | AU76: =IF(AND(AD76>=Settings!$B$8,M76>0),"Y","N") | AV76: =IF(OR(AH76>Settings!$B$9,AI76>Settings!$B$9),"Y","N") | AW76: =IF(AJ76<>"Y","n/a",IF(AND(M76>0,AK76>Settings!$B$10),"Y","N")) | AX76: =IF(AO76>=Settings!$B$11,"Y","N") | AY76: =(AT76="Y")+(AU76="Y")+(AV76="Y")+(AW76="Y")+(AX76="Y") | AZ76: =IF(AY76=0,"None",_xlfn.TEXTJOIN(", ",TRUE(),IF(AT76="Y","Breakout",""),IF(AU76="Y","Accumulation",""),IF(AV76="Y","Institutional buying",""),IF(AW76="Y","Long buildup",""),IF(AX76="Y","Momentum leader",""))) | BA76: =IF(BW76="","","Passes "&AY76&" of 5 buy-side scans"&IF(G76="Y","; RED FLAG: filter out using Red flag column","")) | BB76: None | BC76: Y | BD76: PE > 50 | BF76: =IF(R76*100000>=Settings!$B$5,"Y","N") | BG76: =IF(F76>Settings!$B$6,"Y","N") | BH76: -19.32 | BI76: 1.87 | BJ76: -4.14 | BK76: -8.64 | BL76: 24.84 | BM76: 72.55 | BN76: -0.42 | BO76: -2.63 | BP76: -1.31 | BQ76: 6.95 | BR76: Mixed | BS76: None | BT76: 49.8 | BU76: N | BV76: =IF(OR(BF76<>"Y",BG76<>"Y"),"",(AND(ISNUMBER(BQ76),BQ76>0))+(BR76="Stacked up")+(AND(ISNUMBER(BH76),BH76>=-Settings!$B$17))+(AND(ISNUMBER(BK76),ISNUMBER(BM76),BK76>0,BM76>0))+(AND(ISNUMBER(AQ76),AQ76>=Settings!$B$18))+(AND(ISNUMBER(BT76),BT76>=Settings!$B$19,BT76<=Settings!$B$20))+(AND(ISNUMBER(AS76),AS76>0))+(AND(ISNUMBER(T76),ISNUMBER(M76),T76>=Settings!$B$21,M76>0))+(AND(ISNUMBER(AD76),ISNUMBER(M76),AD76>=Settings!$B$22,M76>0))+(AY76>=1)) | BW76: =IF(OR(AY76=0,BF76<>"Y",BG76<>"Y"),"",1+SUMPRODUCT(($A$6:$A$2604=A76)*($AY$6:$AY$2604>0)*($BF$6:$BF$2604="Y")*($BG$6:$BG$2604="Y")*(($AY$6:$AY$2604>AY76)+($AY$6:$AY$2604=AY76)*($AD$6:$AD$2604>AD76))))
A77: 46296 | B77: CGPOWER | C77: INE067A01029 | D77: Capital Goods | E77: Nifty Next 50 | F77: 138482 | G77: N | I77: N | J77: =IF(K77="","N","Y") | K77: =_xlfn.TEXTJOIN("; ",TRUE,IF(P77="52-wk low","52-wk low",""),IF(AND(AD77>=Settings!$B$12,M77<0),"Distribution",""),IF(AND(AJ77="Y",M77<0,AK77<-Settings!$B$13),"Long unwinding",""),IF(AND(AJ77="Y",M77<0,AK77>Settings!$B$13),"Short buildup","")) | L77: 879 | M77: 2.9 | N77: 125 | O77: None | P77: None | Q77: 46.33 | R77: 24.74 | S77: 1.98 | T77: 1.59 | U77: 1.27 | V77: 0.68 | W77: 1 | X77: 166 | Y77: None | Z77: 26.29 | AA77: 0.57 | AB77: 0.56 | AC77: 1.15 | AD77: 0.94 | AE77: 0.74 | AF77: 0.95 | AG77: Normal | AH77: 0 | AI77: 0 | AJ77: Y | AK77: -1.03 | AL77: Short covering | AM77: 62 | AN77: 200 Mom 30; 500 Mom 50; 500 Multicap MQ 50; TotalMkt MQ 50 | AO77: 4 | AP77: 1.47 | AQ77: 79 | AR77: Y | AS77: 5.9 | AT77: =IF(AND(P77="52-wk high",T77>=Settings!$B$7),"Y","N") | AU77: =IF(AND(AD77>=Settings!$B$8,M77>0),"Y","N") | AV77: =IF(OR(AH77>Settings!$B$9,AI77>Settings!$B$9),"Y","N") | AW77: =IF(AJ77<>"Y","n/a",IF(AND(M77>0,AK77>Settings!$B$10),"Y","N")) | AX77: =IF(AO77>=Settings!$B$11,"Y","N") | AY77: =(AT77="Y")+(AU77="Y")+(AV77="Y")+(AW77="Y")+(AX77="Y") | AZ77: =IF(AY77=0,"None",_xlfn.TEXTJOIN(", ",TRUE(),IF(AT77="Y","Breakout",""),IF(AU77="Y","Accumulation",""),IF(AV77="Y","Institutional buying",""),IF(AW77="Y","Long buildup",""),IF(AX77="Y","Momentum leader",""))) | BA77: =IF(BW77="","","Passes "&AY77&" of 5 buy-side scans"&IF(G77="Y","; RED FLAG: filter out using Red flag column","")) | BB77: None | BC77: Y | BD77: PE > 50 | BF77: =IF(R77*100000>=Settings!$B$5,"Y","N") | BG77: =IF(F77>Settings!$B$6,"Y","N") | BH77: -10.39 | BI77: -0.87 | BJ77: -0.73 | BK77: -9.98 | BL77: 29.21 | BM77: 18.82 | BN77: -0.32 | BO77: -0.64 | BP77: 1.18 | BQ77: 5.78 | BR77: Mixed | BS77: None | BT77: 49.2 | BU77: N | BV77: =IF(OR(BF77<>"Y",BG77<>"Y"),"",(AND(ISNUMBER(BQ77),BQ77>0))+(BR77="Stacked up")+(AND(ISNUMBER(BH77),BH77>=-Settings!$B$17))+(AND(ISNUMBER(BK77),ISNUMBER(BM77),BK77>0,BM77>0))+(AND(ISNUMBER(AQ77),AQ77>=Settings!$B$18))+(AND(ISNUMBER(BT77),BT77>=Settings!$B$19,BT77<=Settings!$B$20))+(AND(ISNUMBER(AS77),AS77>0))+(AND(ISNUMBER(T77),ISNUMBER(M77),T77>=Settings!$B$21,M77>0))+(AND(ISNUMBER(AD77),ISNUMBER(M77),AD77>=Settings!$B$22,M77>0))+(AY77>=1)) | BW77: =IF(OR(AY77=0,BF77<>"Y",BG77<>"Y"),"",1+SUMPRODUCT(($A$6:$A$2604=A77)*($AY$6:$AY$2604>0)*($BF$6:$BF$2604="Y")*($BG$6:$BG$2604="Y")*(($AY$6:$AY$2604>AY77)+($AY$6:$AY$2604=AY77)*($AD$6:$AD$2604>AD77))))
A78: 46296 | B78: IDEA | C78: INE669E01016 | D78: Telecommunication | E78: Nifty Next 50 | F78: 136946 | G78: N | I78: N | J78: =IF(K78="","N","Y") | K78: =_xlfn.TEXTJOIN("; ",TRUE,IF(P78="52-wk low","52-wk low",""),IF(AND(AD78>=Settings!$B$12,M78<0),"Distribution",""),IF(AND(AJ78="Y",M78<0,AK78<-Settings!$B$13),"Long unwinding",""),IF(AND(AJ78="Y",M78<0,AK78>Settings!$B$13),"Short buildup","")) | L78: 12.64 | M78: -2.39 | N78: 1838 | O78: None | P78: None | Q78: 6124.9 | R78: 4851.56 | S78: 1.27 | T78: 1.38 | U78: 1.12 | V78: 0.91 | W78: 5 | X78: 246 | Y78: By volume | Z78: 33.78 | AA78: 1.03 | AB78: 1.16 | AC78: 1.23 | AD78: 1.56 | AE78: 1.36 | AF78: 1.26 | AG78: Normal | AH78: 0 | AI78: 0 | AJ78: Y | AK78: -0.19 | AL78: Long unwinding | AM78: 12 | AN78: 200 Mom 30; 500 Mom 50; Mid150 Mom 50 | AO78: 3 | AP78: 1.8 | AQ78: 86 | AR78: Y | AS78: 2.57 | AT78: =IF(AND(P78="52-wk high",T78>=Settings!$B$7),"Y","N") | AU78: =IF(AND(AD78>=Settings!$B$8,M78>0),"Y","N") | AV78: =IF(OR(AH78>Settings!$B$9,AI78>Settings!$B$9),"Y","N") | AW78: =IF(AJ78<>"Y","n/a",IF(AND(M78>0,AK78>Settings!$B$10),"Y","N")) | AX78: =IF(AO78>=Settings!$B$11,"Y","N") | AY78: =(AT78="Y")+(AU78="Y")+(AV78="Y")+(AW78="Y")+(AX78="Y") | AZ78: =IF(AY78=0,"None",_xlfn.TEXTJOIN(", ",TRUE(),IF(AT78="Y","Breakout",""),IF(AU78="Y","Accumulation",""),IF(AV78="Y","Institutional buying",""),IF(AW78="Y","Long buildup",""),IF(AX78="Y","Momentum leader",""))) | BA78: =IF(BW78="","","Passes "&AY78&" of 5 buy-side scans"&IF(G78="Y","; RED FLAG: filter out using Red flag column","")) | BB78: Upper | BC78: N | BF78: =IF(R78*100000>=Settings!$B$5,"Y","N") | BG78: =IF(F78>Settings!$B$6,"Y","N") | BH78: -19.95 | BI78: -10.48 | BJ78: -10.1 | BK78: -13.66 | BL78: 46.3 | BM78: 48.36 | BN78: -9.48 | BO78: -9.59 | BP78: -6.3 | BQ78: 1.36 | BR78: Mixed | BS78: Bearish cross | BT78: 26.3 | BU78: N | BV78: =IF(OR(BF78<>"Y",BG78<>"Y"),"",(AND(ISNUMBER(BQ78),BQ78>0))+(BR78="Stacked up")+(AND(ISNUMBER(BH78),BH78>=-Settings!$B$17))+(AND(ISNUMBER(BK78),ISNUMBER(BM78),BK78>0,BM78>0))+(AND(ISNUMBER(AQ78),AQ78>=Settings!$B$18))+(AND(ISNUMBER(BT78),BT78>=Settings!$B$19,BT78<=Settings!$B$20))+(AND(ISNUMBER(AS78),AS78>0))+(AND(ISNUMBER(T78),ISNUMBER(M78),T78>=Settings!$B$21,M78>0))+(AND(ISNUMBER(AD78),ISNUMBER(M78),AD78>=Settings!$B$22,M78>0))+(AY78>=1)) | BW78: =IF(OR(AY78=0,BF78<>"Y",BG78<>"Y"),"",1+SUMPRODUCT(($A$6:$A$2604=A78)*($AY$6:$AY$2604>0)*($BF$6:$BF$2604="Y")*($BG$6:$BG$2604="Y")*(($AY$6:$AY$2604>AY78)+($AY$6:$AY$2604=AY78)*($AD$6:$AD$2604>AD78))))
A79: 46296 | B79: TATACAP | C79: INE976I01016 | D79: Financial Services | E79: Nifty Next 50 | F79: 135539 | G79: N | I79: N | J79: =IF(K79="","N","Y") | K79: =_xlfn.TEXTJOIN("; ",TRUE,IF(P79="52-wk low","52-wk low",""),IF(AND(AD79>=Settings!$B$12,M79<0),"Distribution",""),IF(AND(AJ79="Y",M79<0,AK79<-Settings!$B$13),"Long unwinding",""),IF(AND(AJ79="Y",M79<0,AK79>Settings!$B$13),"Short buildup","")) | L79: 319.3 | M79: -2.64 | N79: 1953 | O79: None | P79: None | Q79: 24.68 | R79: 15.24 | S79: 1.72 | T79: 1.47 | U79: 1 | V79: 0.61 | W79: 2 | Y79: None | Z79: 60.59 | AA79: 1.07 | AB79: 1.12 | AC79: 1.89 | AD79: 1.83 | AE79: 1.15 | AF79: 1.06 | AG79: Normal | AH79: 0 | AI79: 0 | AJ79: N | AL79: n/a | AN79: None | AO79: 0 | AR79: N | AS79: 0.6 | AT79: =IF(AND(P79="52-wk high",T79>=Settings!$B$7),"Y","N") | AU79: =IF(AND(AD79>=Settings!$B$8,M79>0),"Y","N") | AV79: =IF(OR(AH79>Settings!$B$9,AI79>Settings!$B$9),"Y","N") | AW79: =IF(AJ79<>"Y","n/a",IF(AND(M79>0,AK79>Settings!$B$10),"Y","N")) | AX79: =IF(AO79>=Settings!$B$11,"Y","N") | AY79: =(AT79="Y")+(AU79="Y")+(AV79="Y")+(AW79="Y")+(AX79="Y") | AZ79: =IF(AY79=0,"None",_xlfn.TEXTJOIN(", ",TRUE(),IF(AT79="Y","Breakout",""),IF(AU79="Y","Accumulation",""),IF(AV79="Y","Institutional buying",""),IF(AW79="Y","Long buildup",""),IF(AX79="Y","Momentum leader",""))) | BA79: =IF(BW79="","","Passes "&AY79&" of 5 buy-side scans"&IF(G79="Y","; RED FLAG: filter out using Red flag column","")) | BB79: None | BC79: N | BF79: =IF(R79*100000>=Settings!$B$5,"Y","N") | BG79: =IF(F79>Settings!$B$6,"Y","N") | BH79: -18.17 | BI79: -5.04 | BJ79: -13.2 | BK79: -11.69 | BL79: 4.38 | BN79: -7.24 | BO79: -9.13 | BP79: -8.37 | BQ79: -6.8 | BR79: Mixed | BS79: None | BT79: 26 | BU79: N | BV79: =IF(OR(BF79<>"Y",BG79<>"Y"),"",(AND(ISNUMBER(BQ79),BQ79>0))+(BR79="Stacked up")+(AND(ISNUMBER(BH79),BH79>=-Settings!$B$17))+(AND(ISNUMBER(BK79),ISNUMBER(BM79),BK79>0,BM79>0))+(AND(ISNUMBER(AQ79),AQ79>=Settings!$B$18))+(AND(ISNUMBER(BT79),BT79>=Settings!$B$19,BT79<=Settings!$B$20))+(AND(ISNUMBER(AS79),AS79>0))+(AND(ISNUMBER(T79),ISNUMBER(M79),T79>=Settings!$B$21,M79>0))+(AND(ISNUMBER(AD79),ISNUMBER(M79),AD79>=Settings!$B$22,M79>0))+(AY79>=1)) | BW79: =IF(OR(AY79=0,BF79<>"Y",BG79<>"Y"),"",1+SUMPRODUCT(($A$6:$A$2604=A79)*($AY$6:$AY$2604>0)*($BF$6:$BF$2604="Y")*($BG$6:$BG$2604="Y")*(($AY$6:$AY$2604>AY79)+($AY$6:$AY$2604=AY79)*($AD$6:$AD$2604>AD79))))
A80: 46296 | B80: SIEMENS | C80: INE003A01024 | D80: Capital Goods | E80: Nifty Next 50 | F80: 135468 | G80: N | I80: N | J80: =IF(K80="","N","Y") | K80: =_xlfn.TEXTJOIN("; ",TRUE,IF(P80="52-wk low","52-wk low",""),IF(AND(AD80>=Settings!$B$12,M80<0),"Distribution",""),IF(AND(AJ80="Y",M80<0,AK80<-Settings!$B$13),"Long unwinding",""),IF(AND(AJ80="Y",M80<0,AK80>Settings!$B$13),"Short buildup","")) | L80: 3804 | M80: 2.1 | N80: 177 | O80: None | P80: None | Q80: 2.44 | R80: 2.62 | S80: 0.93 | T80: 0.69 | U80: 0.6 | V80: 0.65 | W80: 1 | Y80: None | Z80: 42.26 | AA80: 0.96 | AB80: 1.03 | AC80: 0.85 | AD80: 0.76 | AE80: 0.67 | AF80: 1.22 | AG80: Normal | AH80: 0 | AI80: 0 | AJ80: Y | AK80: -2.37 | AL80: Short covering | AM80: 153 | AN80: None | AO80: 0 | AP80: 1.56 | AQ80: 81 | AR80: N | AS80: 5.9 | AT80: =IF(AND(P80="52-wk high",T80>=Settings!$B$7),"Y","N") | AU80: =IF(AND(AD80>=Settings!$B$8,M80>0),"Y","N") | AV80: =IF(OR(AH80>Settings!$B$9,AI80>Settings!$B$9),"Y","N") | AW80: =IF(AJ80<>"Y","n/a",IF(AND(M80>0,AK80>Settings!$B$10),"Y","N")) | AX80: =IF(AO80>=Settings!$B$11,"Y","N") | AY80: =(AT80="Y")+(AU80="Y")+(AV80="Y")+(AW80="Y")+(AX80="Y") | AZ80: =IF(AY80=0,"None",_xlfn.TEXTJOIN(", ",TRUE(),IF(AT80="Y","Breakout",""),IF(AU80="Y","Accumulation",""),IF(AV80="Y","Institutional buying",""),IF(AW80="Y","Long buildup",""),IF(AX80="Y","Momentum leader",""))) | BA80: =IF(BW80="","","Passes "&AY80&" of 5 buy-side scans"&IF(G80="Y","; RED FLAG: filter out using Red flag column","")) | BB80: None | BC80: N | BF80: =IF(R80*100000>=Settings!$B$5,"Y","N") | BG80: =IF(F80>Settings!$B$6,"Y","N") | BH80: -8.32 | BI80: -0.98 | BJ80: -5.61 | BK80: 6.83 | BL80: 26.09 | BM80: 21.86 | BN80: -1.21 | BO80: -1.17 | BP80: 1.23 | BQ80: 5.68 | BR80: Mixed | BS80: None | BT80: 45.5 | BU80: N | BV80: =IF(OR(BF80<>"Y",BG80<>"Y"),"",(AND(ISNUMBER(BQ80),BQ80>0))+(BR80="Stacked up")+(AND(ISNUMBER(BH80),BH80>=-Settings!$B$17))+(AND(ISNUMBER(BK80),ISNUMBER(BM80),BK80>0,BM80>0))+(AND(ISNUMBER(AQ80),AQ80>=Settings!$B$18))+(AND(ISNUMBER(BT80),BT80>=Settings!$B$19,BT80<=Settings!$B$20))+(AND(ISNUMBER(AS80),AS80>0))+(AND(ISNUMBER(T80),ISNUMBER(M80),T80>=Settings!$B$21,M80>0))+(AND(ISNUMBER(AD80),ISNUMBER(M80),AD80>=Settings!$B$22,M80>0))+(AY80>=1)) | BW80: =IF(OR(AY80=0,BF80<>"Y",BG80<>"Y"),"",1+SUMPRODUCT(($A$6:$A$2604=A80)*($AY$6:$AY$2604>0)*($BF$6:$BF$2604="Y")*($BG$6:$BG$2604="Y")*(($AY$6:$AY$2604>AY80)+($AY$6:$AY$2604=AY80)*($AD$6:$AD$2604>AD80))))
A81: 46296 | B81: CHOLAFIN | C81: INE121A01024 | D81: Financial Services | E81: Nifty Next 50 | F81: 134981 | G81: N | I81: N | J81: =IF(K81="","N","Y") | K81: =_xlfn.TEXTJOIN("; ",TRUE,IF(P81="52-wk low","52-wk low",""),IF(AND(AD81>=Settings!$B$12,M81<0),"Distribution",""),IF(AND(AJ81="Y",M81<0,AK81<-Settings!$B$13),"Long unwinding",""),IF(AND(AJ81="Y",M81<0,AK81>Settings!$B$13),"Short buildup","")) | L81: 1580 | M81: -2.47 | N81: 1877 | O81: None | P81: None | Q81: 17 | R81: 15.67 | S81: 1.12 | T81: 1.18 | U81: 1.13 | V81: 1.04 | W81: 7 | X81: 275 | Y81: None | Z81: 59.26 | AA81: 0.97 | AB81: 1 | AC81: 1.11 | AD81: 1.23 | AE81: 1.17 | AF81: 1.04 | AG81: Normal | AH81: 0 | AI81: 0 | AJ81: Y | AK81: -1.08 | AL81: Long unwinding | AM81: 54 | AN81: None | AO81: 0 | AP81: 1 | AQ81: 62 | AR81: Y | AS81: 0.6 | AT81: =IF(AND(P81="52-wk high",T81>=Settings!$B$7),"Y","N") | AU81: =IF(AND(AD81>=Settings!$B$8,M81>0),"Y","N") | AV81: =IF(OR(AH81>Settings!$B$9,AI81>Settings!$B$9),"Y","N") | AW81: =IF(AJ81<>"Y","n/a",IF(AND(M81>0,AK81>Settings!$B$10),"Y","N")) | AX81: =IF(AO81>=Settings!$B$11,"Y","N") | AY81: =(AT81="Y")+(AU81="Y")+(AV81="Y")+(AW81="Y")+(AX81="Y") | AZ81: =IF(AY81=0,"None",_xlfn.TEXTJOIN(", ",TRUE(),IF(AT81="Y","Breakout",""),IF(AU81="Y","Accumulation",""),IF(AV81="Y","Institutional buying",""),IF(AW81="Y","Long buildup",""),IF(AX81="Y","Momentum leader",""))) | BA81: =IF(BW81="","","Passes "&AY81&" of 5 buy-side scans"&IF(G81="Y","; RED FLAG: filter out using Red flag column","")) | BB81: None | BC81: N | BF81: =IF(R81*100000>=Settings!$B$5,"Y","N") | BG81: =IF(F81>Settings!$B$6,"Y","N") | BH81: -19.08 | BI81: -6.05 | BJ81: -12.93 | BK81: -12.38 | BL81: 15.03 | BM81: -1.58 | BN81: -8.6 | BO81: -10.74 | BP81: -9.57 | BQ81: -7.53 | BR81: Mixed | BS81: None | BT81: 16.2 | BU81: N | BV81: =IF(OR(BF81<>"Y",BG81<>"Y"),"",(AND(ISNUMBER(BQ81),BQ81>0))+(BR81="Stacked up")+(AND(ISNUMBER(BH81),BH81>=-Settings!$B$17))+(AND(ISNUMBER(BK81),ISNUMBER(BM81),BK81>0,BM81>0))+(AND(ISNUMBER(AQ81),AQ81>=Settings!$B$18))+(AND(ISNUMBER(BT81),BT81>=Settings!$B$19,BT81<=Settings!$B$20))+(AND(ISNUMBER(AS81),AS81>0))+(AND(ISNUMBER(T81),ISNUMBER(M81),T81>=Settings!$B$21,M81>0))+(AND(ISNUMBER(AD81),ISNUMBER(M81),AD81>=Settings!$B$22,M81>0))+(AY81>=1)) | BW81: =IF(OR(AY81=0,BF81<>"Y",BG81<>"Y"),"",1+SUMPRODUCT(($A$6:$A$2604=A81)*($AY$6:$AY$2604>0)*($BF$6:$BF$2604="Y")*($BG$6:$BG$2604="Y")*(($AY$6:$AY$2604>AY81)+($AY$6:$AY$2604=AY81)*($AD$6:$AD$2604>AD81))))
A82: 46296 | B82: CUMMINSIND | C82: INE298A01020 | D82: Capital Goods | E82: Nifty Next 50 | F82: 134719 | G82: N | I82: N | J82: =IF(K82="","N","Y") | K82: =_xlfn.TEXTJOIN("; ",TRUE,IF(P82="52-wk low","52-wk low",""),IF(AND(AD82>=Settings!$B$12,M82<0),"Distribution",""),IF(AND(AJ82="Y",M82<0,AK82<-Settings!$B$13),"Long unwinding",""),IF(AND(AJ82="Y",M82<0,AK82>Settings!$B$13),"Short buildup","")) | L82: 4860 | M82: 2.1 | N82: 177 | O82: None | P82: None | Q82: 3.94 | R82: 3.94 | S82: 1 | T82: 0.9 | U82: 0.84 | V82: 0.84 | W82: 5 | Y82: None | Z82: 48.69 | AA82: 0.78 | AB82: 0.81 | AC82: 0.77 | AD82: 0.73 | AE82: 0.73 | AF82: 1.11 | AG82: Normal | AH82: 0 | AI82: 0 | AJ82: Y | AK82: 0.96 | AL82: Long buildup | AM82: 91 | AN82: 200 Mom 30; 500 Mom 50; 500 Multicap MQ 50; TotalMkt MQ 50 | AO82: 4 | AP82: 1.3 | AQ82: 73 | AR82: Y | AS82: 5.9 | AT82: =IF(AND(P82="52-wk high",T82>=Settings!$B$7),"Y","N") | AU82: =IF(AND(AD82>=Settings!$B$8,M82>0),"Y","N") | AV82: =IF(OR(AH82>Settings!$B$9,AI82>Settings!$B$9),"Y","N") | AW82: =IF(AJ82<>"Y","n/a",IF(AND(M82>0,AK82>Settings!$B$10),"Y","N")) | AX82: =IF(AO82>=Settings!$B$11,"Y","N") | AY82: =(AT82="Y")+(AU82="Y")+(AV82="Y")+(AW82="Y")+(AX82="Y") | AZ82: =IF(AY82=0,"None",_xlfn.TEXTJOIN(", ",TRUE(),IF(AT82="Y","Breakout",""),IF(AU82="Y","Accumulation",""),IF(AV82="Y","Institutional buying",""),IF(AW82="Y","Long buildup",""),IF(AX82="Y","Momentum leader",""))) | BA82: =IF(BW82="","","Passes "&AY82&" of 5 buy-side scans"&IF(G82="Y","; RED FLAG: filter out using Red flag column","")) | BB82: None | BC82: Y | BD82: PE > 50 | BF82: =IF(R82*100000>=Settings!$B$5,"Y","N") | BG82: =IF(F82>Settings!$B$6,"Y","N") | BH82: -20.33 | BI82: -2.27 | BJ82: -4.8 | BK82: -14.18 | BL82: 5.44 | BM82: 26.27 | BN82: -2.45 | BO82: -5.53 | BP82: -6.32 | BQ82: -3.1 | BR82: Mixed | BS82: None | BT82: 40.1 | BU82: N | BV82: =IF(OR(BF82<>"Y",BG82<>"Y"),"",(AND(ISNUMBER(BQ82),BQ82>0))+(BR82="Stacked up")+(AND(ISNUMBER(BH82),BH82>=-Settings!$B$17))+(AND(ISNUMBER(BK82),ISNUMBER(BM82),BK82>0,BM82>0))+(AND(ISNUMBER(AQ82),AQ82>=Settings!$B$18))+(AND(ISNUMBER(BT82),BT82>=Settings!$B$19,BT82<=Settings!$B$20))+(AND(ISNUMBER(AS82),AS82>0))+(AND(ISNUMBER(T82),ISNUMBER(M82),T82>=Settings!$B$21,M82>0))+(AND(ISNUMBER(AD82),ISNUMBER(M82),AD82>=Settings!$B$22,M82>0))+(AY82>=1)) | BW82: =IF(OR(AY82=0,BF82<>"Y",BG82<>"Y"),"",1+SUMPRODUCT(($A$6:$A$2604=A82)*($AY$6:$AY$2604>0)*($BF$6:$BF$2604="Y")*($BG$6:$BG$2604="Y")*(($AY$6:$AY$2604>AY82)+($AY$6:$AY$2604=AY82)*($AD$6:$AD$2604>AD82))))
A83: 46296 | B83: BOSCHLTD | C83: INE323A01026 | D83: Automobile and Auto Components | E83: Nifty Next 50 | F83: 134148 | G83: N | I83: N | J83: =IF(K83="","N","Y") | K83: =_xlfn.TEXTJOIN("; ",TRUE,IF(P83="52-wk low","52-wk low",""),IF(AND(AD83>=Settings!$B$12,M83<0),"Distribution",""),IF(AND(AJ83="Y",M83<0,AK83<-Settings!$B$13),"Long unwinding",""),IF(AND(AJ83="Y",M83<0,AK83>Settings!$B$13),"Short buildup","")) | L83: 45480 | M83: -3.44 | N83: 2212 | O83: None | P83: None | Q83: 0.49 | R83: 0.25 | S83: 1.93 | T83: 1.35 | U83: 1.26 | V83: 0.65 | W83: 2 | Y83: None | Z83: 48.41 | AA83: 1.03 | AB83: 1.1 | AC83: 1.97 | AD83: 1.59 | AE83: 1.43 | AF83: 1.12 | AG83: Normal | AH83: 0 | AI83: 0 | AJ83: Y | AK83: 3.98 | AL83: Short buildup | AM83: 74 | AN83: TotalMkt MQ 50 | AO83: 1 | AP83: 1.95 | AQ83: 88 | AR83: N | AS83: 0.56 | AT83: =IF(AND(P83="52-wk high",T83>=Settings!$B$7),"Y","N") | AU83: =IF(AND(AD83>=Settings!$B$8,M83>0),"Y","N") | AV83: =IF(OR(AH83>Settings!$B$9,AI83>Settings!$B$9),"Y","N") | AW83: =IF(AJ83<>"Y","n/a",IF(AND(M83>0,AK83>Settings!$B$10),"Y","N")) | AX83: =IF(AO83>=Settings!$B$11,"Y","N") | AY83: =(AT83="Y")+(AU83="Y")+(AV83="Y")+(AW83="Y")+(AX83="Y") | AZ83: =IF(AY83=0,"None",_xlfn.TEXTJOIN(", ",TRUE(),IF(AT83="Y","Breakout",""),IF(AU83="Y","Accumulation",""),IF(AV83="Y","Institutional buying",""),IF(AW83="Y","Long buildup",""),IF(AX83="Y","Momentum leader",""))) | BA83: =IF(BW83="","","Passes "&AY83&" of 5 buy-side scans"&IF(G83="Y","; RED FLAG: filter out using Red flag column","")) | BB83: Upper | BC83: Y | BD83: PE > 50 | BF83: =IF(R83*100000>=Settings!$B$5,"Y","N") | BG83: =IF(F83>Settings!$B$6,"Y","N") | BH83: -9.04 | BI83: -4.75 | BJ83: -6.32 | BK83: 11.51 | BL83: 48.46 | BM83: 18.68 | BN83: -3.75 | BO83: -1.16 | BP83: 4.43 | BQ83: 10.78 | BR83: Mixed | BS83: None | BT83: 37.3 | BU83: N | BV83: =IF(OR(BF83<>"Y",BG83<>"Y"),"",(AND(ISNUMBER(BQ83),BQ83>0))+(BR83="Stacked up")+(AND(ISNUMBER(BH83),BH83>=-Settings!$B$17))+(AND(ISNUMBER(BK83),ISNUMBER(BM83),BK83>0,BM83>0))+(AND(ISNUMBER(AQ83),AQ83>=Settings!$B$18))+(AND(ISNUMBER(BT83),BT83>=Settings!$B$19,BT83<=Settings!$B$20))+(AND(ISNUMBER(AS83),AS83>0))+(AND(ISNUMBER(T83),ISNUMBER(M83),T83>=Settings!$B$21,M83>0))+(AND(ISNUMBER(AD83),ISNUMBER(M83),AD83>=Settings!$B$22,M83>0))+(AY83>=1)) | BW83: =IF(OR(AY83=0,BF83<>"Y",BG83<>"Y"),"",1+SUMPRODUCT(($A$6:$A$2604=A83)*($AY$6:$AY$2604>0)*($BF$6:$BF$2604="Y")*($BG$6:$BG$2604="Y")*(($AY$6:$AY$2604>AY83)+($AY$6:$AY$2604=AY83)*($AD$6:$AD$2604>AD83))))
A84: 46296 | B84: BPCL | C84: INE029A01011 | D84: Oil Gas & Consumable Fuels | E84: Nifty Next 50 | F84: 130415 | G84: N | I84: N | J84: =IF(K84="","N","Y") | K84: =_xlfn.TEXTJOIN("; ",TRUE,IF(P84="52-wk low","52-wk low",""),IF(AND(AD84>=Settings!$B$12,M84<0),"Distribution",""),IF(AND(AJ84="Y",M84<0,AK84<-Settings!$B$13),"Long unwinding",""),IF(AND(AJ84="Y",M84<0,AK84>Settings!$B$13),"Short buildup","")) | L84: 300.6 | M84: -0.86 | N84: 966 | O84: None | P84: None | Q84: 56.19 | R84: 42.79 | S84: 1.27 | T84: 1.1 | U84: 0.8 | V84: 0.62 | W84: 2 | Y84: None | Z84: 48.85 | AA84: 0.88 | AB84: 0.89 | AC84: 1.1 | AD84: 0.98 | AE84: 0.73 | AF84: 1.05 | AG84: Normal | AH84: 0 | AI84: 0 | AJ84: Y | AK84: 1.8 | AL84: Short buildup | AM84: 143 | AN84: None | AO84: 0 | AP84: 0.79 | AQ84: 48 | AR84: Y | AS84: 2.69 | AT84: =IF(AND(P84="52-wk high",T84>=Settings!$B$7),"Y","N") | AU84: =IF(AND(AD84>=Settings!$B$8,M84>0),"Y","N") | AV84: =IF(OR(AH84>Settings!$B$9,AI84>Settings!$B$9),"Y","N") | AW84: =IF(AJ84<>"Y","n/a",IF(AND(M84>0,AK84>Settings!$B$10),"Y","N")) | AX84: =IF(AO84>=Settings!$B$11,"Y","N") | AY84: =(AT84="Y")+(AU84="Y")+(AV84="Y")+(AW84="Y")+(AX84="Y") | AZ84: =IF(AY84=0,"None",_xlfn.TEXTJOIN(", ",TRUE(),IF(AT84="Y","Breakout",""),IF(AU84="Y","Accumulation",""),IF(AV84="Y","Institutional buying",""),IF(AW84="Y","Long buildup",""),IF(AX84="Y","Momentum leader",""))) | BA84: =IF(BW84="","","Passes "&AY84&" of 5 buy-side scans"&IF(G84="Y","; RED FLAG: filter out using Red flag column","")) | BB84: None | BC84: N | BF84: =IF(R84*100000>=Settings!$B$5,"Y","N") | BG84: =IF(F84>Settings!$B$6,"Y","N") | BH84: -23.25 | BI84: -2.12 | BJ84: -5.37 | BK84: -1.18 | BL84: 6.88 | BM84: -11.51 | BN84: -2.29 | BO84: -3.13 | BP84: -3.84 | BQ84: -5.78 | BR84: Stacked down | BS84: None | BT84: 38.7 | BU84: N | BV84: =IF(OR(BF84<>"Y",BG84<>"Y"),"",(AND(ISNUMBER(BQ84),BQ84>0))+(BR84="Stacked up")+(AND(ISNUMBER(BH84),BH84>=-Settings!$B$17))+(AND(ISNUMBER(BK84),ISNUMBER(BM84),BK84>0,BM84>0))+(AND(ISNUMBER(AQ84),AQ84>=Settings!$B$18))+(AND(ISNUMBER(BT84),BT84>=Settings!$B$19,BT84<=Settings!$B$20))+(AND(ISNUMBER(AS84),AS84>0))+(AND(ISNUMBER(T84),ISNUMBER(M84),T84>=Settings!$B$21,M84>0))+(AND(ISNUMBER(AD84),ISNUMBER(M84),AD84>=Settings!$B$22,M84>0))+(AY84>=1)) | BW84: =IF(OR(AY84=0,BF84<>"Y",BG84<>"Y"),"",1+SUMPRODUCT(($A$6:$A$2604=A84)*($AY$6:$AY$2604>0)*($BF$6:$BF$2604="Y")*($BG$6:$BG$2604="Y")*(($AY$6:$AY$2604>AY84)+($AY$6:$AY$2604=AY84)*($AD$6:$AD$2604>AD84))))
